Workbook
Name \g: #REF!
Name \g: #REF!
Name \g: #REF!
Name \g: #REF!
Name \g: #REF!
Name ___________MES3: [1]DATOS!#REF!
Name ___________MES3: [1]DATOS!#REF!
Name ___________MES3: [1]DATOS!#REF!
Name ___________MES3: [1]DATOS!#REF!
Name ___________MES3: [1]DATOS!#REF!
Name ___________MES3: [1]DATOS!#REF!
Name ___________MES3: [1]DATOS!#REF!
Name __________MES3: [1]DATOS!#REF!
Name __________MES3: [1]DATOS!#REF!
Name __________MES3: [1]DATOS!#REF!
Name __________MES3: [1]DATOS!#REF!
Name __________MES3: [1]DATOS!#REF!
Name __________MES3: [1]DATOS!#REF!
Name __________MES3: [1]DATOS!#REF!
Name ________MES3: [1]DATOS!#REF!
Name ________MES3: [1]DATOS!#REF!
Name ________MES3: [1]DATOS!#REF!
Name ________MES3: [1]DATOS!#REF!
Name ________MES3: [1]DATOS!#REF!
Name ________MES3: [1]DATOS!#REF!
Name ________MES3: [1]DATOS!#REF!
Name _______MES3: [1]DATOS!#REF!
Name _______MES3: [1]DATOS!#REF!
Name _______MES3: [1]DATOS!#REF!
Name _______MES3: [1]DATOS!#REF!
Name _______MES3: [1]DATOS!#REF!
Name _______MES3: [1]DATOS!#REF!
Name _______MES3: [1]DATOS!#REF!
Name ______MES3: [1]DATOS!#REF!
Name _____MES1: [15]DATOS!$C$22
Name _____MES2: [1]DATOS!$C$24
Name ____MES1: [1]DATOS!$C$23
Name ____MES2: [1]DATOS!$C$24
Name ___LAS1: #REF!
Name ___LAS2: #REF!
Name ___MES1: [1]DATOS!$C$23
Name ___MES2: [1]DATOS!$C$24
Name ___MES3: [16]DATOS!$C$22
Name ___VMV1: #REF!
Name ___VMV2: #REF!
Name __LAS1: #REF!
Name __LAS2: #REF!
Name __MES1: [1]DATOS!$C$23
Name __MES2: [1]DATOS!$C$24
Name __MES3: [1]DATOS!#REF!
Name __MES3: [1]DATOS!#REF!
Name __MES3: [1]DATOS!#REF!
Name __MES3: [1]DATOS!#REF!
Name __MES3: [1]DATOS!#REF!
Name __MES3: [16]DATOS!$C$22
Name __VMV1: #REF!
Name __VMV2: #REF!
Name _LAS1: #REF!
Name _LAS2: #REF!
Name _MES1: [1]DATOS!$C$23

Sheet res %
A1: CUADRO DE CONTROL DE AVANCE DE METAS
A2: ITEM | B2: DESCRIPCION | C2: UND | D2: TOTAL | E2: ANTERIOR | G2: ACTUAL % | H2: ACUMULADO % | J2: SALDO
A3: =#REF! -> #REF! | B3: =#REF! -> #REF! | C3: GLB | G3: =+#REF! -> #REF! | H3: =#REF! -> #REF!
A4: 02 | B4: =+#REF! -> #REF! | C4: GLB | G4: =+#REF! -> #REF! | H4: =+#REF! -> #REF! | N4: 981176263
A5: 03 | B5: =#REF! -> #REF! | C5: GLB | G5: =+#REF! -> #REF! | H5: =+#REF! -> #REF! | I5: =#REF! -> #REF! | J5: =#REF! -> #REF! | K5: =#REF! -> #REF!
A6: 04 | B6: =#REF! -> #REF! | C6: GLB
A7: 05 | B7: =#REF! -> #REF! | C7: GLB
A8: 06 | B8: =#REF! -> #REF! | C8: GLB
A9: 07 | B9: =#REF! -> #REF! | C9: GLB | G9: =+#REF! -> #REF! | H9: =+#REF! -> #REF!
A10: 08 | B10: =#REF! -> #REF! | C10: GLB | G10: =+#REF! -> #REF! | H10: =+#REF! -> #REF!
A11: 09 | B11: =#REF! -> #REF! | C11: GLB | G11: =+#REF! -> #REF! | H11: =+#REF! -> #REF!
A12: 10 | B12: =#REF! -> #REF! | C12: GLB | G12: =+#REF! -> #REF! | H12: =+#REF! -> #REF!
A13: COSTO DIRECTO | D13: =SUM(#REF!) -> #REF! | F13: =SUM(#REF!) -> #REF! | G13: =+#REF! -> #REF! | H13: =+#REF! -> #REF! | I13: =SUM(#REF!) -> #REF! | K13: =SUM(#REF!) -> #REF! | L13: =+K13+I13 -> #REF!
L14: =+K14+I14 -> 0
A15: GASTOS GENERALES | D15: =ROUND(D13*#REF!,2) -> #REF! | F15: =ROUND(F13*#REF!,2) -> #REF! | I15: =ROUND(I13*#REF!,2) -> #REF! | K15: =ROUND(K13*#REF!,2) -> #REF! | L15: =+K15+I15 -> #REF!
L16: =+K16+I16 -> 0
A17: UTILIDADES | D17: =ROUND(D13*#REF!,2) -> #REF! | F17: =ROUND(F13*#REF!,2) -> #REF! | I17: =ROUND(I13*#REF!,2) -> #REF! | K17: =ROUND(K13*#REF!,2) -> #REF! | L17: =+K17+I17 -> #REF!
L18: =+K18+I18 -> 0
A19: SUB TOTAL | D19: =D13+D15+D17 -> #REF! | F19: =F13+F15+F17 -> #REF! | I19: =I13+I15+I17 -> #REF! | K19: =K13+K15+K17 -> #REF! | L19: =+K19+I19 -> #REF!
L20: =+K20+I20 -> 0
A21: FACTOR DE RELACIÓN | D21: =#REF!*D19 -> #REF! | F21: =ROUND(F19*#REF!,2) -> #REF! | I21: =ROUND(I19*#REF!,2) -> #REF! | K21: =ROUND(K19*#REF!,2) -> #REF! | L21: =+K21+I21 -> #REF!
K22: =+D22-I22 -> 0 | L22: =+K22+I22 -> 0
A23: I.G.V. | D23: =ROUND(D19*#REF!,2)-0.01 -> #REF! | F23: =ROUND(F21*#REF!,2) -> #REF! | I23: =ROUND(I21*#REF!,2) -> #REF! | K23: =ROUND(K21*#REF!,2)-0.01 -> #REF! | L23: =+K23+I23 -> #REF!
L24: =+K24+I24 -> 0
A25: VALORIZACION DE OBRA | D25: =D21+D23 -> #REF! | F25: =F23+F21 -> #REF! | I25: =I21+I23 -> #REF! | K25: =K21+K23 -> #REF! | L25: =+K25+I25 -> #REF!
L26: =+K26+I26 -> 0
A27: PORCENTAJE | D27: 1 | F27: =F25/D25 -> #REF! | K27: =+K25/D25 -> #REF! | L27: =+K27+H13 -> #REF!
L28: =+K28+I28 -> 0

Sheet FT
C2: FICHA TÉCNICA DEL PROYECTO
C3: A. DATOS GENERALES
C4: Entidad | D4: : | E4: MUNICIPALIDAD DISTRITAL DE PILLCO MARCA
C5: Obra | D5: : | E5: "MEJORAMIENTO Y AMPLIACIÓN DE LOS SERVICIOS DE TRANSITABILIDAD VEHICULAR Y PEATONAL DEL JR LOS PINOS Y JR LOS CEDROS EN CAYHUAYNA Y CAYHUAYNA DEL DISTRITO DE PILLCO MARCA - PROVINCIA DE HUÁNUCO - DEPARTAMENTO DE HUÁNUCO" con CUI N°2536252
C6: Código único de inversión | D6: : | E6: 2536252
C7: Aprobación del expediente técnico | D7: : | E7: RESOLUCIÓN DE GERENCIA N°125-2026-MDPM/GM
C8: Fecha de aprobación de expediente técnico | E8: 46120
C9: Fecha de presupuesto base | D9: : | E9: 46485
C10: Ubicación | D10: : | E10: DEPARTAMENTO: HUÁNUCO
E11: PROVINCIA: HUÁNUCO
E12: DISTRITO: PILLCO MARCA
E13: LOCALIDAD: CAYHUAYNA
C14: B. DEL CONTRATISTA EJECUTOR
C15: Ejecutor | D15: : | E15: CONSORCIO EJECUTOR LOS PINOS
C16: Representante común legal | D16: : | E16: SR. CALLUPE JARA KENEDY ISAAC
C17: Domicilio legal | D17: : | E17: BARRIO USHNOPATA N° S/N CP MENOR HUANCACHUPA -PILLCO MARCA -HUÁNUCO
C18: Proceso de selección | D18: : | E18: LICITACION PÚBLICA ABREVIADA DE OBRAS N°04-2026-MDPM/C-1
C19: Adjudicación de buena pro | D19: : | E19: 46175
C20: Contrato | D20: : | E20: CONTRATO DE EJECUCIÓN DE OBRA N°004-2026-MDPM/GM
C21: Fecha de firma del contrato | D21: : | E21: 46192
C22: Modalidad de ejecución | D22: : | E22: ADMINISTRACIÓN INDIRECTA - CONTRATA
C23: Sistema de contratación | D23: : | E23: PRECIOS UNITARIOS
C24: Valor referencial (con IGV) | D24: : | E24: 638827.47
C25: Monto del contrato principal (incl. IGV) | D25: : | E25: 638827.47
C26: Monto del contrato vigente (incl. IGV) | D26: : | E26: =+E25 -> 638827.47
C27: Adelanto directo otorgado | D27: : | E27: NO SE OTORGÓ ADELANTO
C28: Fecha efectiva del adelanto directo | D28: : | E28: -
C29: Adelanto de materiales otorgado | D29: : | E29: NO SE OTORGÓ ADELANTO
C30: Fecha efectiva del adelanto de materiales | D30: : | E30: -
C31: Plazo de ejecución contractual | D31: : | E31: SESENTA (60) DÍAS CALENDARIOS
C32: Residente de obra | D32: : | E32: ING. RAMIREZ BLANCO GABRIEL AUGUSTO HERMOGENES
C33: C. DE LA SUPERVISIÓN
C34: Contratista | D34: : | E34: PROYECTA PCL S.A.C
C35: Ruc N° | D35: : | E35: 20607943355
C36: Representante legal | D36: : | E36: SR. JOSÉ EDUARDO NIEVES CUADROS (DNI N°47768125)
C37: Domicilio legal | D37: : | E37: JR. BOLÍVAR HUÁNUCO - HUÁNUCO - HUÁNUCO
C38: Proceso de selección | D38: : | E38: CONTRATO MENOR
C39: Fecha de cuantía de contratación | D39: : | E39: 46195
C40: Contrato | D40: : | E40: CONTRATO DE CONSULTORÍA DE OBRA N°010-2026-MDPM/GM
C41: Fecha de firma del contrato | D41: : | E41: 46205
C42: Valor referencial (incl. IGV) | D42: : | E42: 41200
C43: Monto del contrato original (incl. IGV) | D43: : | E43: 41200
C44: Monto del contrato vigente (incl. IGV) | D44: : | E44: =+E43 -> 41200
C45: Plazo de prestación del servicio | D45: : | E45: NOVENTA (90) DÍAS CALENDARIOS
C46: Supervisor de obra | D46: : | E46: ING. CESAR RICARDO ZELADA RODRIGUEZ (CIP N° 98469)
C47: D. DE LOS PLAZOS DE EJECUCIÓN
C48: Fecha de entrega de terreno | D48: : | E48: 46193
C49: Fecha de inicio de ejecución de obra | D49: : | E49: 46193
C50: Plazo de ejecución | D50: : | E50: 60
C51: Fecha de término programado | D51: : | E51: =+E49+E50-1 -> 46252
C52: Ampliaciones de plazo | D52: : | E52: -
C53: Suspensiones de plazo | D53: : | E53: -
C54: Fecha de término real | D54: : | E54: -
C55: E. ESTADO SITUACIONAL DE LA OBRA
C56: Forma de valorización | D56: : | E56: MENSUAL
C57: Situación de la obra | D57: : | E57: EN EJECUCIÓN
C58: Avance físico acumulado programado | D58: : | E58: =+'CONTROL GEN. AVAN. OBRA.'!L14 -> 0.565
C59: Avance físico acumulado ejecutado | D59: : | E59: =+'CONTROL GEN. AVAN. OBRA.'!N14 -> 0.9782
C60: Situación del avance físico | D60: : | E60: ADELANTADA EN 41.32%

Sheet PRESUPUESTO
B1: PRESUPUESTO DE OBRA
B2: =+FT!E20 -> CONTRATO DE EJECUCIÓN DE OBRA N°004-2026-MDPM/GM
B3: Obra: | C3: =+FT!E5 -> "MEJORAMIENTO Y AMPLIACIÓN DE LOS SERVICIOS DE TRANSITABILIDAD VEHICULAR Y PEATONAL DEL JR LOS PINOS Y JR LOS CEDROS EN CAYHUAYNA Y CAYHUAYNA DEL DISTRITO DE PILLCO MARCA - PROVINCIA DE HUÁNUCO - DEPARTAMENTO DE HUÁNUCO" con CUI N°2536252
B4: Entidad: | C4: =+FT!$E$4 -> MUNICIPALIDAD DISTRITAL DE PILLCO MARCA
B5: Ejecutor: | C5: =+FT!$E$15 -> CONSORCIO EJECUTOR LOS PINOS
B6: Supervisor: | C6: =+FT!$E$34 -> PROYECTA PCL S.A.C
B7: Residente: | C7: =+FT!$E$32 -> ING. RAMIREZ BLANCO GABRIEL AUGUSTO HERMOGENES
B8: Ing. Supervisor: | C8: =+FT!$E$46 -> ING. CESAR RICARDO ZELADA RODRIGUEZ (CIP N° 98469)
B10: ITEM | C10: DESCRIPCION | D10: PRESUPUESTO DE OBRA
D11: UND | E11: METRADO | F11: P.UND | G11: TOTAL
B12: 01 | C12: CREACION DE PISTAS Y VEREDAS JR LOS CEDROS
B13: 01.01 | C13: OBRAS PROVISIONALES Y TRABAJOS PRELIMINARES
B14: 01.01.01 | C14: OBRAS PROVISIONALES
B15: 01.01.01.01 | C15: ALQUILER DE ALAMACEN, OFICINA Y CASETA DE GUARDIANIA | D15: mes | E15: 2 | F15: 2400 | G15: =ROUND(E15*F15,2) -> 4800
B16: 01.01.01.02 | C16: CARTEL DE IDENTIFICACION DE LA OBRA DE 3.60 x 4.80 m (SOPORTE DE MADERA) | D16: und | E16: 1 | F16: 1205.49 | G16: =ROUND(E16*F16,2) -> 1205.49
B17: 01.01.01.03 | C17: ALQUILER DE BAÑOS PORTATILES Y LAVADERO | D17: mes | E17: 2 | F17: 850 | G17: =ROUND(E17*F17,2) -> 1700
B18: 01.01.02 | C18: TRABAJOS PRELIMINARES | G18: =ROUND(E18*F18,2) -> 0
B19: 01.01.02.01 | C19: LIMPIEZA DE TERRENO MANUAL | D19: m2 | E19: 1932.21 | F19: 1.06 | G19: =ROUND(E19*F19,2) -> 2048.14
B20: 01.01.02.02 | C20: TRAZO Y REPLANTEO EN TERRENO NORMAL | D20: m2 | E20: 1932.21 | F20: 4.32 | G20: =ROUND(E20*F20,2) -> 8347.15
B21: 01.01.02.03 | C21: MOVILIZACION Y DESMOVILIZACIÓN DE MAQUINARIA Y EQUIPO | D21: GLB | E21: 1 | F21: 2500 | G21: =ROUND(E21*F21,2) -> 2500
B22: 01.01.03 | C22: DEMOLICIONES | G22: =ROUND(E22*F22,2) -> 0
B23: 01.01.03.01 | C23: DEMOLICION DE VEREDAS EXISTENTES DE 0.10M | D23: m2 | E23: 135.5 | F23: 21.33 | G23: =ROUND(E23*F23,2) -> 2890.22
B24: 01.01.03.02 | C24: ELIMINACION DE MATERIAL EXCEDENTE C/VOLQUETE DE 15M3 (D=10 KM) | D24: m3 | E24: 20.33 | F24: 18.98 | G24: =ROUND(E24*F24,2) -> 385.86
B25: 01.01.04 | C25: PLAN DE DESVIO VEHICULAR
B26: 01.01.04.01 | C26: TRANQUERAS DE MADERA 2.40 x 1.20 | D26: und | E26: 2 | F26: 221.35 | G26: =ROUND(E26*F26,2) -> 442.7
B27: 01.01.04.02 | C27: SEÑALIZACION DE DESVIO DE TRANSITO EN PERIODO DE CONSTRUCCION | D27: GLB | E27: 1 | F27: 221.16 | G27: =ROUND(E27*F27,2) -> 221.16
B28: 01.02 | C28: PAVIMENTO RIGIDO | G28: =ROUND(E28*F28,2) -> 0
B29: 01.02.01 | C29: MOVIMIENTO DE TIERRAS HASTA EL NIVEL DE SUB - RASANTE
B30: 01.02.01.01 | C30: CORTE EN TERRENO NORMAL CON MAQUINARIA | D30: m3 | E30: 590.54 | F30: 10.47 | G30: =ROUND(E30*F30,2) -> 6182.95
B31: 01.02.01.02 | C31: RELLENO COMPACTACION CON MATERIAL PROPIO SELECCIONADO | D31: m3 | E31: 51.64 | F31: 19.04 | G31: =ROUND(E31*F31,2) -> 983.23
B32: 01.02.01.03 | C32: ELIMINACION DE MATERIAL EXCEDENTE C/VOLQUETE DE 15M3 (D=10KM) | D32: m3 | E32: 738.18 | F32: 18.98 | G32: =ROUND(E32*F32,2) -> 14010.66
B33: 01.02.02 | C33: BASE | G33: =ROUND(E33*F33,2) -> 0
B34: 01.02.02.01 | C34: CONFORMACION DE BASE MATERIAL MEZCLADO E=0.20m | D34: m2 | E34: 910.14 | F34: 31.15 | G34: =ROUND(E34*F34,2) -> 28350.86
B35: 01.02.03 | C35: SUB RASANTE | G35: =ROUND(E35*F35,2) -> 0
B36: 01.02.03.01 | C36: PERFILADO, RIEGO Y COMPACTACIÓN DE SUBRASANTE | D36: m2 | E36: 910.14 | F36: 5.54 | G36: =ROUND(E36*F36,2) -> 5042.18
B37: 01.02.04 | C37: OBRAS DE CONCRETO | G37: =ROUND(E37*F37,2) -> 0
B38: 01.02.04.01 | C38: ENCOFRADO Y DESENCOFRADO EN PAVIMENTOS | D38: m2 | E38: 127.29 | F38: 63.41 | G38: =ROUND(E38*F38,2) -> 8071.46
B39: 01.02.04.02 | C39: CONCRETO F'C =210 KG/CM2 EN VIA E=15CM | D39: m2 | E39: 910.14 | F39: 119.99 | G39: =ROUND(E39*F39,2) -> 109207.7
B40: 01.02.04.03 | C40: CURADO DE CONCRETO | D40: m2 | E40: 910.14 | F40: 2.92 | G40: =ROUND(E40*F40,2) -> 2657.61
B41: 01.02.04.04 | C41: ACERO FY = 4200Kg/cm2 EN JUNTAS DE DILATACION LONGITUDINAL Ø 3/8" | D41: kg | E41: 80.64 | F41: 12.14 | G41: =ROUND(E41*F41,2) -> 978.97
B42: 01.02.04.05 | C42: ACERO FY = 2400Kg/cm2 GRADO 60 EN JUNTAS DE DILATACION TRANSVERSAL Ø 3/4" | D42: kg | E42: 176.4 | F42: 42.88 | G42: =ROUND(E42*F42,2) -> 7564.03
B43: 01.02.04.06 | C43: JUNTA DE AISLAMIENTO e=1" X 0.20 m | D43: m | E43: 360 | F43: 5.59 | G43: =ROUND(E43*F43,2) -> 2012.4
B44: 01.02.04.07 | C44: JUNTA DE DILATACION e=1" X 0.10 m | D44: m | E44: 255 | F44: 5.59 | G44: =ROUND(E44*F44,2) -> 1425.45
B45: 01.02.04.08 | C45: JUNTAS DE CONTRACCION CON ELASTOMERICO DE POLIURETANO E=1/2" X 0.10m | D45: m | E45: 150 | F45: 19.22 | G45: =ROUND(E45*F45,2) -> 2883
B46: 01.02.05 | C46: NIVELACION DE BUZONES | G46: =ROUND(E46*F46,2) -> 0
B47: 01.02.05.01 | C47: NIVELACION DE BUZONES EN GENERAL | D47: und | E47: 3 | F47: 471.14 | G47: =ROUND(E47*F47,2) -> 1413.42
B48: 01.02.06 | C48: SEÑALIZACION | G48: =ROUND(E48*F48,2) -> 0
B49: 01.02.06.01 | C49: PINTURA EN PAVIMENTO (SIMBOLO Y LETRA) | D49: m2 | E49: 50.6 | F49: 38.21 | G49: =ROUND(E49*F49,2) -> 1933.43
B50: 01.02.06.02 | C50: PINTURA DE PAVIMENTO (LINEAS DISCONTINUAS CENTRALES) | D50: m | E50: 170 | F50: 10.43 | G50: =ROUND(E50*F50,2) -> 1773.1
B51: 01.02.06.03 | C51: SEÑALIZACION VERTICAL | D51: und | E51: 4 | F51: 361.47 | G51: =ROUND(E51*F51,2) -> 1445.88
B52: 01.03 | C52: VEREDAS, RAMPAS Y MARTILLOS | G52: =ROUND(E52*F52,2) -> 0
B53: 01.03.01 | C53: MOVIMIENTO DE TIERRAS HASTA EL NIVEL DE SUB - RASANTE
B54: 01.03.01.01 | C54: EXCAVACION EN TERRENO NORMAL C/MAQUINARIA LIVIANA | D54: m3 | E54: 56.3 | F54: 22.11 | G54: =ROUND(E54*F54,2) -> 1244.79
B55: 01.03.01.02 | C55: RELLENO Y COMPACTACION CON MATERIAL PROPIO SELECCIONADO | D55: m3 | E55: 12 | F55: 42.31 | G55: =ROUND(E55*F55,2) -> 507.72
B56: 01.03.01.03 | C56: ELIMINACION DE MATERIAL EXCEDENTE C/VOLQUETE DE 15M3 (D=10KM) | D56: m3 | E56: 55.38 | F56: 18.98 | G56: =ROUND(E56*F56,2) -> 1051.11
B57: 01.03.01.04 | C57: PERFILADO Y COMPACTADO CON PLANCHA | D57: m2 | E57: 547.38 | F57: 4.25 | G57: =ROUND(E57*F57,2) -> 2326.37
B58: 01.03.01.05 | C58: CONFORMACIÓN Y COMPACTACIÓN DE BASE EN VEREDAS Y RAMPAS (e=10cm) | D58: m2 | E58: 547.38 | F58: 16.02 | G58: =ROUND(E58*F58,2) -> 8769.03
B59: 01.03.02 | C59: OBRAS DE CONCRETO EN VEREDAS | G59: =ROUND(E59*F59,2) -> 0
B60: 01.03.02.01 | C60: ENCOFRADO Y DESENCOFRADO EN VEREDAS | D60: m2 | E60: 55.28 | F60: 72.37 | G60: =ROUND(E60*F60,2) -> 4000.61
B61: 01.03.02.02 | C61: CONCRETO F'c=175 kg/cm2 (E=4") EN VEREDA CON ACABADO FROTACHADO Y BRUÑADO S/DISEÑO | D61: m2 | E61: 547.38 | F61: 49.11 | G61: =ROUND(E61*F61,2) -> 26881.83
B62: 01.03.02.03 | C62: CONCRETO F'c=175 kg/cm2 PARA UÑA EN VEREDA (A=0.025 m2) | D62: m | E62: 404 | F62: 16.32 | G62: =ROUND(E62*F62,2) -> 6593.28
B63: 01.03.02.04 | C63: CURADO DE CONCRETO | E63: 547.38 | F63: 2.92 | G63: =ROUND(E63*F63,2) -> 1598.35
B64: 01.03.02.05 | C64: JUNTA ASFALTICA | D64: m | E64: 158.4 | F64: 4.48 | G64: =ROUND(E64*F64,2) -> 709.63
B65: 01.03.03 | C65: OBRAS DE CONCRETO EN RAMPA | G65: =ROUND(E65*F65,2) -> 0
B66: 01.03.03.01 | C66: ENCOFRADO Y DESENCOFRADO EN RAMPAS | D66: m2 | E66: 16.25 | F66: 46.94 | G66: =ROUND(E66*F66,2) -> 762.78
B67: 01.03.03.02 | C67: CONCRETO F'c=175 KG/CM2, ACABADO 1:2 BRUÑADO Y FROTACHADO | D67: m2 | E67: 86.65 | F67: 53.06 | G67: =ROUND(E67*F67,2) -> 4597.65
B68: 01.03.03.03 | C68: CURADO DE CONCRETO EN RAMPA | D68: m2 | E68: 86.65 | F68: 2.92 | G68: =ROUND(E68*F68,2) -> 253.02
B69: 01.03.03.04 | C69: JUNTA ASFALTICA | D69: m | E69: 110 | F69: 4.48 | G69: =ROUND(E69*F69,2) -> 492.8
B70: 01.03.04 | C70: OBRAS DE CONCRETO EN MARTILLO
B71: 01.03.04.01 | C71: CONCRETO F'c=175 KG/CM2, ACABADO FROTACHADO | D71: m2 | E71: 64 | F71: 49.11 | G71: =ROUND(E71*F71,2) -> 3143.04
B72: 01.03.04.02 | C72: ENCOFRADO Y DESENCOFRADO DE MARTILLOS | D72: m2 | E72: 2.8 | F72: 87.93 | G72: =ROUND(E72*F72,2) -> 246.2
B73: 01.03.04.03 | C73: UÑA DE CONCRETO SUMERGIDOF'c=175 kg/cm2A=0.13m | D73: m | E73: 28 | F73: 51.24 | G73: =ROUND(E73*F73,2) -> 1434.72
B74: 01.03.04.04 | C74: CURADO DE CONCRETO | D74: m2 | E74: 64 | F74: 2.92 | G74: =ROUND(E74*F74,2) -> 186.88
B75: 01.03.05 | C75: NIVELACION DE CONEXIONES DOMICILIARIAS
B76: 01.03.05.01 | C76: NIVELACION DE CONEXIONES DOMICILIARIAS DE AGUA | D76: und | E76: 32 | F76: 202.81 | G76: =ROUND(E76*F76,2) -> 6489.92
B77: 01.03.05.02 | C77: NIVELACION DE CONEXIONES DOMICILIARIAS DE DESAGUE | D77: und | E77: 32 | F77: 312.41 | G77: =ROUND(E77*F77,2) -> 9997.12
B78: 01.04 | C78: CUNETA PLUVIAL
B79: 01.04.01 | C79: MOVIMIENTO DE TIERRAS HASTA NIVEL DE SUB-RAZANTE
B80: 01.04.01.01 | C80: EXCAVACION EN TERRENO NORMAL | D80: m3 | E80: 43.2 | F80: 56.41 | G80: =ROUND(E80*F80,2) -> 2436.91
B81: 01.04.01.02 | C81: RELLENO COMPACTADO CON MATERIAL PROPIO | D81: m3 | E81: 5.5 | F81: 42.31 | G81: =ROUND(E81*F81,2) -> 232.71
B82: 01.04.01.03 | C82: ACARREO DE MATERIAL EXCEDENTE HASTA 30 M | D82: m3 | E82: 47.13 | F82: 28.21 | G82: =ROUND(E82*F82,2) -> 1329.54
B83: 01.04.01.04 | C83: ELIMINACION DE MATERIAL EXCEDENTE C/VOLQUETE DE 15M3 (D=10KM) | D83: m3 | E83: 47.13 | F83: 18.98 | G83: =ROUND(E83*F83,2) -> 894.53
B84: 01.04.01.05 | C84: CONFORMACIÓN Y COMPACTACIÓN SUBRASANTE C/PLANCHA | D84: m2 | E84: 115.95 | F84: 4.25 | G84: =ROUND(E84*F84,2) -> 492.79
B85: 01.04.02 | C85: OBRAS DE CONCRETO SIMPLE EN CUNETAS
B86: 01.04.02.01 | C86: ENCOFRADO Y DESENCOFRADO EN CUNETA TRIANGULAR | D86: m2 | E86: 5.76 | F86: 34.68 | G86: =ROUND(E86*F86,2) -> 199.76
B87: 01.04.02.02 | C87: CONCRETO F'C =175 KG/CM2 EN CUNETA TRIANGULAR | D87: m | E87: 386 | F87: 40.96 | G87: =ROUND(E87*F87,2) -> 15810.56
B88: 01.04.02.03 | C88: CURADO DE CONCRETO TRIANGULAR | D88: m2 | E88: 115.8 | F88: 5.86 | G88: =ROUND(E88*F88,2) -> 678.59
B89: 01.04.02.04 | C89: JUNTA TRANSVERSAL DE DILATACION e=20mm | D89: m | E89: 38.5 | F89: 5.44 | G89: =ROUND(E89*F89,2) -> 209.44
B90: 01.05 | C90: SARDINELES DE CONCRETO
B91: 01.05.01 | C91: MOVIMIENTO DE TIERRAS HASTA NIVEL DE SUB RAZANTE
B92: 01.05.01.01 | C92: EXCAVACION EN TERRENO NORMAL | D92: m3 | E92: 9 | F92: 56.41 | G92: =ROUND(E92*F92,2) -> 507.69
B93: 01.05.01.02 | C93: RELLENO COMPACTACION CON MATERIAL PROPIO SELECCIONADO | D93: m3 | E93: 10.75 | F93: 19.04 | G93: =ROUND(E93*F93,2) -> 204.68
B94: 01.05.01.03 | C94: ACARREO DE MATERIAL EXCEDENTE HASTA 30 M | D94: m3 | E94: 8.75 | F94: 28.21 | G94: =ROUND(E94*F94,2) -> 246.84
B95: 01.05.01.04 | C95: ELIMINACION DE MATERIAL EXCEDENTE C/VOLQUETE DE 15M3 (D=10KM) | D95: m3 | E95: 8.75 | F95: 18.98 | G95: =ROUND(E95*F95,2) -> 166.08
B96: 01.05.02 | C96: OBRAS DE CONCRETO EN SARDINEL ARMADO
B97: 01.05.02.01 | C97: ACERO CORRUGADO F'Y=4200 KG/CM2 GRADO 60 | D97: kg | E97: 653.8 | F97: 7.85 | G97: =ROUND(E97*F97,2) -> 5132.33
B98: 01.05.02.02 | C98: ENCOFRADO Y DESENCOFRADO EN SARDINELES | D98: m2 | E98: 251.02 | F98: 73.97 | G98: =ROUND(E98*F98,2) -> 18567.95
B99: 01.05.02.03 | C99: CONCRETO F'C=175 KG/CM2 PARA SARDINEL (b=0.15m , h=0.40m) ACABADO SOLAQUEADO | D99: m3 | E99: 32.94 | F99: 477.23 | G99: =ROUND(E99*F99,2) -> 15719.96
B100: 01.05.02.04 | C100: CURADO DE CONCRETO | D100: m2 | E100: 219.61 | F100: 2.92 | G100: =ROUND(E100*F100,2) -> 641.26
B101: 01.05.02.05 | C101: JUNTA ASFALTICA | D101: m | E101: 6 | F101: 4.48 | G101: =ROUND(E101*F101,2) -> 26.88
...

Sheet CALEN. PROG.
B1: CALENDARIO DE AVANCE DE OBRA VALORIZADO PROGRAMADO ADECUADO AL INICIO DE LA OBRA
B2: Obra: | C2: =+FT!$E$5 -> "MEJORAMIENTO Y AMPLIACIÓN DE LOS SERVICIOS DE TRANSITABILIDAD VEHICULAR Y PEATONAL DEL JR LOS PINOS Y JR LOS CEDROS EN CAYHUAYNA Y CAYHUAYNA DEL DISTRITO DE PILLCO MARCA - PROVINCIA DE HUÁNUCO - DEPARTAMENTO DE HUÁNUCO" con CUI N°2536252
B3: Entidad: | C3: =+FT!$E$4 -> MUNICIPALIDAD DISTRITAL DE PILLCO MARCA
B4: Ejecutor: | C4: =+FT!$E$15 -> CONSORCIO EJECUTOR LOS PINOS
B5: Supervisor: | C5: =+FT!$E$34 -> PROYECTA PCL S.A.C | D5: VALOR REFERENCIAL (CON IGV) | G5: =+FT!$E$24 -> 638827.47
B6: Residente: | C6: =+FT!$E$32 -> ING. RAMIREZ BLANCO GABRIEL AUGUSTO HERMOGENES | D6: MONTO DEL CONTRATO (INCL. IGV): | G6: =+FT!$E$25 -> 638827.47
B7: Ing. Supervisor: | C7: =+FT!$E$46 -> ING. CESAR RICARDO ZELADA RODRIGUEZ (CIP N° 98469) | D7: PLAZO DE EJECUCIÓN: | G7: =+FT!$E$31 -> SESENTA (60) DÍAS CALENDARIOS
B9: ITEM | C9: DESCRIPCION | D9: PRESUPUESTO DE OBRA | I9: 46174 | L9: 46204 | O9: 46235
I10: 46193 | J10: 46203 | L10: 46204 | M10: 46234 | O10: 46235 | P10: 46253
D11: UND | E11: METRADO | F11: P.UND | G11: TOTAL | I11: PORCEN. (%) | J11: COSTO (S/) | L11: PORCEN. (%) | M11: COSTO (S/) | O11: PORCEN. (%) | P11: COSTO (S/)
B12: 01 | C12: CREACION DE PISTAS Y VEREDAS JR LOS CEDROS
B13: 01.01 | C13: OBRAS PROVISIONALES Y TRABAJOS PRELIMINARES
B14: 01.01.01 | C14: OBRAS PROVISIONALES
B15: 01.01.01.01 | C15: ALQUILER DE ALAMACEN, OFICINA Y CASETA DE GUARDIANIA | D15: mes | E15: 2 | F15: 2400 | G15: =ROUND(E15*F15,2) -> 4800 | I15: =ROUND(J15/$G15,4) -> 0.3333 | J15: 1600 | L15: =ROUND(M15/$G15,4) -> 0.3333 | M15: 1600 | O15: =ROUND(P15/$G15,4) -> 0.3333 | P15: 1600
B16: 01.01.01.02 | C16: CARTEL DE IDENTIFICACION DE LA OBRA DE 3.60 x 4.80 m (SOPORTE DE MADERA) | D16: und | E16: 1 | F16: 1205.49 | G16: =ROUND(E16*F16,2) -> 1205.49 | I16: =ROUND(J16/$G16,4) -> 1 | J16: 1205.49 | L16: =ROUND(M16/$G16,4) -> 0 | O16: =ROUND(P16/$G16,4) -> 0
B17: 01.01.01.03 | C17: ALQUILER DE BAÑOS PORTATILES Y LAVADERO | D17: mes | E17: 2 | F17: 850 | G17: =ROUND(E17*F17,2) -> 1700 | I17: =ROUND(J17/$G17,4) -> 0.1833 | J17: 311.66667 | L17: =ROUND(M17/$G17,4) -> 0.5167 | M17: 878.33333 | O17: =ROUND(P17/$G17,4) -> 0.3 | P17: 510
B18: 01.01.02 | C18: TRABAJOS PRELIMINARES | G18: =ROUND(E18*F18,2) -> 0
B19: 01.01.02.01 | C19: LIMPIEZA DE TERRENO MANUAL | D19: m2 | E19: 1932.21 | F19: 1.06 | G19: =ROUND(E19*F19,2) -> 2048.14 | I19: =ROUND(J19/$G19,4) -> 1 | J19: 2048.14 | L19: =ROUND(M19/$G19,4) -> 0 | O19: =ROUND(P19/$G19,4) -> 0
B20: 01.01.02.02 | C20: TRAZO Y REPLANTEO EN TERRENO NORMAL | D20: m2 | E20: 1932.21 | F20: 4.32 | G20: =ROUND(E20*F20,2) -> 8347.15 | I20: =ROUND(J20/$G20,4) -> 0.1046 | J20: 873.44 | L20: =ROUND(M20/$G20,4) -> 0.4539 | M20: 3789.15 | O20: =ROUND(P20/$G20,4) -> 0.4414 | P20: 3684.56
B21: 01.01.02.03 | C21: MOVILIZACION Y DESMOVILIZACION DE MAQUINARIA Y EQUIPO | D21: GLB | E21: 1 | F21: 2500 | G21: =ROUND(E21*F21,2) -> 2500 | I21: =ROUND(J21/$G21,4) -> 1 | J21: 2500 | L21: =ROUND(M21/$G21,4) -> 0 | O21: =ROUND(P21/$G21,4) -> 0
B22: 01.01.03 | C22: DEMOLICIONES | G22: =ROUND(E22*F22,2) -> 0
B23: 01.01.03.01 | C23: DEMOLICION DE VEREDAS EXISTENTES DE 0.10M | D23: m2 | E23: 135.5 | F23: 21.33 | G23: =ROUND(E23*F23,2) -> 2890.22 | I23: =ROUND(J23/$G23,4) -> 1 | J23: 2890.22 | L23: =ROUND(M23/$G23,4) -> 0 | O23: =ROUND(P23/$G23,4) -> 0
B24: 01.01.03.02 | C24: ELIMINACION DE MATERIAL EXCEDENTE C/VOLQUETE DE 15M3 (D=10 KM) | D24: m3 | E24: 20.33 | F24: 18.98 | G24: =ROUND(E24*F24,2) -> 385.86 | I24: =ROUND(J24/$G24,4) -> 1 | J24: 385.86 | L24: =ROUND(M24/$G24,4) -> 0 | O24: =ROUND(P24/$G24,4) -> 0
B25: 01.01.04 | C25: PLAN DE DESVIO VEHICULAR
B26: 01.01.04.01 | C26: TRANQUERAS DE MADERA 2.40 x 1.20 | D26: und | E26: 2 | F26: 221.35 | G26: =ROUND(E26*F26,2) -> 442.7 | I26: =ROUND(J26/$G26,4) -> 1 | J26: 442.7 | L26: =ROUND(M26/$G26,4) -> 0 | O26: =ROUND(P26/$G26,4) -> 0
B27: 01.01.04.02 | C27: SEÑALIZACION DE DESVIO DE TRANSITO EN PERIODO DE CONSTRUCCION | D27: GLB | E27: 1 | F27: 221.16 | G27: =ROUND(E27*F27,2) -> 221.16 | I27: =ROUND(J27/$G27,4) -> 1 | J27: 221.16 | L27: =ROUND(M27/$G27,4) -> 0 | O27: =ROUND(P27/$G27,4) -> 0
B28: 01.02 | C28: PAVIMENTO RIGIDO | G28: =ROUND(E28*F28,2) -> 0
B29: 01.02.01 | C29: MOVIMIENTO DE TIERRAS HASTA EL NIVEL DE SUB - RASANTE
B30: 01.02.01.01 | C30: CORTE EN TERRENO NORMAL CON MAQUINARIA | D30: m3 | E30: 590.54 | F30: 10.47 | G30: =ROUND(E30*F30,2) -> 6182.95 | I30: =ROUND(J30/$G30,4) -> 1 | J30: 6182.95 | L30: =ROUND(M30/$G30,4) -> 0 | O30: =ROUND(P30/$G30,4) -> 0
B31: 01.02.01.02 | C31: RELLENO COMPACTACION CON MATERIAL PROPIO SELECCIONADO | D31: m3 | E31: 51.64 | F31: 19.04 | G31: =ROUND(E31*F31,2) -> 983.23 | I31: =ROUND(J31/$G31,4) -> 1 | J31: 983.23 | L31: =ROUND(M31/$G31,4) -> 0 | O31: =ROUND(P31/$G31,4) -> 0
B32: 01.02.01.03 | C32: ELIMINACION DE MATERIAL EXCEDENTE C/VOLQUETE DE 15M3 (D=10KM) | D32: m3 | E32: 738.18 | F32: 18.98 | G32: =ROUND(E32*F32,2) -> 14010.66 | I32: =ROUND(J32/$G32,4) -> 0 | L32: =ROUND(M32/$G32,4) -> 1 | M32: 14010.66 | O32: =ROUND(P32/$G32,4) -> 0
B33: 01.02.02 | C33: BASE | G33: =ROUND(E33*F33,2) -> 0
B34: 01.02.02.01 | C34: CONFORMACION DE BASE MATERIAL MEZCLADO E=0.20m | D34: m2 | E34: 910.14 | F34: 31.15 | G34: =ROUND(E34*F34,2) -> 28350.86 | I34: =ROUND(J34/$G34,4) -> 1 | J34: 28350.86 | L34: =ROUND(M34/$G34,4) -> 0 | O34: =ROUND(P34/$G34,4) -> 0
B35: 01.02.03 | C35: SUB RASANTE | G35: =ROUND(E35*F35,2) -> 0
B36: 01.02.03.01 | C36: PERFILADO, RIEGO Y COMPACTACIÓN DE SUBRASANTE | D36: m2 | E36: 910.14 | F36: 5.54 | G36: =ROUND(E36*F36,2) -> 5042.18 | I36: =ROUND(J36/$G36,4) -> 1 | J36: 5042.18 | L36: =ROUND(M36/$G36,4) -> 0 | O36: =ROUND(P36/$G36,4) -> 0
B37: 01.02.04 | C37: OBRAS DE CONCRETO | G37: =ROUND(E37*F37,2) -> 0
B38: 01.02.04.01 | C38: ENCOFRADO Y DESENCOFRADO EN PAVIMENTOS | D38: m2 | E38: 127.29 | F38: 63.41 | G38: =ROUND(E38*F38,2) -> 8071.46 | I38: =ROUND(J38/$G38,4) -> 1 | J38: 8071.46 | L38: =ROUND(M38/$G38,4) -> 0 | O38: =ROUND(P38/$G38,4) -> 0
B39: 01.02.04.02 | C39: CONCRETO F'C =210 KG/CM2 EN VIA E=15CM | D39: m2 | E39: 910.14 | F39: 119.99 | G39: =ROUND(E39*F39,2) -> 109207.7 | I39: =ROUND(J39/$G39,4) -> 0.0787 | J39: 8593.32 | L39: =ROUND(M39/$G39,4) -> 0.9213 | M39: 100614.38 | O39: =ROUND(P39/$G39,4) -> 0
B40: 01.02.04.03 | C40: CURADO DE CONCRETO | D40: m2 | E40: 910.14 | F40: 2.92 | G40: =ROUND(E40*F40,2) -> 2657.61 | I40: =ROUND(J40/$G40,4) -> 0 | L40: =ROUND(M40/$G40,4) -> 1 | M40: 2657.61 | O40: =ROUND(P40/$G40,4) -> 0
B41: 01.02.04.04 | C41: ACERO FY = 4200Kg/cm2 EN JUNTAS DE DILATACION LONGITUDINAL Ø 3/8" | D41: kg | E41: 80.64 | F41: 12.14 | G41: =ROUND(E41*F41,2) -> 978.97 | I41: =ROUND(J41/$G41,4) -> 1 | J41: 978.97 | L41: =ROUND(M41/$G41,4) -> 0 | O41: =ROUND(P41/$G41,4) -> 0
B42: 01.02.04.05 | C42: ACERO FY = 2400Kg/cm2 GRADO 60 EN JUNTAS DE DILATACION TRANSVERSAL Ø 3/4" | D42: kg | E42: 176.4 | F42: 42.88 | G42: =ROUND(E42*F42,2) -> 7564.03 | I42: =ROUND(J42/$G42,4) -> 1 | J42: 7564.03 | L42: =ROUND(M42/$G42,4) -> 0 | O42: =ROUND(P42/$G42,4) -> 0
B43: 01.02.04.06 | C43: JUNTA DE AISLAMIENTO e=1" X 0.20 m | D43: m | E43: 360 | F43: 5.59 | G43: =ROUND(E43*F43,2) -> 2012.4 | I43: =ROUND(J43/$G43,4) -> 0 | L43: =ROUND(M43/$G43,4) -> 1 | M43: 2012.4 | O43: =ROUND(P43/$G43,4) -> 0
B44: 01.02.04.07 | C44: JUNTA DE DILATACION e=1" X 0.10 m | D44: m | E44: 255 | F44: 5.59 | G44: =ROUND(E44*F44,2) -> 1425.45 | I44: =ROUND(J44/$G44,4) -> 0 | L44: =ROUND(M44/$G44,4) -> 1 | M44: 1425.45 | O44: =ROUND(P44/$G44,4) -> 0
B45: 01.02.04.08 | C45: JUNTAS DE CONTRACCION CON ELASTOMERICO DE POLIURETANO E=1/2" X 0.10m | D45: m | E45: 150 | F45: 19.22 | G45: =ROUND(E45*F45,2) -> 2883 | I45: =ROUND(J45/$G45,4) -> 0 | L45: =ROUND(M45/$G45,4) -> 1 | M45: 2883 | O45: =ROUND(P45/$G45,4) -> 0
B46: 01.02.05 | C46: NIVELACION DE BUZONES | G46: =ROUND(E46*F46,2) -> 0
B47: 01.02.05.01 | C47: NIVELACION DE BUZONES EN GENERAL | D47: und | E47: 3 | F47: 471.14 | G47: =ROUND(E47*F47,2) -> 1413.42 | I47: =ROUND(J47/$G47,4) -> 1 | J47: 1413.42 | L47: =ROUND(M47/$G47,4) -> 0 | O47: =ROUND(P47/$G47,4) -> 0
B48: 01.02.06 | C48: SEÑALIZACION | G48: =ROUND(E48*F48,2) -> 0
B49: 01.02.06.01 | C49: PINTURA EN PAVIMENTO (SIMBOLO Y LETRA) | D49: m2 | E49: 50.6 | F49: 38.21 | G49: =ROUND(E49*F49,2) -> 1933.43 | I49: =ROUND(J49/$G49,4) -> 0 | L49: =ROUND(M49/$G49,4) -> 1 | M49: 1933.43 | O49: =ROUND(P49/$G49,4) -> 0
B50: 01.02.06.02 | C50: PINTURA DE PAVIMENTO (LINEAS DISCONTINUAS CENTRALES) | D50: m | E50: 170 | F50: 10.43 | G50: =ROUND(E50*F50,2) -> 1773.1 | I50: =ROUND(J50/$G50,4) -> 0 | L50: =ROUND(M50/$G50,4) -> 1 | M50: 1773.1 | O50: =ROUND(P50/$G50,4) -> 0
B51: 01.02.06.03 | C51: SEÑALIZACION VERTICAL | D51: und | E51: 4 | F51: 361.47 | G51: =ROUND(E51*F51,2) -> 1445.88 | I51: =ROUND(J51/$G51,4) -> 0 | L51: =ROUND(M51/$G51,4) -> 1 | M51: 1445.88 | O51: =ROUND(P51/$G51,4) -> 0
B52: 01.03 | C52: VEREDAS, RAMPAS Y MARTILLOS | G52: =ROUND(E52*F52,2) -> 0
B53: 01.03.01 | C53: MOVIMIENTO DE TIERRAS HASTA EL NIVEL DE SUB - RASANTE
B54: 01.03.01.01 | C54: EXCAVACION EN TERRENO NORMAL C/MAQUINARIA LIVIANA | D54: m3 | E54: 56.3 | F54: 22.11 | G54: =ROUND(E54*F54,2) -> 1244.79 | I54: =ROUND(J54/$G54,4) -> 0 | L54: =ROUND(M54/$G54,4) -> 1 | M54: 1244.79 | O54: =ROUND(P54/$G54,4) -> 0
B55: 01.03.01.02 | C55: RELLENO Y COMPACTACION CON MATERIAL PROPIO SELECCIONADO | D55: m3 | E55: 12 | F55: 42.31 | G55: =ROUND(E55*F55,2) -> 507.72 | I55: =ROUND(J55/$G55,4) -> 0 | L55: =ROUND(M55/$G55,4) -> 0 | O55: =ROUND(P55/$G55,4) -> 1 | P55: 507.72
B56: 01.03.01.03 | C56: ELIMINACION DE MATERIAL EXCEDENTE C/VOLQUETE DE 15M3 (D=10KM) | D56: m3 | E56: 55.38 | F56: 18.98 | G56: =ROUND(E56*F56,2) -> 1051.11 | I56: =ROUND(J56/$G56,4) -> 0 | L56: =ROUND(M56/$G56,4) -> 0 | O56: =ROUND(P56/$G56,4) -> 1 | P56: 1051.11
B57: 01.03.01.04 | C57: PERFILADO Y COMPACTADO CON PLANCHA | D57: m2 | E57: 547.38 | F57: 4.25 | G57: =ROUND(E57*F57,2) -> 2326.37 | I57: =ROUND(J57/$G57,4) -> 0 | L57: =ROUND(M57/$G57,4) -> 0 | O57: =ROUND(P57/$G57,4) -> 1 | P57: 2326.37
B58: 01.03.01.05 | C58: CONFORMACIÓN Y COMPACTACIÓN DE BASE EN VEREDAS Y RAMPAS (e=10cm) | D58: m2 | E58: 547.38 | F58: 16.02 | G58: =ROUND(E58*F58,2) -> 8769.03 | I58: =ROUND(J58/$G58,4) -> 0 | L58: =ROUND(M58/$G58,4) -> 0 | O58: =ROUND(P58/$G58,4) -> 1 | P58: 8769.03
B59: 01.03.02 | C59: OBRAS DE CONCRETO EN VEREDAS | G59: =ROUND(E59*F59,2) -> 0
B60: 01.03.02.01 | C60: ENCOFRADO Y DESENCOFRADO EN VEREDAS | D60: m2 | E60: 55.28 | F60: 72.37 | G60: =ROUND(E60*F60,2) -> 4000.61 | I60: =ROUND(J60/$G60,4) -> 0 | L60: =ROUND(M60/$G60,4) -> 0 | O60: =ROUND(P60/$G60,4) -> 1 | P60: 4000.61
B61: 01.03.02.02 | C61: CONCRETO F'c=175 kg/cm2 (E=4") EN VEREDA CON ACABADO FROTACHADO Y BRUÑADO S/DISEÑO | D61: m2 | E61: 547.38 | F61: 49.11 | G61: =ROUND(E61*F61,2) -> 26881.83 | I61: =ROUND(J61/$G61,4) -> 0 | L61: =ROUND(M61/$G61,4) -> 0 | O61: =ROUND(P61/$G61,4) -> 1 | P61: 26881.83
B62: 01.03.02.03 | C62: CONCRETO F'c=175 kg/cm2 PARA UÑA EN VEREDA (A=0.025 m2) | D62: m | E62: 404 | F62: 16.32 | G62: =ROUND(E62*F62,2) -> 6593.28 | I62: =ROUND(J62/$G62,4) -> 0 | L62: =ROUND(M62/$G62,4) -> 0 | O62: =ROUND(P62/$G62,4) -> 1 | P62: 6593.28
B63: 01.03.02.04 | C63: CURADO DE CONCRETO | E63: 547.38 | F63: 2.92 | G63: =ROUND(E63*F63,2) -> 1598.35 | I63: =ROUND(J63/$G63,4) -> 0 | L63: =ROUND(M63/$G63,4) -> 0 | O63: =ROUND(P63/$G63,4) -> 1 | P63: 1598.35
B64: 01.03.02.05 | C64: JUNTA ASFALTICA | D64: m | E64: 158.4 | F64: 4.48 | G64: =ROUND(E64*F64,2) -> 709.63 | I64: =ROUND(J64/$G64,4) -> 0 | L64: =ROUND(M64/$G64,4) -> 0 | O64: =ROUND(P64/$G64,4) -> 1 | P64: 709.63
B65: 01.03.03 | C65: OBRAS DE CONCRETO EN RAMPA | G65: =ROUND(E65*F65,2) -> 0
B66: 01.03.03.01 | C66: ENCOFRADO Y DESENCOFRADO EN RAMPAS | D66: m2 | E66: 16.25 | F66: 46.94 | G66: =ROUND(E66*F66,2) -> 762.78 | I66: =ROUND(J66/$G66,4) -> 0 | L66: =ROUND(M66/$G66,4) -> 0 | O66: =ROUND(P66/$G66,4) -> 1 | P66: 762.78
B67: 01.03.03.02 | C67: CONCRETO F'c=175 KG/CM2, ACABADO 1:2 BRUÑADO Y FROTACHADO | D67: m2 | E67: 86.65 | F67: 53.06 | G67: =ROUND(E67*F67,2) -> 4597.65 | I67: =ROUND(J67/$G67,4) -> 0 | L67: =ROUND(M67/$G67,4) -> 0 | O67: =ROUND(P67/$G67,4) -> 1 | P67: 4597.65
B68: 01.03.03.03 | C68: CURADO DE CONCRETO EN RAMPA | D68: m2 | E68: 86.65 | F68: 2.92 | G68: =ROUND(E68*F68,2) -> 253.02 | I68: =ROUND(J68/$G68,4) -> 0 | L68: =ROUND(M68/$G68,4) -> 0 | O68: =ROUND(P68/$G68,4) -> 1 | P68: 253.02
B69: 01.03.03.04 | C69: JUNTA ASFALTICA | D69: m | E69: 110 | F69: 4.48 | G69: =ROUND(E69*F69,2) -> 492.8 | I69: =ROUND(J69/$G69,4) -> 0 | L69: =ROUND(M69/$G69,4) -> 0 | O69: =ROUND(P69/$G69,4) -> 1 | P69: 492.8
B70: 01.03.04 | C70: OBRAS DE CONCRETO EN MARTILLO
B71: 01.03.04.01 | C71: CONCRETO F'c=175 KG/CM2, ACABADO FROTACHADO | D71: m2 | E71: 64 | F71: 49.11 | G71: =ROUND(E71*F71,2) -> 3143.04 | I71: =ROUND(J71/$G71,4) -> 0 | L71: =ROUND(M71/$G71,4) -> 0 | O71: =ROUND(P71/$G71,4) -> 1 | P71: 3143.04
B72: 01.03.04.02 | C72: ENCOFRADO Y DESENCOFRADO DE MARTILLOS | D72: m2 | E72: 2.8 | F72: 87.93 | G72: =ROUND(E72*F72,2) -> 246.2 | I72: =ROUND(J72/$G72,4) -> 0 | L72: =ROUND(M72/$G72,4) -> 0 | O72: =ROUND(P72/$G72,4) -> 1 | P72: 246.2
B73: 01.03.04.03 | C73: UÑA DE CONCRETO SUMERGIDOF'c=175 kg/cm2A=0.13m | D73: m | E73: 28 | F73: 51.24 | G73: =ROUND(E73*F73,2) -> 1434.72 | I73: =ROUND(J73/$G73,4) -> 0 | L73: =ROUND(M73/$G73,4) -> 0 | O73: =ROUND(P73/$G73,4) -> 1 | P73: 1434.72
B74: 01.03.04.04 | C74: CURADO DE CONCRETO | D74: m2 | E74: 64 | F74: 2.92 | G74: =ROUND(E74*F74,2) -> 186.88 | I74: =ROUND(J74/$G74,4) -> 0 | L74: =ROUND(M74/$G74,4) -> 0 | O74: =ROUND(P74/$G74,4) -> 1 | P74: 186.88
B75: 01.03.05 | C75: NIVELACION DE CONEXIONES DOMICILIARIAS
B76: 01.03.05.01 | C76: NIVELACION DE CONEXIONES DOMICILIARIAS DE AGUA | D76: und | E76: 32 | F76: 202.81 | G76: =ROUND(E76*F76,2) -> 6489.92 | I76: =ROUND(J76/$G76,4) -> 0 | L76: =ROUND(M76/$G76,4) -> 0 | O76: =ROUND(P76/$G76,4) -> 1 | P76: 6489.92
B77: 01.03.05.02 | C77: NIVELACION DE CONEXIONES DOMICILIARIAS DE DESAGUE | D77: und | E77: 32 | F77: 312.41 | G77: =ROUND(E77*F77,2) -> 9997.12 | I77: =ROUND(J77/$G77,4) -> 0 | L77: =ROUND(M77/$G77,4) -> 0 | O77: =ROUND(P77/$G77,4) -> 1 | P77: 9997.12
B78: 01.04 | C78: CUNETA PLUVIAL
B79: 01.04.01 | C79: MOVIMIENTO DE TIERRAS HASTA NIVEL DE SUB-RAZANTE
B80: 01.04.01.01 | C80: EXCAVACION EN TERRENO NORMAL | D80: m3 | E80: 43.2 | F80: 56.41 | G80: =ROUND(E80*F80,2) -> 2436.91 | I80: =ROUND(J80/$G80,4) -> 0 | L80: =ROUND(M80/$G80,4) -> 0.6667 | M80: 1624.61 | O80: =ROUND(P80/$G80,4) -> 0.3333 | P80: 812.3
B81: 01.04.01.02 | C81: RELLENO COMPACTADO CON MATERIAL PROPIO | D81: m3 | E81: 5.5 | F81: 42.31 | G81: =ROUND(E81*F81,2) -> 232.71 | I81: =ROUND(J81/$G81,4) -> 0 | L81: =ROUND(M81/$G81,4) -> 0 | O81: =ROUND(P81/$G81,4) -> 1 | P81: 232.71
B82: 01.04.01.03 | C82: ACARREO DE MATERIAL EXCEDENTE HASTA 30 M | D82: m3 | E82: 47.13 | F82: 28.21 | G82: =ROUND(E82*F82,2) -> 1329.54 | I82: =ROUND(J82/$G82,4) -> 0 | L82: =ROUND(M82/$G82,4) -> 0.125 | M82: 166.19 | O82: =ROUND(P82/$G82,4) -> 0.875 | P82: 1163.35
B83: 01.04.01.04 | C83: ELIMINACION DE MATERIAL EXCEDENTE C/VOLQUETE DE 15M3 (D=10KM) | D83: m3 | E83: 47.13 | F83: 18.98 | G83: =ROUND(E83*F83,2) -> 894.53 | I83: =ROUND(J83/$G83,4) -> 0 | L83: =ROUND(M83/$G83,4) -> 0 | O83: =ROUND(P83/$G83,4) -> 1 | P83: 894.53
B84: 01.04.01.05 | C84: CONFORMACIÓN Y COMPACTACIÓN SUBRASANTE C/PLANCHA | D84: m2 | E84: 115.95 | F84: 4.25 | G84: =ROUND(E84*F84,2) -> 492.79 | I84: =ROUND(J84/$G84,4) -> 0 | L84: =ROUND(M84/$G84,4) -> 0 | O84: =ROUND(P84/$G84,4) -> 1 | P84: 492.79
B85: 01.04.02 | C85: OBRAS DE CONCRETO SIMPLE EN CUNETAS
B86: 01.04.02.01 | C86: ENCOFRADO Y DESENCOFRADO EN CUNETA TRIANGULAR | D86: m2 | E86: 5.76 | F86: 34.68 | G86: =ROUND(E86*F86,2) -> 199.76 | I86: =ROUND(J86/$G86,4) -> 0 | L86: =ROUND(M86/$G86,4) -> 0 | O86: =ROUND(P86/$G86,4) -> 1 | P86: 199.76
B87: 01.04.02.02 | C87: CONCRETO F'C =175 KG/CM2 EN CUNETA TRIANGULAR | D87: m | E87: 386 | F87: 40.96 | G87: =ROUND(E87*F87,2) -> 15810.56 | I87: =ROUND(J87/$G87,4) -> 0 | L87: =ROUND(M87/$G87,4) -> 0 | O87: =ROUND(P87/$G87,4) -> 1 | P87: 15810.56
B88: 01.04.02.03 | C88: CURADO DE CONCRETO TRIANGULAR | D88: m2 | E88: 115.8 | F88: 5.86 | G88: =ROUND(E88*F88,2) -> 678.59 | I88: =ROUND(J88/$G88,4) -> 0 | L88: =ROUND(M88/$G88,4) -> 0 | O88: =ROUND(P88/$G88,4) -> 1 | P88: 678.59
B89: 01.04.02.04 | C89: JUNTA TRANSVERSAL DE DILATACION e=20mm | D89: m | E89: 38.5 | F89: 5.44 | G89: =ROUND(E89*F89,2) -> 209.44 | I89: =ROUND(J89/$G89,4) -> 0 | L89: =ROUND(M89/$G89,4) -> 0 | O89: =ROUND(P89/$G89,4) -> 1 | P89: 209.44
B90: 01.05 | C90: SARDINELES DE CONCRETO
B91: 01.05.01 | C91: MOVIMIENTO DE TIERRAS HASTA NIVEL DE SUB RAZANTE
B92: 01.05.01.01 | C92: EXCAVACION EN TERRENO NORMAL | D92: m3 | E92: 9 | F92: 56.41 | G92: =ROUND(E92*F92,2) -> 507.69 | I92: =ROUND(J92/$G92,4) -> 0 | L92: =ROUND(M92/$G92,4) -> 1 | M92: 507.69 | O92: =ROUND(P92/$G92,4) -> 0
B93: 01.05.01.02 | C93: RELLENO COMPACTACION CON MATERIAL PROPIO SELECCIONADO | D93: m3 | E93: 10.75 | F93: 19.04 | G93: =ROUND(E93*F93,2) -> 204.68 | I93: =ROUND(J93/$G93,4) -> 0 | L93: =ROUND(M93/$G93,4) -> 1 | M93: 204.68 | O93: =ROUND(P93/$G93,4) -> 0
B94: 01.05.01.03 | C94: ACARREO DE MATERIAL EXCEDENTE HASTA 30 M | D94: m3 | E94: 8.75 | F94: 28.21 | G94: =ROUND(E94*F94,2) -> 246.84 | I94: =ROUND(J94/$G94,4) -> 0 | L94: =ROUND(M94/$G94,4) -> 1 | M94: 246.84 | O94: =ROUND(P94/$G94,4) -> 0
B95: 01.05.01.04 | C95: ELIMINACION DE MATERIAL EXCEDENTE C/VOLQUETE DE 15M3 (D=10KM) | D95: m3 | E95: 8.75 | F95: 18.98 | G95: =ROUND(E95*F95,2) -> 166.08 | I95: =ROUND(J95/$G95,4) -> 0 | L95: =ROUND(M95/$G95,4) -> 1 | M95: 166.08 | O95: =ROUND(P95/$G95,4) -> 0
B96: 01.05.02 | C96: OBRAS DE CONCRETO EN SARDINEL ARMADO
B97: 01.05.02.01 | C97: ACERO CORRUGADO F'Y=4200 KG/CM2 GRADO 60 | D97: kg | E97: 653.8 | F97: 7.85 | G97: =ROUND(E97*F97,2) -> 5132.33 | I97: =ROUND(J97/$G97,4) -> 0 | L97: =ROUND(M97/$G97,4) -> 0 | O97: =ROUND(P97/$G97,4) -> 1 | P97: 5132.33
B98: 01.05.02.02 | C98: ENCOFRADO Y DESENCOFRADO EN SARDINELES | D98: m2 | E98: 251.02 | F98: 73.97 | G98: =ROUND(E98*F98,2) -> 18567.95 | I98: =ROUND(J98/$G98,4) -> 0 | L98: =ROUND(M98/$G98,4) -> 0.1892 | M98: 3512.19 | O98: =ROUND(P98/$G98,4) -> 0.8108 | P98: 15055.76
B99: 01.05.02.03 | C99: CONCRETO F'C=175 KG/CM2 PARA SARDINEL (b=0.15m , h=0.40m) ACABADO SOLAQUEADO | D99: m3 | E99: 32.94 | F99: 477.23 | G99: =ROUND(E99*F99,2) -> 15719.96 | I99: =ROUND(J99/$G99,4) -> 0 | L99: =ROUND(M99/$G99,4) -> 0 | O99: =ROUND(P99/$G99,4) -> 1 | P99: 15719.96
B100: 01.05.02.04 | C100: CURADO DE CONCRETO | D100: m2 | E100: 219.61 | F100: 2.92 | G100: =ROUND(E100*F100,2) -> 641.26 | I100: =ROUND(J100/$G100,4) -> 0 | L100: =ROUND(M100/$G100,4) -> 0 | O100: =ROUND(P100/$G100,4) -> 1 | P100: 641.26
B101: 01.05.02.05 | C101: JUNTA ASFALTICA | D101: m | E101: 6 | F101: 4.48 | G101: =ROUND(E101*F101,2) -> 26.88 | I101: =ROUND(J101/$G101,4) -> 0 | L101: =ROUND(M101/$G101,4) -> 0 | O101: =ROUND(P101/$G101,4) -> 1 | P101: 26.88
...

Sheet METRADOS
B1: RESUMEN DE METRADOS EJECUTADOS EN EL PRESENTE MES
B2: Obra: | C2: =+FT!$E$5 -> "MEJORAMIENTO Y AMPLIACIÓN DE LOS SERVICIOS DE TRANSITABILIDAD VEHICULAR Y PEATONAL DEL JR LOS PINOS Y JR LOS CEDROS EN CAYHUAYNA Y CAYHUAYNA DEL DISTRITO DE PILLCO MARCA - PROVINCIA DE HUÁNUCO - DEPARTAMENTO DE HUÁNUCO" con CUI N°2536252
B3: Entidad: | C3: =+FT!$E$4 -> MUNICIPALIDAD DISTRITAL DE PILLCO MARCA
B4: Ejecutor: | C4: =+FT!$E$15 -> CONSORCIO EJECUTOR LOS PINOS
B5: Supervisor: | C5: =+FT!$E$34 -> PROYECTA PCL S.A.C | D5: VALOR REFERENCIAL (CON IGV) | G5: =+FT!$E$24 -> 638827.47
B6: Residente: | C6: =+FT!$E$32 -> ING. RAMIREZ BLANCO GABRIEL AUGUSTO HERMOGENES | D6: MONTO DEL CONTRATO (INCL. IGV): | G6: =+FT!$E$25 -> 638827.47
B7: Ing. Supervisor: | C7: =+FT!$E$46 -> ING. CESAR RICARDO ZELADA RODRIGUEZ (CIP N° 98469) | D7: PLAZO DE EJECUCIÓN: | G7: =+FT!$E$31 -> SESENTA (60) DÍAS CALENDARIOS
B9: ITEM | C9: DESCRIPCION | D9: METRADO CONTRATADO | G9: 46174 | I9: 46204 | K9: 46143 | M9: METRADO ACUMULADO | O9: SALDO POR METRAR
D10: UND | E10: METRADO | G10: METRADO | I10: METRADO | K10: METRADO
B11: 01 | C11: CREACION DE PISTAS Y VEREDAS JR LOS CEDROS
B12: 01.01 | C12: OBRAS PROVISIONALES Y TRABAJOS PRELIMINARES | M12: =+G12+I12+K12 -> 0 | O12: =+E12-M12 -> 0
B13: 01.01.01 | C13: OBRAS PROVISIONALES
B14: 01.01.01.01 | C14: ALQUILER DE ALAMACEN, OFICINA Y CASETA DE GUARDIANIA | D14: mes | E14: 2 | G14: 1 | I14: 0.48 | M14: =+G14+I14+K14 -> 1.48 | O14: =+E14-M14 -> 0.52
B15: 01.01.01.02 | C15: CARTEL DE IDENTIFICACION DE LA OBRA DE 3.60 x 4.80 m (SOPORTE DE MADERA) | D15: und | E15: 1 | G15: 1 | M15: =+G15+I15+K15 -> 1 | O15: =+E15-M15 -> 0
B16: 01.01.01.03 | C16: ALQUILER DE BAÑOS PORTATILES Y LAVADERO | D16: mes | E16: 2 | G16: 1 | I16: 0.48 | M16: =+G16+I16+K16 -> 1.48 | O16: =+E16-M16 -> 0.52
B17: 01.01.02 | C17: TRABAJOS PRELIMINARES
B18: 01.01.02.01 | C18: LIMPIEZA DE TERRENO MANUAL | D18: m2 | E18: 1932.21 | G18: 1932.21 | M18: =+G18+I18+K18 -> 1932.21 | O18: =+E18-M18 -> 0
B19: 01.01.02.02 | C19: TRAZO Y REPLANTEO EN TERRENO NORMAL | D19: m2 | E19: 1932.21 | G19: 1932.21 | M19: =+G19+I19+K19 -> 1932.21 | O19: =+E19-M19 -> 0
B20: 01.01.02.03 | C20: MOVILIZACION Y DESMOVILIZACIÓN DE MAQUINARIA Y EQUIPO | D20: GLB | E20: 1 | G20: 1 | M20: =+G20+I20+K20 -> 1 | O20: =+E20-M20 -> 0
B21: 01.01.03 | C21: DEMOLICIONES
B22: 01.01.03.01 | C22: DEMOLICION DE VEREDAS EXISTENTES DE 0.10M | D22: m2 | E22: 135.5 | G22: 135.5 | M22: =+G22+I22+K22 -> 135.5 | O22: =+E22-M22 -> 0
B23: 01.01.03.02 | C23: ELIMINACION DE MATERIAL EXCEDENTE C/VOLQUETE DE 15M3 (D=10 KM) | D23: m3 | E23: 20.33 | G23: 20.33 | M23: =+G23+I23+K23 -> 20.33 | O23: =+E23-M23 -> 0
B24: 01.01.04 | C24: PLAN DE DESVIO VEHICULAR
B25: 01.01.04.01 | C25: TRANQUERAS DE MADERA 2.40 x 1.20 | D25: und | E25: 2 | G25: 2 | M25: =+G25+I25+K25 -> 2 | O25: =+E25-M25 -> 0
B26: 01.01.04.02 | C26: SEÑALIZACION DE DESVIO DE TRANSITO EN PERIODO DE CONSTRUCCION | D26: GLB | E26: 1 | G26: 1 | M26: =+G26+I26+K26 -> 1 | O26: =+E26-M26 -> 0
B27: 01.02 | C27: PAVIMENTO RIGIDO
B28: 01.02.01 | C28: MOVIMIENTO DE TIERRAS HASTA EL NIVEL DE SUB - RASANTE
B29: 01.02.01.01 | C29: CORTE EN TERRENO NORMAL CON MAQUINARIA | D29: m3 | E29: 590.54 | G29: 590.54 | M29: =+G29+I29+K29 -> 590.54 | O29: =+E29-M29 -> 0
B30: 01.02.01.02 | C30: RELLENO COMPACTACION CON MATERIAL PROPIO SELECCIONADO | D30: m3 | E30: 51.64 | G30: 51.64 | M30: =+G30+I30+K30 -> 51.64 | O30: =+E30-M30 -> 0
B31: 01.02.01.03 | C31: ELIMINACION DE MATERIAL EXCEDENTE C/VOLQUETE DE 15M3 (D=10KM) | D31: m3 | E31: 738.18 | G31: 738.18 | M31: =+G31+I31+K31 -> 738.18 | O31: =+E31-M31 -> 0
B32: 01.02.02 | C32: BASE
B33: 01.02.02.01 | C33: CONFORMACION DE BASE MATERIAL MEZCLADO E=0.20m | D33: m2 | E33: 910.14 | G33: 910.14 | M33: =+G33+I33+K33 -> 910.14 | O33: =+E33-M33 -> 0
B34: 01.02.03 | C34: SUB RASANTE
B35: 01.02.03.01 | C35: PERFILADO, RIEGO Y COMPACTACIÓN DE SUBRASANTE | D35: m2 | E35: 910.14 | G35: 910.14 | M35: =+G35+I35+K35 -> 910.14 | O35: =+E35-M35 -> 0
B36: 01.02.04 | C36: OBRAS DE CONCRETO
B37: 01.02.04.01 | C37: ENCOFRADO Y DESENCOFRADO EN PAVIMENTOS | D37: m2 | E37: 127.29 | G37: 127.29 | M37: =+G37+I37+K37 -> 127.29 | O37: =+E37-M37 -> 0
B38: 01.02.04.02 | C38: CONCRETO F'C =210 KG/CM2 EN VIA E=15CM | D38: m2 | E38: 910.14 | G38: 910.14 | M38: =+G38+I38+K38 -> 910.14 | O38: =+E38-M38 -> 0
B39: 01.02.04.03 | C39: CURADO DE CONCRETO | D39: m2 | E39: 910.14 | G39: 910.14 | M39: =+G39+I39+K39 -> 910.14 | O39: =+E39-M39 -> 0
B40: 01.02.04.04 | C40: ACERO FY = 4200Kg/cm2 EN JUNTAS DE DILATACION LONGITUDINAL Ø 3/8" | D40: kg | E40: 80.64 | G40: 80.64 | M40: =+G40+I40+K40 -> 80.64 | O40: =+E40-M40 -> 0
B41: 01.02.04.05 | C41: ACERO FY = 2400Kg/cm2 GRADO 60 EN JUNTAS DE DILATACION TRANSVERSAL Ø 3/4" | D41: kg | E41: 176.4 | G41: 176.4 | M41: =+G41+I41+K41 -> 176.4 | O41: =+E41-M41 -> 0
B42: 01.02.04.06 | C42: JUNTA DE AISLAMIENTO e=1" X 0.20 m | D42: m | E42: 360 | G42: 360 | M42: =+G42+I42+K42 -> 360 | O42: =+E42-M42 -> 0
B43: 01.02.04.07 | C43: JUNTA DE DILATACION e=1" X 0.10 m | D43: m | E43: 255 | G43: 255 | M43: =+G43+I43+K43 -> 255 | O43: =+E43-M43 -> 0
B44: 01.02.04.08 | C44: JUNTAS DE CONTRACCION CON ELASTOMERICO DE POLIURETANO E=1/2" X 0.10m | D44: m | E44: 150 | G44: 150 | M44: =+G44+I44+K44 -> 150 | O44: =+E44-M44 -> 0
B45: 01.02.05 | C45: NIVELACION DE BUZONES
B46: 01.02.05.01 | C46: NIVELACION DE BUZONES EN GENERAL | D46: und | E46: 3 | G46: 3 | M46: =+G46+I46+K46 -> 3 | O46: =+E46-M46 -> 0
B47: 01.02.06 | C47: SEÑALIZACION
B48: 01.02.06.01 | C48: PINTURA EN PAVIMENTO (SIMBOLO Y LETRA) | D48: m2 | E48: 50.6 | M48: =+G48+I48+K48 -> 0 | O48: =+E48-M48 -> 50.6
B49: 01.02.06.02 | C49: PINTURA DE PAVIMENTO (LINEAS DISCONTINUAS CENTRALES) | D49: m | E49: 170 | M49: =+G49+I49+K49 -> 0 | O49: =+E49-M49 -> 170
B50: 01.02.06.03 | C50: SEÑALIZACION VERTICAL | D50: und | E50: 4 | M50: =+G50+I50+K50 -> 0 | O50: =+E50-M50 -> 4
B51: 01.03 | C51: VEREDAS, RAMPAS Y MARTILLOS
B52: 01.03.01 | C52: MOVIMIENTO DE TIERRAS HASTA EL NIVEL DE SUB - RASANTE
B53: 01.03.01.01 | C53: EXCAVACION EN TERRENO NORMAL C/MAQUINARIA LIVIANA | D53: m3 | E53: 56.3 | G53: 56.3 | M53: =+G53+I53+K53 -> 56.3 | O53: =+E53-M53 -> 0
B54: 01.03.01.02 | C54: RELLENO Y COMPACTACION CON MATERIAL PROPIO SELECCIONADO | D54: m3 | E54: 12 | G54: 12 | M54: =+G54+I54+K54 -> 12 | O54: =+E54-M54 -> 0
B55: 01.03.01.03 | C55: ELIMINACION DE MATERIAL EXCEDENTE C/VOLQUETE DE 15M3 (D=10KM) | D55: m3 | E55: 55.38 | G55: 55.38 | M55: =+G55+I55+K55 -> 55.38 | O55: =+E55-M55 -> 0
B56: 01.03.01.04 | C56: PERFILADO Y COMPACTADO CON PLANCHA | D56: m2 | E56: 547.38 | G56: 547.38 | M56: =+G56+I56+K56 -> 547.38 | O56: =+E56-M56 -> 0
B57: 01.03.01.05 | C57: CONFORMACIÓN Y COMPACTACIÓN DE BASE EN VEREDAS Y RAMPAS (e=10cm) | D57: m2 | E57: 547.38 | G57: 547.38 | M57: =+G57+I57+K57 -> 547.38 | O57: =+E57-M57 -> 0
B58: 01.03.02 | C58: OBRAS DE CONCRETO EN VEREDAS
B59: 01.03.02.01 | C59: ENCOFRADO Y DESENCOFRADO EN VEREDAS | D59: m2 | E59: 55.28 | I59: 55.28 | M59: =+G59+I59+K59 -> 55.28 | O59: =+E59-M59 -> 0
B60: 01.03.02.02 | C60: CONCRETO F'c=175 kg/cm2 (E=4") EN VEREDA CON ACABADO FROTACHADO Y BRUÑADO S/DISEÑO | D60: m2 | E60: 547.38 | I60: 547.38 | M60: =+G60+I60+K60 -> 547.38 | O60: =+E60-M60 -> 0
B61: 01.03.02.03 | C61: CONCRETO F'c=175 kg/cm2 PARA UÑA EN VEREDA (A=0.025 m2) | D61: m | E61: 404 | I61: 404 | M61: =+G61+I61+K61 -> 404 | O61: =+E61-M61 -> 0
B62: 01.03.02.04 | C62: CURADO DE CONCRETO | E62: 547.38 | I62: 547.38 | M62: =+G62+I62+K62 -> 547.38 | O62: =+E62-M62 -> 0
B63: 01.03.02.05 | C63: JUNTA ASFALTICA | D63: m | E63: 158.4 | I63: 158.4 | M63: =+G63+I63+K63 -> 158.4 | O63: =+E63-M63 -> 0
B64: 01.03.03 | C64: OBRAS DE CONCRETO EN RAMPA
B65: 01.03.03.01 | C65: ENCOFRADO Y DESENCOFRADO EN RAMPAS | D65: m2 | E65: 16.25 | I65: 16.25 | M65: =+G65+I65+K65 -> 16.25 | O65: =+E65-M65 -> 0
B66: 01.03.03.02 | C66: CONCRETO F'c=175 KG/CM2, ACABADO 1:2 BRUÑADO Y FROTACHADO | D66: m2 | E66: 86.65 | I66: 86.65 | M66: =+G66+I66+K66 -> 86.65 | O66: =+E66-M66 -> 0
B67: 01.03.03.03 | C67: CURADO DE CONCRETO EN RAMPA | D67: m2 | E67: 86.65 | I67: 86.65 | M67: =+G67+I67+K67 -> 86.65 | O67: =+E67-M67 -> 0
B68: 01.03.03.04 | C68: JUNTA ASFALTICA | D68: m | E68: 110 | I68: 110 | M68: =+G68+I68+K68 -> 110 | O68: =+E68-M68 -> 0
B69: 01.03.04 | C69: OBRAS DE CONCRETO EN MARTILLO
B70: 01.03.04.01 | C70: CONCRETO F'c=175 KG/CM2, ACABADO FROTACHADO | D70: m2 | E70: 64 | I70: 64 | M70: =+G70+I70+K70 -> 64 | O70: =+E70-M70 -> 0
B71: 01.03.04.02 | C71: ENCOFRADO Y DESENCOFRADO DE MARTILLOS | D71: m2 | E71: 2.8 | I71: 2.8 | M71: =+G71+I71+K71 -> 2.8 | O71: =+E71-M71 -> 0
B72: 01.03.04.03 | C72: UÑA DE CONCRETO SUMERGIDOF'c=175 kg/cm2A=0.13m | D72: m | E72: 28 | I72: 28 | M72: =+G72+I72+K72 -> 28 | O72: =+E72-M72 -> 0
B73: 01.03.04.04 | C73: CURADO DE CONCRETO | D73: m2 | E73: 64 | I73: 64 | M73: =+G73+I73+K73 -> 64 | O73: =+E73-M73 -> 0
B74: 01.03.05 | C74: NIVELACION DE CONEXIONES DOMICILIARIAS
B75: 01.03.05.01 | C75: NIVELACION DE CONEXIONES DOMICILIARIAS DE AGUA | D75: und | E75: 32 | G75: 32 | M75: =+G75+I75+K75 -> 32 | O75: =+E75-M75 -> 0
B76: 01.03.05.02 | C76: NIVELACION DE CONEXIONES DOMICILIARIAS DE DESAGUE | D76: und | E76: 32 | G76: 32 | M76: =+G76+I76+K76 -> 32 | O76: =+E76-M76 -> 0
B77: 01.04 | C77: CUNETA PLUVIAL
B78: 01.04.01 | C78: MOVIMIENTO DE TIERRAS HASTA NIVEL DE SUB-RAZANTE
B79: 01.04.01.01 | C79: EXCAVACION EN TERRENO NORMAL | D79: m3 | E79: 43.2 | I79: 43.2 | M79: =+G79+I79+K79 -> 43.2 | O79: =+E79-M79 -> 0
B80: 01.04.01.02 | C80: RELLENO COMPACTADO CON MATERIAL PROPIO | D80: m3 | E80: 5.5 | I80: 5.5 | M80: =+G80+I80+K80 -> 5.5 | O80: =+E80-M80 -> 0
B81: 01.04.01.03 | C81: ACARREO DE MATERIAL EXCEDENTE HASTA 30 M | D81: m3 | E81: 47.13 | I81: 47.13 | M81: =+G81+I81+K81 -> 47.13 | O81: =+E81-M81 -> 0
B82: 01.04.01.04 | C82: ELIMINACION DE MATERIAL EXCEDENTE C/VOLQUETE DE 15M3 (D=10KM) | D82: m3 | E82: 47.13 | I82: 47.13 | M82: =+G82+I82+K82 -> 47.13 | O82: =+E82-M82 -> 0
B83: 01.04.01.05 | C83: CONFORMACIÓN Y COMPACTACIÓN SUBRASANTE C/PLANCHA | D83: m2 | E83: 115.95 | I83: 115.95 | M83: =+G83+I83+K83 -> 115.95 | O83: =+E83-M83 -> 0
B84: 01.04.02 | C84: OBRAS DE CONCRETO SIMPLE EN CUNETAS
B85: 01.04.02.01 | C85: ENCOFRADO Y DESENCOFRADO EN CUNETA TRIANGULAR | D85: m2 | E85: 5.76 | I85: 5.76 | M85: =+G85+I85+K85 -> 5.76 | O85: =+E85-M85 -> 0
B86: 01.04.02.02 | C86: CONCRETO F'C =175 KG/CM2 EN CUNETA TRIANGULAR | D86: m | E86: 386 | I86: 386 | M86: =+G86+I86+K86 -> 386 | O86: =+E86-M86 -> 0
B87: 01.04.02.03 | C87: CURADO DE CONCRETO TRIANGULAR | D87: m2 | E87: 115.8 | I87: 115.8 | M87: =+G87+I87+K87 -> 115.8 | O87: =+E87-M87 -> 0
B88: 01.04.02.04 | C88: JUNTA TRANSVERSAL DE DILATACION e=20mm | D88: m | E88: 38.5 | I88: 38.5 | M88: =+G88+I88+K88 -> 38.5 | O88: =+E88-M88 -> 0
B89: 01.05 | C89: SARDINELES DE CONCRETO
B90: 01.05.01 | C90: MOVIMIENTO DE TIERRAS HASTA NIVEL DE SUB RAZANTE
B91: 01.05.01.01 | C91: EXCAVACION EN TERRENO NORMAL | D91: m3 | E91: 9 | I91: 9 | M91: =+G91+I91+K91 -> 9 | O91: =+E91-M91 -> 0
B92: 01.05.01.02 | C92: RELLENO COMPACTACION CON MATERIAL PROPIO SELECCIONADO | D92: m3 | E92: 10.75 | I92: 10.75 | M92: =+G92+I92+K92 -> 10.75 | O92: =+E92-M92 -> 0
B93: 01.05.01.03 | C93: ACARREO DE MATERIAL EXCEDENTE HASTA 30 M | D93: m3 | E93: 8.75 | I93: 8.75 | M93: =+G93+I93+K93 -> 8.75 | O93: =+E93-M93 -> 0
B94: 01.05.01.04 | C94: ELIMINACION DE MATERIAL EXCEDENTE C/VOLQUETE DE 15M3 (D=10KM) | D94: m3 | E94: 8.75 | I94: 8.75 | M94: =+G94+I94+K94 -> 8.75 | O94: =+E94-M94 -> 0
B95: 01.05.02 | C95: OBRAS DE CONCRETO EN SARDINEL ARMADO
B96: 01.05.02.01 | C96: ACERO CORRUGADO F'Y=4200 KG/CM2 GRADO 60 | D96: kg | E96: 653.8 | I96: 653.8 | M96: =+G96+I96+K96 -> 653.8 | O96: =+E96-M96 -> 0
B97: 01.05.02.02 | C97: ENCOFRADO Y DESENCOFRADO EN SARDINELES | D97: m2 | E97: 251.02 | I97: 251.02 | M97: =+G97+I97+K97 -> 251.02 | O97: =+E97-M97 -> 0
B98: 01.05.02.03 | C98: CONCRETO F'C=175 KG/CM2 PARA SARDINEL (b=0.15m , h=0.40m) ACABADO SOLAQUEADO | D98: m3 | E98: 32.94 | I98: 32.94 | M98: =+G98+I98+K98 -> 32.94 | O98: =+E98-M98 -> 0
B99: 01.05.02.04 | C99: CURADO DE CONCRETO | D99: m2 | E99: 219.61 | I99: 219.61 | M99: =+G99+I99+K99 -> 219.61 | O99: =+E99-M99 -> 0
B100: 01.05.02.05 | C100: JUNTA ASFALTICA | D100: m | E100: 6 | I100: 6 | M100: =+G100+I100+K100 -> 6 | O100: =+E100-M100 -> 0
B101: 01.06 | C101: MURO DE CONTENCION
...

Sheet CALEN. VALO.
B1: CALENDARIO DE AVANCE DE OBRA VALORIZADO EJECUTADO
B2: Obra: | C2: =+FT!$E$5 -> "MEJORAMIENTO Y AMPLIACIÓN DE LOS SERVICIOS DE TRANSITABILIDAD VEHICULAR Y PEATONAL DEL JR LOS PINOS Y JR LOS CEDROS EN CAYHUAYNA Y CAYHUAYNA DEL DISTRITO DE PILLCO MARCA - PROVINCIA DE HUÁNUCO - DEPARTAMENTO DE HUÁNUCO" con CUI N°2536252
B3: Entidad: | C3: =+FT!$E$4 -> MUNICIPALIDAD DISTRITAL DE PILLCO MARCA
B4: Ejecutor: | C4: =+FT!$E$15 -> CONSORCIO EJECUTOR LOS PINOS
B5: Supervisor: | C5: =+FT!$E$34 -> PROYECTA PCL S.A.C | D5: VALOR REFERENCIAL (CON IGV) | G5: =+FT!$E$24 -> 638827.47
B6: Residente: | C6: =+FT!$E$32 -> ING. RAMIREZ BLANCO GABRIEL AUGUSTO HERMOGENES | D6: MONTO DEL CONTRATO (INCL. IGV): | G6: =+FT!$E$25 -> 638827.47
B7: Ing. Supervisor: | C7: =+FT!$E$46 -> ING. CESAR RICARDO ZELADA RODRIGUEZ (CIP N° 98469) | D7: PLAZO DE EJECUCIÓN: | G7: =+FT!$E$31 -> SESENTA (60) DÍAS CALENDARIOS
B9: ITEM | C9: DESCRIPCION | D9: PRESUPUESTO DE OBRA | I9: 46174 | L9: 46204 | O9: 46235
I10: 46193 | J10: 46203 | L10: 46204 | M10: 46234 | O10: 46235 | P10: 46253
D11: UND | E11: METRADO | F11: P.UND | G11: TOTAL | I11: PORCEN. (%) | J11: COSTO (S/) | L11: PORCEN. (%) | M11: COSTO (S/) | O11: PORCEN. (%) | P11: COSTO (S/)
B12: 01 | C12: CREACION DE PISTAS Y VEREDAS JR LOS CEDROS
B13: 01.01 | C13: OBRAS PROVISIONALES Y TRABAJOS PRELIMINARES
B14: 01.01.01 | C14: OBRAS PROVISIONALES
B15: 01.01.01.01 | C15: ALQUILER DE ALAMACEN, OFICINA Y CASETA DE GUARDIANIA | D15: mes | E15: 2 | F15: 2400 | G15: =ROUND(E15*F15,2) -> 4800 | I15: =ROUND(J15/$G15,4) -> 0.5 | J15: 2400 | L15: =ROUND(M15/$G15,4) -> 0.24 | M15: 1152 | O15: =ROUND(P15/$G15,4) -> 0
B16: 01.01.01.02 | C16: CARTEL DE IDENTIFICACION DE LA OBRA DE 3.60 x 4.80 m (SOPORTE DE MADERA) | D16: und | E16: 1 | F16: 1205.49 | G16: =ROUND(E16*F16,2) -> 1205.49 | I16: =ROUND(J16/$G16,4) -> 1 | J16: 1205.49 | L16: =ROUND(M16/$G16,4) -> 0 | M16: 0 | O16: =ROUND(P16/$G16,4) -> 0
B17: 01.01.01.03 | C17: ALQUILER DE BAÑOS PORTATILES Y LAVADERO | D17: mes | E17: 2 | F17: 850 | G17: =ROUND(E17*F17,2) -> 1700 | I17: =ROUND(J17/$G17,4) -> 0.5 | J17: 850 | L17: =ROUND(M17/$G17,4) -> 0.24 | M17: 408 | O17: =ROUND(P17/$G17,4) -> 0
B18: 01.01.02 | C18: TRABAJOS PRELIMINARES | G18: =ROUND(E18*F18,2) -> 0
B19: 01.01.02.01 | C19: LIMPIEZA DE TERRENO MANUAL | D19: m2 | E19: 1932.21 | F19: 1.06 | G19: =ROUND(E19*F19,2) -> 2048.14 | I19: =ROUND(J19/$G19,4) -> 1 | J19: 2048.14 | L19: =ROUND(M19/$G19,4) -> 0 | M19: 0 | O19: =ROUND(P19/$G19,4) -> 0
B20: 01.01.02.02 | C20: TRAZO Y REPLANTEO EN TERRENO NORMAL | D20: m2 | E20: 1932.21 | F20: 4.32 | G20: =ROUND(E20*F20,2) -> 8347.15 | I20: =ROUND(J20/$G20,4) -> 1 | J20: 8347.15 | L20: =ROUND(M20/$G20,4) -> 0 | M20: 0 | O20: =ROUND(P20/$G20,4) -> 0
B21: 01.01.02.03 | C21: MOVILIZACION Y DESMOVILIZACION DE MAQUINARIA Y EQUIPO | D21: GLB | E21: 1 | F21: 2500 | G21: =ROUND(E21*F21,2) -> 2500 | I21: =ROUND(J21/$G21,4) -> 1 | J21: 2500 | L21: =ROUND(M21/$G21,4) -> 0 | M21: 0 | O21: =ROUND(P21/$G21,4) -> 0
B22: 01.01.03 | C22: DEMOLICIONES | G22: =ROUND(E22*F22,2) -> 0
B23: 01.01.03.01 | C23: DEMOLICION DE VEREDAS EXISTENTES DE 0.10M | D23: m2 | E23: 135.5 | F23: 21.33 | G23: =ROUND(E23*F23,2) -> 2890.22 | I23: =ROUND(J23/$G23,4) -> 1 | J23: 2890.22 | L23: =ROUND(M23/$G23,4) -> 0 | M23: 0 | O23: =ROUND(P23/$G23,4) -> 0
B24: 01.01.03.02 | C24: ELIMINACION DE MATERIAL EXCEDENTE C/VOLQUETE DE 15M3 (D=10 KM) | D24: m3 | E24: 20.33 | F24: 18.98 | G24: =ROUND(E24*F24,2) -> 385.86 | I24: =ROUND(J24/$G24,4) -> 1 | J24: 385.86 | L24: =ROUND(M24/$G24,4) -> 0 | M24: 0 | O24: =ROUND(P24/$G24,4) -> 0
B25: 01.01.04 | C25: PLAN DE DESVIO VEHICULAR
B26: 01.01.04.01 | C26: TRANQUERAS DE MADERA 2.40 x 1.20 | D26: und | E26: 2 | F26: 221.35 | G26: =ROUND(E26*F26,2) -> 442.7 | I26: =ROUND(J26/$G26,4) -> 1 | J26: 442.7 | L26: =ROUND(M26/$G26,4) -> 0 | M26: 0 | O26: =ROUND(P26/$G26,4) -> 0
B27: 01.01.04.02 | C27: SEÑALIZACION DE DESVIO DE TRANSITO EN PERIODO DE CONSTRUCCION | D27: GLB | E27: 1 | F27: 221.16 | G27: =ROUND(E27*F27,2) -> 221.16 | I27: =ROUND(J27/$G27,4) -> 1 | J27: 221.16 | L27: =ROUND(M27/$G27,4) -> 0 | M27: 0 | O27: =ROUND(P27/$G27,4) -> 0
B28: 01.02 | C28: PAVIMENTO RIGIDO | G28: =ROUND(E28*F28,2) -> 0
B29: 01.02.01 | C29: MOVIMIENTO DE TIERRAS HASTA EL NIVEL DE SUB - RASANTE
B30: 01.02.01.01 | C30: CORTE EN TERRENO NORMAL CON MAQUINARIA | D30: m3 | E30: 590.54 | F30: 10.47 | G30: =ROUND(E30*F30,2) -> 6182.95 | I30: =ROUND(J30/$G30,4) -> 1 | J30: 6182.95 | L30: =ROUND(M30/$G30,4) -> 0 | M30: 0 | O30: =ROUND(P30/$G30,4) -> 0
B31: 01.02.01.02 | C31: RELLENO COMPACTACION CON MATERIAL PROPIO SELECCIONADO | D31: m3 | E31: 51.64 | F31: 19.04 | G31: =ROUND(E31*F31,2) -> 983.23 | I31: =ROUND(J31/$G31,4) -> 1 | J31: 983.23 | L31: =ROUND(M31/$G31,4) -> 0 | M31: 0 | O31: =ROUND(P31/$G31,4) -> 0
B32: 01.02.01.03 | C32: ELIMINACION DE MATERIAL EXCEDENTE C/VOLQUETE DE 15M3 (D=10KM) | D32: m3 | E32: 738.18 | F32: 18.98 | G32: =ROUND(E32*F32,2) -> 14010.66 | I32: =ROUND(J32/$G32,4) -> 1 | J32: 14010.66 | L32: =ROUND(M32/$G32,4) -> 0 | M32: 0 | O32: =ROUND(P32/$G32,4) -> 0
B33: 01.02.02 | C33: BASE | G33: =ROUND(E33*F33,2) -> 0
B34: 01.02.02.01 | C34: CONFORMACION DE BASE MATERIAL MEZCLADO E=0.20m | D34: m2 | E34: 910.14 | F34: 31.15 | G34: =ROUND(E34*F34,2) -> 28350.86 | I34: =ROUND(J34/$G34,4) -> 1 | J34: 28350.86 | L34: =ROUND(M34/$G34,4) -> 0 | M34: 0 | O34: =ROUND(P34/$G34,4) -> 0
B35: 01.02.03 | C35: SUB RASANTE | G35: =ROUND(E35*F35,2) -> 0
B36: 01.02.03.01 | C36: PERFILADO, RIEGO Y COMPACTACIÓN DE SUBRASANTE | D36: m2 | E36: 910.14 | F36: 5.54 | G36: =ROUND(E36*F36,2) -> 5042.18 | I36: =ROUND(J36/$G36,4) -> 1 | J36: 5042.18 | L36: =ROUND(M36/$G36,4) -> 0 | M36: 0 | O36: =ROUND(P36/$G36,4) -> 0
B37: 01.02.04 | C37: OBRAS DE CONCRETO | G37: =ROUND(E37*F37,2) -> 0
B38: 01.02.04.01 | C38: ENCOFRADO Y DESENCOFRADO EN PAVIMENTOS | D38: m2 | E38: 127.29 | F38: 63.41 | G38: =ROUND(E38*F38,2) -> 8071.46 | I38: =ROUND(J38/$G38,4) -> 1 | J38: 8071.46 | L38: =ROUND(M38/$G38,4) -> 0 | M38: 0 | O38: =ROUND(P38/$G38,4) -> 0
B39: 01.02.04.02 | C39: CONCRETO F'C =210 KG/CM2 EN VIA E=15CM | D39: m2 | E39: 910.14 | F39: 119.99 | G39: =ROUND(E39*F39,2) -> 109207.7 | I39: =ROUND(J39/$G39,4) -> 1 | J39: 109207.7 | L39: =ROUND(M39/$G39,4) -> 0 | M39: 0 | O39: =ROUND(P39/$G39,4) -> 0
B40: 01.02.04.03 | C40: CURADO DE CONCRETO | D40: m2 | E40: 910.14 | F40: 2.92 | G40: =ROUND(E40*F40,2) -> 2657.61 | I40: =ROUND(J40/$G40,4) -> 1 | J40: 2657.61 | L40: =ROUND(M40/$G40,4) -> 0 | M40: 0 | O40: =ROUND(P40/$G40,4) -> 0
B41: 01.02.04.04 | C41: ACERO FY = 4200Kg/cm2 EN JUNTAS DE DILATACION LONGITUDINAL Ø 3/8" | D41: kg | E41: 80.64 | F41: 12.14 | G41: =ROUND(E41*F41,2) -> 978.97 | I41: =ROUND(J41/$G41,4) -> 1 | J41: 978.97 | L41: =ROUND(M41/$G41,4) -> 0 | M41: 0 | O41: =ROUND(P41/$G41,4) -> 0
B42: 01.02.04.05 | C42: ACERO FY = 2400Kg/cm2 GRADO 60 EN JUNTAS DE DILATACION TRANSVERSAL Ø 3/4" | D42: kg | E42: 176.4 | F42: 42.88 | G42: =ROUND(E42*F42,2) -> 7564.03 | I42: =ROUND(J42/$G42,4) -> 1 | J42: 7564.03 | L42: =ROUND(M42/$G42,4) -> 0 | M42: 0 | O42: =ROUND(P42/$G42,4) -> 0
B43: 01.02.04.06 | C43: JUNTA DE AISLAMIENTO e=1" X 0.20 m | D43: m | E43: 360 | F43: 5.59 | G43: =ROUND(E43*F43,2) -> 2012.4 | I43: =ROUND(J43/$G43,4) -> 1 | J43: 2012.4 | L43: =ROUND(M43/$G43,4) -> 0 | M43: 0 | O43: =ROUND(P43/$G43,4) -> 0
B44: 01.02.04.07 | C44: JUNTA DE DILATACION e=1" X 0.10 m | D44: m | E44: 255 | F44: 5.59 | G44: =ROUND(E44*F44,2) -> 1425.45 | I44: =ROUND(J44/$G44,4) -> 1 | J44: 1425.45 | L44: =ROUND(M44/$G44,4) -> 0 | M44: 0 | O44: =ROUND(P44/$G44,4) -> 0
B45: 01.02.04.08 | C45: JUNTAS DE CONTRACCION CON ELASTOMERICO DE POLIURETANO E=1/2" X 0.10m | D45: m | E45: 150 | F45: 19.22 | G45: =ROUND(E45*F45,2) -> 2883 | I45: =ROUND(J45/$G45,4) -> 1 | J45: 2883 | L45: =ROUND(M45/$G45,4) -> 0 | M45: 0 | O45: =ROUND(P45/$G45,4) -> 0
B46: 01.02.05 | C46: NIVELACION DE BUZONES | G46: =ROUND(E46*F46,2) -> 0
B47: 01.02.05.01 | C47: NIVELACION DE BUZONES EN GENERAL | D47: und | E47: 3 | F47: 471.14 | G47: =ROUND(E47*F47,2) -> 1413.42 | I47: =ROUND(J47/$G47,4) -> 1 | J47: 1413.42 | L47: =ROUND(M47/$G47,4) -> 0 | M47: 0 | O47: =ROUND(P47/$G47,4) -> 0
B48: 01.02.06 | C48: SEÑALIZACION | G48: =ROUND(E48*F48,2) -> 0
B49: 01.02.06.01 | C49: PINTURA EN PAVIMENTO (SIMBOLO Y LETRA) | D49: m2 | E49: 50.6 | F49: 38.21 | G49: =ROUND(E49*F49,2) -> 1933.43 | I49: =ROUND(J49/$G49,4) -> 0 | J49: 0 | L49: =ROUND(M49/$G49,4) -> 0 | M49: 0 | O49: =ROUND(P49/$G49,4) -> 0
B50: 01.02.06.02 | C50: PINTURA DE PAVIMENTO (LINEAS DISCONTINUAS CENTRALES) | D50: m | E50: 170 | F50: 10.43 | G50: =ROUND(E50*F50,2) -> 1773.1 | I50: =ROUND(J50/$G50,4) -> 0 | J50: 0 | L50: =ROUND(M50/$G50,4) -> 0 | M50: 0 | O50: =ROUND(P50/$G50,4) -> 0
B51: 01.02.06.03 | C51: SEÑALIZACION VERTICAL | D51: und | E51: 4 | F51: 361.47 | G51: =ROUND(E51*F51,2) -> 1445.88 | I51: =ROUND(J51/$G51,4) -> 0 | J51: 0 | L51: =ROUND(M51/$G51,4) -> 0 | M51: 0 | O51: =ROUND(P51/$G51,4) -> 0
B52: 01.03 | C52: VEREDAS, RAMPAS Y MARTILLOS | G52: =ROUND(E52*F52,2) -> 0
B53: 01.03.01 | C53: MOVIMIENTO DE TIERRAS HASTA EL NIVEL DE SUB - RASANTE
B54: 01.03.01.01 | C54: EXCAVACION EN TERRENO NORMAL C/MAQUINARIA LIVIANA | D54: m3 | E54: 56.3 | F54: 22.11 | G54: =ROUND(E54*F54,2) -> 1244.79 | I54: =ROUND(J54/$G54,4) -> 1 | J54: 1244.79 | L54: =ROUND(M54/$G54,4) -> 0 | M54: 0 | O54: =ROUND(P54/$G54,4) -> 0
B55: 01.03.01.02 | C55: RELLENO Y COMPACTACION CON MATERIAL PROPIO SELECCIONADO | D55: m3 | E55: 12 | F55: 42.31 | G55: =ROUND(E55*F55,2) -> 507.72 | I55: =ROUND(J55/$G55,4) -> 1 | J55: 507.72 | L55: =ROUND(M55/$G55,4) -> 0 | M55: 0 | O55: =ROUND(P55/$G55,4) -> 0
B56: 01.03.01.03 | C56: ELIMINACION DE MATERIAL EXCEDENTE C/VOLQUETE DE 15M3 (D=10KM) | D56: m3 | E56: 55.38 | F56: 18.98 | G56: =ROUND(E56*F56,2) -> 1051.11 | I56: =ROUND(J56/$G56,4) -> 1 | J56: 1051.11 | L56: =ROUND(M56/$G56,4) -> 0 | M56: 0 | O56: =ROUND(P56/$G56,4) -> 0
B57: 01.03.01.04 | C57: PERFILADO Y COMPACTADO CON PLANCHA | D57: m2 | E57: 547.38 | F57: 4.25 | G57: =ROUND(E57*F57,2) -> 2326.37 | I57: =ROUND(J57/$G57,4) -> 1 | J57: 2326.37 | L57: =ROUND(M57/$G57,4) -> 0 | M57: 0 | O57: =ROUND(P57/$G57,4) -> 0
B58: 01.03.01.05 | C58: CONFORMACIÓN Y COMPACTACIÓN DE BASE EN VEREDAS Y RAMPAS (e=10cm) | D58: m2 | E58: 547.38 | F58: 16.02 | G58: =ROUND(E58*F58,2) -> 8769.03 | I58: =ROUND(J58/$G58,4) -> 1 | J58: 8769.03 | L58: =ROUND(M58/$G58,4) -> 0 | M58: 0 | O58: =ROUND(P58/$G58,4) -> 0
B59: 01.03.02 | C59: OBRAS DE CONCRETO EN VEREDAS | G59: =ROUND(E59*F59,2) -> 0
B60: 01.03.02.01 | C60: ENCOFRADO Y DESENCOFRADO EN VEREDAS | D60: m2 | E60: 55.28 | F60: 72.37 | G60: =ROUND(E60*F60,2) -> 4000.61 | I60: =ROUND(J60/$G60,4) -> 0 | J60: 0 | L60: =ROUND(M60/$G60,4) -> 1 | M60: 4000.61 | O60: =ROUND(P60/$G60,4) -> 0
B61: 01.03.02.02 | C61: CONCRETO F'c=175 kg/cm2 (E=4") EN VEREDA CON ACABADO FROTACHADO Y BRUÑADO S/DISEÑO | D61: m2 | E61: 547.38 | F61: 49.11 | G61: =ROUND(E61*F61,2) -> 26881.83 | I61: =ROUND(J61/$G61,4) -> 0 | J61: 0 | L61: =ROUND(M61/$G61,4) -> 1 | M61: 26881.83 | O61: =ROUND(P61/$G61,4) -> 0
B62: 01.03.02.03 | C62: CONCRETO F'c=175 kg/cm2 PARA UÑA EN VEREDA (A=0.025 m2) | D62: m | E62: 404 | F62: 16.32 | G62: =ROUND(E62*F62,2) -> 6593.28 | I62: =ROUND(J62/$G62,4) -> 0 | J62: 0 | L62: =ROUND(M62/$G62,4) -> 1 | M62: 6593.28 | O62: =ROUND(P62/$G62,4) -> 0
B63: 01.03.02.04 | C63: CURADO DE CONCRETO | E63: 547.38 | F63: 2.92 | G63: =ROUND(E63*F63,2) -> 1598.35 | I63: =ROUND(J63/$G63,4) -> 0 | J63: 0 | L63: =ROUND(M63/$G63,4) -> 1 | M63: 1598.35 | O63: =ROUND(P63/$G63,4) -> 0
B64: 01.03.02.05 | C64: JUNTA ASFALTICA | D64: m | E64: 158.4 | F64: 4.48 | G64: =ROUND(E64*F64,2) -> 709.63 | I64: =ROUND(J64/$G64,4) -> 0 | J64: 0 | L64: =ROUND(M64/$G64,4) -> 1 | M64: 709.63 | O64: =ROUND(P64/$G64,4) -> 0
B65: 01.03.03 | C65: OBRAS DE CONCRETO EN RAMPA | G65: =ROUND(E65*F65,2) -> 0
B66: 01.03.03.01 | C66: ENCOFRADO Y DESENCOFRADO EN RAMPAS | D66: m2 | E66: 16.25 | F66: 46.94 | G66: =ROUND(E66*F66,2) -> 762.78 | I66: =ROUND(J66/$G66,4) -> 0 | J66: 0 | L66: =ROUND(M66/$G66,4) -> 1 | M66: 762.78 | O66: =ROUND(P66/$G66,4) -> 0
B67: 01.03.03.02 | C67: CONCRETO F'c=175 KG/CM2, ACABADO 1:2 BRUÑADO Y FROTACHADO | D67: m2 | E67: 86.65 | F67: 53.06 | G67: =ROUND(E67*F67,2) -> 4597.65 | I67: =ROUND(J67/$G67,4) -> 0 | J67: 0 | L67: =ROUND(M67/$G67,4) -> 1 | M67: 4597.65 | O67: =ROUND(P67/$G67,4) -> 0
B68: 01.03.03.03 | C68: CURADO DE CONCRETO EN RAMPA | D68: m2 | E68: 86.65 | F68: 2.92 | G68: =ROUND(E68*F68,2) -> 253.02 | I68: =ROUND(J68/$G68,4) -> 0 | J68: 0 | L68: =ROUND(M68/$G68,4) -> 1 | M68: 253.02 | O68: =ROUND(P68/$G68,4) -> 0
B69: 01.03.03.04 | C69: JUNTA ASFALTICA | D69: m | E69: 110 | F69: 4.48 | G69: =ROUND(E69*F69,2) -> 492.8 | I69: =ROUND(J69/$G69,4) -> 0 | J69: 0 | L69: =ROUND(M69/$G69,4) -> 1 | M69: 492.8 | O69: =ROUND(P69/$G69,4) -> 0
B70: 01.03.04 | C70: OBRAS DE CONCRETO EN MARTILLO
B71: 01.03.04.01 | C71: CONCRETO F'c=175 KG/CM2, ACABADO FROTACHADO | D71: m2 | E71: 64 | F71: 49.11 | G71: =ROUND(E71*F71,2) -> 3143.04 | I71: =ROUND(J71/$G71,4) -> 0 | J71: 0 | L71: =ROUND(M71/$G71,4) -> 1 | M71: 3143.04 | O71: =ROUND(P71/$G71,4) -> 0
B72: 01.03.04.02 | C72: ENCOFRADO Y DESENCOFRADO DE MARTILLOS | D72: m2 | E72: 2.8 | F72: 87.93 | G72: =ROUND(E72*F72,2) -> 246.2 | I72: =ROUND(J72/$G72,4) -> 0 | J72: 0 | L72: =ROUND(M72/$G72,4) -> 1 | M72: 246.2 | O72: =ROUND(P72/$G72,4) -> 0
B73: 01.03.04.03 | C73: UÑA DE CONCRETO SUMERGIDOF'c=175 kg/cm2A=0.13m | D73: m | E73: 28 | F73: 51.24 | G73: =ROUND(E73*F73,2) -> 1434.72 | I73: =ROUND(J73/$G73,4) -> 0 | J73: 0 | L73: =ROUND(M73/$G73,4) -> 1 | M73: 1434.72 | O73: =ROUND(P73/$G73,4) -> 0
B74: 01.03.04.04 | C74: CURADO DE CONCRETO | D74: m2 | E74: 64 | F74: 2.92 | G74: =ROUND(E74*F74,2) -> 186.88 | I74: =ROUND(J74/$G74,4) -> 0 | J74: 0 | L74: =ROUND(M74/$G74,4) -> 1 | M74: 186.88 | O74: =ROUND(P74/$G74,4) -> 0
B75: 01.03.05 | C75: NIVELACION DE CONEXIONES DOMICILIARIAS
B76: 01.03.05.01 | C76: NIVELACION DE CONEXIONES DOMICILIARIAS DE AGUA | D76: und | E76: 32 | F76: 202.81 | G76: =ROUND(E76*F76,2) -> 6489.92 | I76: =ROUND(J76/$G76,4) -> 1 | J76: 6489.92 | L76: =ROUND(M76/$G76,4) -> 0 | M76: 0 | O76: =ROUND(P76/$G76,4) -> 0
B77: 01.03.05.02 | C77: NIVELACION DE CONEXIONES DOMICILIARIAS DE DESAGUE | D77: und | E77: 32 | F77: 312.41 | G77: =ROUND(E77*F77,2) -> 9997.12 | I77: =ROUND(J77/$G77,4) -> 1 | J77: 9997.12 | L77: =ROUND(M77/$G77,4) -> 0 | M77: 0 | O77: =ROUND(P77/$G77,4) -> 0
B78: 01.04 | C78: CUNETA PLUVIAL
B79: 01.04.01 | C79: MOVIMIENTO DE TIERRAS HASTA NIVEL DE SUB-RAZANTE
B80: 01.04.01.01 | C80: EXCAVACION EN TERRENO NORMAL | D80: m3 | E80: 43.2 | F80: 56.41 | G80: =ROUND(E80*F80,2) -> 2436.91 | I80: =ROUND(J80/$G80,4) -> 0 | J80: 0 | L80: =ROUND(M80/$G80,4) -> 1 | M80: 2436.91 | O80: =ROUND(P80/$G80,4) -> 0
B81: 01.04.01.02 | C81: RELLENO COMPACTADO CON MATERIAL PROPIO | D81: m3 | E81: 5.5 | F81: 42.31 | G81: =ROUND(E81*F81,2) -> 232.71 | I81: =ROUND(J81/$G81,4) -> 0 | J81: 0 | L81: =ROUND(M81/$G81,4) -> 1 | M81: 232.71 | O81: =ROUND(P81/$G81,4) -> 0
B82: 01.04.01.03 | C82: ACARREO DE MATERIAL EXCEDENTE HASTA 30 M | D82: m3 | E82: 47.13 | F82: 28.21 | G82: =ROUND(E82*F82,2) -> 1329.54 | I82: =ROUND(J82/$G82,4) -> 0 | J82: 0 | L82: =ROUND(M82/$G82,4) -> 1 | M82: 1329.54 | O82: =ROUND(P82/$G82,4) -> 0
B83: 01.04.01.04 | C83: ELIMINACION DE MATERIAL EXCEDENTE C/VOLQUETE DE 15M3 (D=10KM) | D83: m3 | E83: 47.13 | F83: 18.98 | G83: =ROUND(E83*F83,2) -> 894.53 | I83: =ROUND(J83/$G83,4) -> 0 | J83: 0 | L83: =ROUND(M83/$G83,4) -> 1 | M83: 894.53 | O83: =ROUND(P83/$G83,4) -> 0
B84: 01.04.01.05 | C84: CONFORMACIÓN Y COMPACTACIÓN SUBRASANTE C/PLANCHA | D84: m2 | E84: 115.95 | F84: 4.25 | G84: =ROUND(E84*F84,2) -> 492.79 | I84: =ROUND(J84/$G84,4) -> 0 | J84: 0 | L84: =ROUND(M84/$G84,4) -> 1 | M84: 492.79 | O84: =ROUND(P84/$G84,4) -> 0
B85: 01.04.02 | C85: OBRAS DE CONCRETO SIMPLE EN CUNETAS
B86: 01.04.02.01 | C86: ENCOFRADO Y DESENCOFRADO EN CUNETA TRIANGULAR | D86: m2 | E86: 5.76 | F86: 34.68 | G86: =ROUND(E86*F86,2) -> 199.76 | I86: =ROUND(J86/$G86,4) -> 0 | J86: 0 | L86: =ROUND(M86/$G86,4) -> 1 | M86: 199.76 | O86: =ROUND(P86/$G86,4) -> 0
B87: 01.04.02.02 | C87: CONCRETO F'C =175 KG/CM2 EN CUNETA TRIANGULAR | D87: m | E87: 386 | F87: 40.96 | G87: =ROUND(E87*F87,2) -> 15810.56 | I87: =ROUND(J87/$G87,4) -> 0 | J87: 0 | L87: =ROUND(M87/$G87,4) -> 1 | M87: 15810.56 | O87: =ROUND(P87/$G87,4) -> 0
B88: 01.04.02.03 | C88: CURADO DE CONCRETO TRIANGULAR | D88: m2 | E88: 115.8 | F88: 5.86 | G88: =ROUND(E88*F88,2) -> 678.59 | I88: =ROUND(J88/$G88,4) -> 0 | J88: 0 | L88: =ROUND(M88/$G88,4) -> 1 | M88: 678.59 | O88: =ROUND(P88/$G88,4) -> 0
B89: 01.04.02.04 | C89: JUNTA TRANSVERSAL DE DILATACION e=20mm | D89: m | E89: 38.5 | F89: 5.44 | G89: =ROUND(E89*F89,2) -> 209.44 | I89: =ROUND(J89/$G89,4) -> 0 | J89: 0 | L89: =ROUND(M89/$G89,4) -> 1 | M89: 209.44 | O89: =ROUND(P89/$G89,4) -> 0
B90: 01.05 | C90: SARDINELES DE CONCRETO
B91: 01.05.01 | C91: MOVIMIENTO DE TIERRAS HASTA NIVEL DE SUB RAZANTE
B92: 01.05.01.01 | C92: EXCAVACION EN TERRENO NORMAL | D92: m3 | E92: 9 | F92: 56.41 | G92: =ROUND(E92*F92,2) -> 507.69 | I92: =ROUND(J92/$G92,4) -> 0 | J92: 0 | L92: =ROUND(M92/$G92,4) -> 1 | M92: 507.69 | O92: =ROUND(P92/$G92,4) -> 0
B93: 01.05.01.02 | C93: RELLENO COMPACTACION CON MATERIAL PROPIO SELECCIONADO | D93: m3 | E93: 10.75 | F93: 19.04 | G93: =ROUND(E93*F93,2) -> 204.68 | I93: =ROUND(J93/$G93,4) -> 0 | J93: 0 | L93: =ROUND(M93/$G93,4) -> 1 | M93: 204.68 | O93: =ROUND(P93/$G93,4) -> 0
B94: 01.05.01.03 | C94: ACARREO DE MATERIAL EXCEDENTE HASTA 30 M | D94: m3 | E94: 8.75 | F94: 28.21 | G94: =ROUND(E94*F94,2) -> 246.84 | I94: =ROUND(J94/$G94,4) -> 0 | J94: 0 | L94: =ROUND(M94/$G94,4) -> 1 | M94: 246.84 | O94: =ROUND(P94/$G94,4) -> 0
B95: 01.05.01.04 | C95: ELIMINACION DE MATERIAL EXCEDENTE C/VOLQUETE DE 15M3 (D=10KM) | D95: m3 | E95: 8.75 | F95: 18.98 | G95: =ROUND(E95*F95,2) -> 166.08 | I95: =ROUND(J95/$G95,4) -> 0 | J95: 0 | L95: =ROUND(M95/$G95,4) -> 1 | M95: 166.08 | O95: =ROUND(P95/$G95,4) -> 0
B96: 01.05.02 | C96: OBRAS DE CONCRETO EN SARDINEL ARMADO
B97: 01.05.02.01 | C97: ACERO CORRUGADO F'Y=4200 KG/CM2 GRADO 60 | D97: kg | E97: 653.8 | F97: 7.85 | G97: =ROUND(E97*F97,2) -> 5132.33 | I97: =ROUND(J97/$G97,4) -> 0 | J97: 0 | L97: =ROUND(M97/$G97,4) -> 1 | M97: 5132.33 | O97: =ROUND(P97/$G97,4) -> 0
B98: 01.05.02.02 | C98: ENCOFRADO Y DESENCOFRADO EN SARDINELES | D98: m2 | E98: 251.02 | F98: 73.97 | G98: =ROUND(E98*F98,2) -> 18567.95 | I98: =ROUND(J98/$G98,4) -> 0 | J98: 0 | L98: =ROUND(M98/$G98,4) -> 1 | M98: 18567.95 | O98: =ROUND(P98/$G98,4) -> 0
B99: 01.05.02.03 | C99: CONCRETO F'C=175 KG/CM2 PARA SARDINEL (b=0.15m , h=0.40m) ACABADO SOLAQUEADO | D99: m3 | E99: 32.94 | F99: 477.23 | G99: =ROUND(E99*F99,2) -> 15719.96 | I99: =ROUND(J99/$G99,4) -> 0 | J99: 0 | L99: =ROUND(M99/$G99,4) -> 1 | M99: 15719.96 | O99: =ROUND(P99/$G99,4) -> 0
B100: 01.05.02.04 | C100: CURADO DE CONCRETO | D100: m2 | E100: 219.61 | F100: 2.92 | G100: =ROUND(E100*F100,2) -> 641.26 | I100: =ROUND(J100/$G100,4) -> 0 | J100: 0 | L100: =ROUND(M100/$G100,4) -> 1 | M100: 641.26 | O100: =ROUND(P100/$G100,4) -> 0
B101: 01.05.02.05 | C101: JUNTA ASFALTICA | D101: m | E101: 6 | F101: 4.48 | G101: =ROUND(E101*F101,2) -> 26.88 | I101: =ROUND(J101/$G101,4) -> 0 | J101: 0 | L101: =ROUND(M101/$G101,4) -> 1 | M101: 26.88 | O101: =ROUND(P101/$G101,4) -> 0
...

Sheet VAL. MENSUAL
B1: VALORIZACIÓN N°02 DEL MES DE JULIO DE 2026
B2: =+FT!E20 -> CONTRATO DE EJECUCIÓN DE OBRA N°004-2026-MDPM/GM
B3: Obra: | C3: "MEJORAMIENTO Y AMPLIACION DE LOS SERVICIOS DE TRANSITABILIDAD VEHICULAR Y PEATONAL DEL JR LOS PINOS Y JR LOS CEDROS EN CAYHUAYNA Y CAYHUAYNA DEL DISTRITO DE PILLCO MARCA - PROVINCIA DE HUANUCO - DEPARTAMENTO DE HUANUCO" CON CUI N°2536252
B4: Entidad: | C4: MUNICIPALIDAD DISTRITAL DE PILLCO MARCA
B5: Ejecutor: | C5: =+FT!$E$15 -> CONSORCIO EJECUTOR LOS PINOS
B6: Supervisor: | C6: =+FT!$E$34 -> PROYECTA PCL S.A.C | D6: VALOR REFERENCIAL (CON IGV) | G6: 638827.47
B7: Residente: | C7: =+FT!$E$32 -> ING. RAMIREZ BLANCO GABRIEL AUGUSTO HERMOGENES | D7: MONTO DEL CONTRATO (INCL. IGV): | G7: 638827.47
B8: Ing. Supervisor: | C8: =+FT!$E$46 -> ING. CESAR RICARDO ZELADA RODRIGUEZ (CIP N° 98469) | D8: PLAZO DE EJECUCIÓN: | G8: SESENTA (60) DÍAS CALENDARIOS
B10: ITEM | C10: DESCRIPCION | D10: PRESUPUESTO DE OBRA | I10: ACUMULADO ANTERIOR | M10: ACTUAL | Q10: ACUMULADO ACTUAL | U10: SALDO
D11: UND | E11: METRADO | F11: P.UND | G11: TOTAL | I11: METRADO | J11: COSTO (S/) | K11: % | M11: METRADO | N11: COSTO (S/) | O11: % | Q11: METRADO | R11: COSTO (S/) | S11: % | U11: METRADO | V11: COSTO (S/) | W11: %
B12: 01 | C12: CREACION DE PISTAS Y VEREDAS JR LOS CEDROS
B13: 01.01 | C13: OBRAS PROVISIONALES Y TRABAJOS PRELIMINARES
B14: 01.01.01 | C14: OBRAS PROVISIONALES
B15: 01.01.01.01 | C15: ALQUILER DE ALAMACEN, OFICINA Y CASETA DE GUARDIANIA | D15: mes | E15: 2 | F15: 2400 | G15: =ROUND(E15*F15,2) -> 4800 | I15: 1 | J15: 2400 | K15: 0.5 | M15: 0.48 | N15: =ROUND(M15*$F15,2) -> 1152 | O15: =ROUND(N15/$G15,4) -> 0.24 | Q15: =+I15+M15 -> 1.48 | R15: =+J15+N15 -> 3552 | S15: =+K15+O15 -> 0.74 | U15: =+E15-Q15 -> 0.52 | V15: =+G15-R15 -> 1248 | W15: =1-S15 -> 0.26
B16: 01.01.01.02 | C16: CARTEL DE IDENTIFICACION DE LA OBRA DE 3.60 x 4.80 m (SOPORTE DE MADERA) | D16: und | E16: 1 | F16: 1205.49 | G16: =ROUND(E16*F16,2) -> 1205.49 | I16: 1 | J16: 1205.49 | K16: 1 | N16: =ROUND(M16*$F16,2) -> 0 | O16: =ROUND(N16/$G16,4) -> 0 | Q16: =+I16+M16 -> 1 | R16: =+J16+N16 -> 1205.49 | S16: =+K16+O16 -> 1 | U16: =+E16-Q16 -> 0 | V16: =+G16-R16 -> 0 | W16: =1-S16 -> 0
B17: 01.01.01.03 | C17: ALQUILER DE BAÑOS PORTATILES Y LAVADERO | D17: mes | E17: 2 | F17: 850 | G17: =ROUND(E17*F17,2) -> 1700 | I17: 1 | J17: 850 | K17: 0.5 | M17: 0.48 | N17: =ROUND(M17*$F17,2) -> 408 | O17: =ROUND(N17/$G17,4) -> 0.24 | Q17: =+I17+M17 -> 1.48 | R17: =+J17+N17 -> 1258 | S17: =+K17+O17 -> 0.74 | U17: =+E17-Q17 -> 0.52 | V17: =+G17-R17 -> 442 | W17: =1-S17 -> 0.26
B18: 01.01.02 | C18: TRABAJOS PRELIMINARES | G18: =ROUND(E18*F18,2) -> 0
B19: 01.01.02.01 | C19: LIMPIEZA DE TERRENO MANUAL | D19: m2 | E19: 1932.21 | F19: 1.06 | G19: =ROUND(E19*F19,2) -> 2048.14 | I19: 1932.21 | J19: 2048.14 | K19: 1 | N19: =ROUND(M19*$F19,2) -> 0 | O19: =ROUND(N19/$G19,4) -> 0 | Q19: =+I19+M19 -> 1932.21 | R19: =+J19+N19 -> 2048.14 | S19: =+K19+O19 -> 1 | U19: =+E19-Q19 -> 0 | V19: =+G19-R19 -> 0 | W19: =1-S19 -> 0
B20: 01.01.02.02 | C20: TRAZO Y REPLANTEO EN TERRENO NORMAL | D20: m2 | E20: 1932.21 | F20: 4.32 | G20: =ROUND(E20*F20,2) -> 8347.15 | I20: 1932.21 | J20: 8347.15 | K20: 1 | N20: =ROUND(M20*$F20,2) -> 0 | O20: =ROUND(N20/$G20,4) -> 0 | Q20: =+I20+M20 -> 1932.21 | R20: =+J20+N20 -> 8347.15 | S20: =+K20+O20 -> 1 | U20: =+E20-Q20 -> 0 | V20: =+G20-R20 -> 0 | W20: =1-S20 -> 0
B21: 01.01.02.03 | C21: MOVILIZACION Y DESMOVILIZACION DE MAQUINARIA Y EQUIPO | D21: GLB | E21: 1 | F21: 2500 | G21: =ROUND(E21*F21,2) -> 2500 | I21: 1 | J21: 2500 | K21: 1 | N21: =ROUND(M21*$F21,2) -> 0 | O21: =ROUND(N21/$G21,4) -> 0 | Q21: =+I21+M21 -> 1 | R21: =+J21+N21 -> 2500 | S21: =+K21+O21 -> 1 | U21: =+E21-Q21 -> 0 | V21: =+G21-R21 -> 0 | W21: =1-S21 -> 0
B22: 01.01.03 | C22: DEMOLICIONES | G22: =ROUND(E22*F22,2) -> 0
B23: 01.01.03.01 | C23: DEMOLICION DE VEREDAS EXISTENTES DE 0.10M | D23: m2 | E23: 135.5 | F23: 21.33 | G23: =ROUND(E23*F23,2) -> 2890.22 | I23: 135.5 | J23: 2890.22 | K23: 1 | N23: =ROUND(M23*$F23,2) -> 0 | O23: =ROUND(N23/$G23,4) -> 0 | Q23: =+I23+M23 -> 135.5 | R23: =+J23+N23 -> 2890.22 | S23: =+K23+O23 -> 1 | U23: =+E23-Q23 -> 0 | V23: =+G23-R23 -> 0 | W23: =1-S23 -> 0
B24: 01.01.03.02 | C24: ELIMINACION DE MATERIAL EXCEDENTE C/VOLQUETE DE 15M3 (D=10 KM) | D24: m3 | E24: 20.33 | F24: 18.98 | G24: =ROUND(E24*F24,2) -> 385.86 | I24: 20.33 | J24: 385.86 | K24: 1 | N24: =ROUND(M24*$F24,2) -> 0 | O24: =ROUND(N24/$G24,4) -> 0 | Q24: =+I24+M24 -> 20.33 | R24: =+J24+N24 -> 385.86 | S24: =+K24+O24 -> 1 | U24: =+E24-Q24 -> 0 | V24: =+G24-R24 -> 0 | W24: =1-S24 -> 0
B25: 01.01.04 | C25: PLAN DE DESVIO VEHICULAR
B26: 01.01.04.01 | C26: TRANQUERAS DE MADERA 2.40 x 1.20 | D26: und | E26: 2 | F26: 221.35 | G26: =ROUND(E26*F26,2) -> 442.7 | I26: 2 | J26: 442.7 | K26: 1 | N26: =ROUND(M26*$F26,2) -> 0 | O26: =ROUND(N26/$G26,4) -> 0 | Q26: =+I26+M26 -> 2 | R26: =+J26+N26 -> 442.7 | S26: =+K26+O26 -> 1 | U26: =+E26-Q26 -> 0 | V26: =+G26-R26 -> 0 | W26: =1-S26 -> 0
B27: 01.01.04.02 | C27: SEÑALIZACION DE DESVIO DE TRANSITO EN PERIODO DE CONSTRUCCION | D27: GLB | E27: 1 | F27: 221.16 | G27: =ROUND(E27*F27,2) -> 221.16 | I27: 1 | J27: 221.16 | K27: 1 | N27: =ROUND(M27*$F27,2) -> 0 | O27: =ROUND(N27/$G27,4) -> 0 | Q27: =+I27+M27 -> 1 | R27: =+J27+N27 -> 221.16 | S27: =+K27+O27 -> 1 | U27: =+E27-Q27 -> 0 | V27: =+G27-R27 -> 0 | W27: =1-S27 -> 0
B28: 01.02 | C28: PAVIMENTO RIGIDO | G28: =ROUND(E28*F28,2) -> 0
B29: 01.02.01 | C29: MOVIMIENTO DE TIERRAS HASTA EL NIVEL DE SUB - RASANTE
B30: 01.02.01.01 | C30: CORTE EN TERRENO NORMAL CON MAQUINARIA | D30: m3 | E30: 590.54 | F30: 10.47 | G30: =ROUND(E30*F30,2) -> 6182.95 | I30: 590.54 | J30: 6182.95 | K30: 1 | N30: =ROUND(M30*$F30,2) -> 0 | O30: =ROUND(N30/$G30,4) -> 0 | Q30: =+I30+M30 -> 590.54 | R30: =+J30+N30 -> 6182.95 | S30: =+K30+O30 -> 1 | U30: =+E30-Q30 -> 0 | V30: =+G30-R30 -> 0 | W30: =1-S30 -> 0
B31: 01.02.01.02 | C31: RELLENO COMPACTACION CON MATERIAL PROPIO SELECCIONADO | D31: m3 | E31: 51.64 | F31: 19.04 | G31: =ROUND(E31*F31,2) -> 983.23 | I31: 51.64 | J31: 983.23 | K31: 1 | N31: =ROUND(M31*$F31,2) -> 0 | O31: =ROUND(N31/$G31,4) -> 0 | Q31: =+I31+M31 -> 51.64 | R31: =+J31+N31 -> 983.23 | S31: =+K31+O31 -> 1 | U31: =+E31-Q31 -> 0 | V31: =+G31-R31 -> 0 | W31: =1-S31 -> 0
B32: 01.02.01.03 | C32: ELIMINACION DE MATERIAL EXCEDENTE C/VOLQUETE DE 15M3 (D=10KM) | D32: m3 | E32: 738.18 | F32: 18.98 | G32: =ROUND(E32*F32,2) -> 14010.66 | I32: 738.18 | J32: 14010.66 | K32: 1 | N32: =ROUND(M32*$F32,2) -> 0 | O32: =ROUND(N32/$G32,4) -> 0 | Q32: =+I32+M32 -> 738.18 | R32: =+J32+N32 -> 14010.66 | S32: =+K32+O32 -> 1 | U32: =+E32-Q32 -> 0 | V32: =+G32-R32 -> 0 | W32: =1-S32 -> 0
B33: 01.02.02 | C33: BASE | G33: =ROUND(E33*F33,2) -> 0
B34: 01.02.02.01 | C34: CONFORMACION DE BASE MATERIAL MEZCLADO E=0.20m | D34: m2 | E34: 910.14 | F34: 31.15 | G34: =ROUND(E34*F34,2) -> 28350.86 | I34: 910.14 | J34: 28350.86 | K34: 1 | N34: =ROUND(M34*$F34,2) -> 0 | O34: =ROUND(N34/$G34,4) -> 0 | Q34: =+I34+M34 -> 910.14 | R34: =+J34+N34 -> 28350.86 | S34: =+K34+O34 -> 1 | U34: =+E34-Q34 -> 0 | V34: =+G34-R34 -> 0 | W34: =1-S34 -> 0
B35: 01.02.03 | C35: SUB RASANTE | G35: =ROUND(E35*F35,2) -> 0
B36: 01.02.03.01 | C36: PERFILADO, RIEGO Y COMPACTACIÓN DE SUBRASANTE | D36: m2 | E36: 910.14 | F36: 5.54 | G36: =ROUND(E36*F36,2) -> 5042.18 | I36: 910.14 | J36: 5042.18 | K36: 1 | N36: =ROUND(M36*$F36,2) -> 0 | O36: =ROUND(N36/$G36,4) -> 0 | Q36: =+I36+M36 -> 910.14 | R36: =+J36+N36 -> 5042.18 | S36: =+K36+O36 -> 1 | U36: =+E36-Q36 -> 0 | V36: =+G36-R36 -> 0 | W36: =1-S36 -> 0
B37: 01.02.04 | C37: OBRAS DE CONCRETO | G37: =ROUND(E37*F37,2) -> 0
B38: 01.02.04.01 | C38: ENCOFRADO Y DESENCOFRADO EN PAVIMENTOS | D38: m2 | E38: 127.29 | F38: 63.41 | G38: =ROUND(E38*F38,2) -> 8071.46 | I38: 127.29 | J38: 8071.46 | K38: 1 | N38: =ROUND(M38*$F38,2) -> 0 | O38: =ROUND(N38/$G38,4) -> 0 | Q38: =+I38+M38 -> 127.29 | R38: =+J38+N38 -> 8071.46 | S38: =+K38+O38 -> 1 | U38: =+E38-Q38 -> 0 | V38: =+G38-R38 -> 0 | W38: =1-S38 -> 0
B39: 01.02.04.02 | C39: CONCRETO F'C =210 KG/CM2 EN VIA E=15CM | D39: m2 | E39: 910.14 | F39: 119.99 | G39: =ROUND(E39*F39,2) -> 109207.7 | I39: 910.14 | J39: 109207.7 | K39: 1 | N39: =ROUND(M39*$F39,2) -> 0 | O39: =ROUND(N39/$G39,4) -> 0 | Q39: =+I39+M39 -> 910.14 | R39: =+J39+N39 -> 109207.7 | S39: =+K39+O39 -> 1 | U39: =+E39-Q39 -> 0 | V39: =+G39-R39 -> 0 | W39: =1-S39 -> 0
B40: 01.02.04.03 | C40: CURADO DE CONCRETO | D40: m2 | E40: 910.14 | F40: 2.92 | G40: =ROUND(E40*F40,2) -> 2657.61 | I40: 910.14 | J40: 2657.61 | K40: 1 | N40: =ROUND(M40*$F40,2) -> 0 | O40: =ROUND(N40/$G40,4) -> 0 | Q40: =+I40+M40 -> 910.14 | R40: =+J40+N40 -> 2657.61 | S40: =+K40+O40 -> 1 | U40: =+E40-Q40 -> 0 | V40: =+G40-R40 -> 0 | W40: =1-S40 -> 0
B41: 01.02.04.04 | C41: ACERO FY = 4200Kg/cm2 EN JUNTAS DE DILATACION LONGITUDINAL Ø 3/8" | D41: kg | E41: 80.64 | F41: 12.14 | G41: =ROUND(E41*F41,2) -> 978.97 | I41: 80.64 | J41: 978.97 | K41: 1 | N41: =ROUND(M41*$F41,2) -> 0 | O41: =ROUND(N41/$G41,4) -> 0 | Q41: =+I41+M41 -> 80.64 | R41: =+J41+N41 -> 978.97 | S41: =+K41+O41 -> 1 | U41: =+E41-Q41 -> 0 | V41: =+G41-R41 -> 0 | W41: =1-S41 -> 0
B42: 01.02.04.05 | C42: ACERO FY = 2400Kg/cm2 GRADO 60 EN JUNTAS DE DILATACION TRANSVERSAL Ø 3/4" | D42: kg | E42: 176.4 | F42: 42.88 | G42: =ROUND(E42*F42,2) -> 7564.03 | I42: 176.4 | J42: 7564.03 | K42: 1 | N42: =ROUND(M42*$F42,2) -> 0 | O42: =ROUND(N42/$G42,4) -> 0 | Q42: =+I42+M42 -> 176.4 | R42: =+J42+N42 -> 7564.03 | S42: =+K42+O42 -> 1 | U42: =+E42-Q42 -> 0 | V42: =+G42-R42 -> 0 | W42: =1-S42 -> 0
B43: 01.02.04.06 | C43: JUNTA DE AISLAMIENTO e=1" X 0.20 m | D43: m | E43: 360 | F43: 5.59 | G43: =ROUND(E43*F43,2) -> 2012.4 | I43: 360 | J43: 2012.4 | K43: 1 | N43: =ROUND(M43*$F43,2) -> 0 | O43: =ROUND(N43/$G43,4) -> 0 | Q43: =+I43+M43 -> 360 | R43: =+J43+N43 -> 2012.4 | S43: =+K43+O43 -> 1 | U43: =+E43-Q43 -> 0 | V43: =+G43-R43 -> 0 | W43: =1-S43 -> 0
B44: 01.02.04.07 | C44: JUNTA DE DILATACION e=1" X 0.10 m | D44: m | E44: 255 | F44: 5.59 | G44: =ROUND(E44*F44,2) -> 1425.45 | I44: 255 | J44: 1425.45 | K44: 1 | N44: =ROUND(M44*$F44,2) -> 0 | O44: =ROUND(N44/$G44,4) -> 0 | Q44: =+I44+M44 -> 255 | R44: =+J44+N44 -> 1425.45 | S44: =+K44+O44 -> 1 | U44: =+E44-Q44 -> 0 | V44: =+G44-R44 -> 0 | W44: =1-S44 -> 0
B45: 01.02.04.08 | C45: JUNTAS DE CONTRACCION CON ELASTOMERICO DE POLIURETANO E=1/2" X 0.10m | D45: m | E45: 150 | F45: 19.22 | G45: =ROUND(E45*F45,2) -> 2883 | I45: 150 | J45: 2883 | K45: 1 | N45: =ROUND(M45*$F45,2) -> 0 | O45: =ROUND(N45/$G45,4) -> 0 | Q45: =+I45+M45 -> 150 | R45: =+J45+N45 -> 2883 | S45: =+K45+O45 -> 1 | U45: =+E45-Q45 -> 0 | V45: =+G45-R45 -> 0 | W45: =1-S45 -> 0
B46: 01.02.05 | C46: NIVELACION DE BUZONES | G46: =ROUND(E46*F46,2) -> 0
B47: 01.02.05.01 | C47: NIVELACION DE BUZONES EN GENERAL | D47: und | E47: 3 | F47: 471.14 | G47: =ROUND(E47*F47,2) -> 1413.42 | I47: 3 | J47: 1413.42 | K47: 1 | N47: =ROUND(M47*$F47,2) -> 0 | O47: =ROUND(N47/$G47,4) -> 0 | Q47: =+I47+M47 -> 3 | R47: =+J47+N47 -> 1413.42 | S47: =+K47+O47 -> 1 | U47: =+E47-Q47 -> 0 | V47: =+G47-R47 -> 0 | W47: =1-S47 -> 0
B48: 01.02.06 | C48: SEÑALIZACION | G48: =ROUND(E48*F48,2) -> 0
B49: 01.02.06.01 | C49: PINTURA EN PAVIMENTO (SIMBOLO Y LETRA) | D49: m2 | E49: 50.6 | F49: 38.21 | G49: =ROUND(E49*F49,2) -> 1933.43 | J49: 0 | K49: 0 | N49: =ROUND(M49*$F49,2) -> 0 | O49: =ROUND(N49/$G49,4) -> 0 | Q49: =+I49+M49 -> 0 | R49: =+J49+N49 -> 0 | S49: =+K49+O49 -> 0 | U49: =+E49-Q49 -> 50.6 | V49: =+G49-R49 -> 1933.43 | W49: =1-S49 -> 1
B50: 01.02.06.02 | C50: PINTURA DE PAVIMENTO (LINEAS DISCONTINUAS CENTRALES) | D50: m | E50: 170 | F50: 10.43 | G50: =ROUND(E50*F50,2) -> 1773.1 | J50: 0 | K50: 0 | N50: =ROUND(M50*$F50,2) -> 0 | O50: =ROUND(N50/$G50,4) -> 0 | Q50: =+I50+M50 -> 0 | R50: =+J50+N50 -> 0 | S50: =+K50+O50 -> 0 | U50: =+E50-Q50 -> 170 | V50: =+G50-R50 -> 1773.1 | W50: =1-S50 -> 1
B51: 01.02.06.03 | C51: SEÑALIZACION VERTICAL | D51: und | E51: 4 | F51: 361.47 | G51: =ROUND(E51*F51,2) -> 1445.88 | J51: 0 | K51: 0 | N51: =ROUND(M51*$F51,2) -> 0 | O51: =ROUND(N51/$G51,4) -> 0 | Q51: =+I51+M51 -> 0 | R51: =+J51+N51 -> 0 | S51: =+K51+O51 -> 0 | U51: =+E51-Q51 -> 4 | V51: =+G51-R51 -> 1445.88 | W51: =1-S51 -> 1
B52: 01.03 | C52: VEREDAS, RAMPAS Y MARTILLOS | G52: =ROUND(E52*F52,2) -> 0
B53: 01.03.01 | C53: MOVIMIENTO DE TIERRAS HASTA EL NIVEL DE SUB - RASANTE
B54: 01.03.01.01 | C54: EXCAVACION EN TERRENO NORMAL C/MAQUINARIA LIVIANA | D54: m3 | E54: 56.3 | F54: 22.11 | G54: =ROUND(E54*F54,2) -> 1244.79 | I54: 56.3 | J54: 1244.79 | K54: 1 | N54: =ROUND(M54*$F54,2) -> 0 | O54: =ROUND(N54/$G54,4) -> 0 | Q54: =+I54+M54 -> 56.3 | R54: =+J54+N54 -> 1244.79 | S54: =+K54+O54 -> 1 | U54: =+E54-Q54 -> 0 | V54: =+G54-R54 -> 0 | W54: =1-S54 -> 0
B55: 01.03.01.02 | C55: RELLENO Y COMPACTACION CON MATERIAL PROPIO SELECCIONADO | D55: m3 | E55: 12 | F55: 42.31 | G55: =ROUND(E55*F55,2) -> 507.72 | I55: 12 | J55: 507.72 | K55: 1 | N55: =ROUND(M55*$F55,2) -> 0 | O55: =ROUND(N55/$G55,4) -> 0 | Q55: =+I55+M55 -> 12 | R55: =+J55+N55 -> 507.72 | S55: =+K55+O55 -> 1 | U55: =+E55-Q55 -> 0 | V55: =+G55-R55 -> 0 | W55: =1-S55 -> 0
B56: 01.03.01.03 | C56: ELIMINACION DE MATERIAL EXCEDENTE C/VOLQUETE DE 15M3 (D=10KM) | D56: m3 | E56: 55.38 | F56: 18.98 | G56: =ROUND(E56*F56,2) -> 1051.11 | I56: 55.38 | J56: 1051.11 | K56: 1 | N56: =ROUND(M56*$F56,2) -> 0 | O56: =ROUND(N56/$G56,4) -> 0 | Q56: =+I56+M56 -> 55.38 | R56: =+J56+N56 -> 1051.11 | S56: =+K56+O56 -> 1 | U56: =+E56-Q56 -> 0 | V56: =+G56-R56 -> 0 | W56: =1-S56 -> 0
B57: 01.03.01.04 | C57: PERFILADO Y COMPACTADO CON PLANCHA | D57: m2 | E57: 547.38 | F57: 4.25 | G57: =ROUND(E57*F57,2) -> 2326.37 | I57: 547.38 | J57: 2326.37 | K57: 1 | N57: =ROUND(M57*$F57,2) -> 0 | O57: =ROUND(N57/$G57,4) -> 0 | Q57: =+I57+M57 -> 547.38 | R57: =+J57+N57 -> 2326.37 | S57: =+K57+O57 -> 1 | U57: =+E57-Q57 -> 0 | V57: =+G57-R57 -> 0 | W57: =1-S57 -> 0
B58: 01.03.01.05 | C58: CONFORMACIÓN Y COMPACTACIÓN DE BASE EN VEREDAS Y RAMPAS (e=10cm) | D58: m2 | E58: 547.38 | F58: 16.02 | G58: =ROUND(E58*F58,2) -> 8769.03 | I58: 547.38 | J58: 8769.03 | K58: 1 | N58: =ROUND(M58*$F58,2) -> 0 | O58: =ROUND(N58/$G58,4) -> 0 | Q58: =+I58+M58 -> 547.38 | R58: =+J58+N58 -> 8769.03 | S58: =+K58+O58 -> 1 | U58: =+E58-Q58 -> 0 | V58: =+G58-R58 -> 0 | W58: =1-S58 -> 0
B59: 01.03.02 | C59: OBRAS DE CONCRETO EN VEREDAS | G59: =ROUND(E59*F59,2) -> 0
B60: 01.03.02.01 | C60: ENCOFRADO Y DESENCOFRADO EN VEREDAS | D60: m2 | E60: 55.28 | F60: 72.37 | G60: =ROUND(E60*F60,2) -> 4000.61 | J60: 0 | K60: 0 | M60: =+E60 -> 55.28 | N60: =ROUND(M60*$F60,2) -> 4000.61 | O60: =ROUND(N60/$G60,4) -> 1 | Q60: =+I60+M60 -> 55.28 | R60: =+J60+N60 -> 4000.61 | S60: =+K60+O60 -> 1 | U60: =+E60-Q60 -> 0 | V60: =+G60-R60 -> 0 | W60: =1-S60 -> 0
B61: 01.03.02.02 | C61: CONCRETO F'c=175 kg/cm2 (E=4") EN VEREDA CON ACABADO FROTACHADO Y BRUÑADO S/DISEÑO | D61: m2 | E61: 547.38 | F61: 49.11 | G61: =ROUND(E61*F61,2) -> 26881.83 | J61: 0 | K61: 0 | M61: =+E61 -> 547.38 | N61: =ROUND(M61*$F61,2) -> 26881.83 | O61: =ROUND(N61/$G61,4) -> 1 | Q61: =+I61+M61 -> 547.38 | R61: =+J61+N61 -> 26881.83 | S61: =+K61+O61 -> 1 | U61: =+E61-Q61 -> 0 | V61: =+G61-R61 -> 0 | W61: =1-S61 -> 0
B62: 01.03.02.03 | C62: CONCRETO F'c=175 kg/cm2 PARA UÑA EN VEREDA (A=0.025 m2) | D62: m | E62: 404 | F62: 16.32 | G62: =ROUND(E62*F62,2) -> 6593.28 | J62: 0 | K62: 0 | M62: =+E62 -> 404 | N62: =ROUND(M62*$F62,2) -> 6593.28 | O62: =ROUND(N62/$G62,4) -> 1 | Q62: =+I62+M62 -> 404 | R62: =+J62+N62 -> 6593.28 | S62: =+K62+O62 -> 1 | U62: =+E62-Q62 -> 0 | V62: =+G62-R62 -> 0 | W62: =1-S62 -> 0
B63: 01.03.02.04 | C63: CURADO DE CONCRETO | E63: 547.38 | F63: 2.92 | G63: =ROUND(E63*F63,2) -> 1598.35 | J63: 0 | K63: 0 | M63: =+E63 -> 547.38 | N63: =ROUND(M63*$F63,2) -> 1598.35 | O63: =ROUND(N63/$G63,4) -> 1 | Q63: =+I63+M63 -> 547.38 | R63: =+J63+N63 -> 1598.35 | S63: =+K63+O63 -> 1 | U63: =+E63-Q63 -> 0 | V63: =+G63-R63 -> 0 | W63: =1-S63 -> 0
B64: 01.03.02.05 | C64: JUNTA ASFALTICA | D64: m | E64: 158.4 | F64: 4.48 | G64: =ROUND(E64*F64,2) -> 709.63 | J64: 0 | K64: 0 | M64: =+E64 -> 158.4 | N64: =ROUND(M64*$F64,2) -> 709.63 | O64: =ROUND(N64/$G64,4) -> 1 | Q64: =+I64+M64 -> 158.4 | R64: =+J64+N64 -> 709.63 | S64: =+K64+O64 -> 1 | U64: =+E64-Q64 -> 0 | V64: =+G64-R64 -> 0 | W64: =1-S64 -> 0
B65: 01.03.03 | C65: OBRAS DE CONCRETO EN RAMPA | G65: =ROUND(E65*F65,2) -> 0
B66: 01.03.03.01 | C66: ENCOFRADO Y DESENCOFRADO EN RAMPAS | D66: m2 | E66: 16.25 | F66: 46.94 | G66: =ROUND(E66*F66,2) -> 762.78 | J66: 0 | K66: 0 | M66: =+E66 -> 16.25 | N66: =ROUND(M66*$F66,2) -> 762.78 | O66: =ROUND(N66/$G66,4) -> 1 | Q66: =+I66+M66 -> 16.25 | R66: =+J66+N66 -> 762.78 | S66: =+K66+O66 -> 1 | U66: =+E66-Q66 -> 0 | V66: =+G66-R66 -> 0 | W66: =1-S66 -> 0
B67: 01.03.03.02 | C67: CONCRETO F'c=175 KG/CM2, ACABADO 1:2 BRUÑADO Y FROTACHADO | D67: m2 | E67: 86.65 | F67: 53.06 | G67: =ROUND(E67*F67,2) -> 4597.65 | J67: 0 | K67: 0 | M67: =+E67 -> 86.65 | N67: =ROUND(M67*$F67,2) -> 4597.65 | O67: =ROUND(N67/$G67,4) -> 1 | Q67: =+I67+M67 -> 86.65 | R67: =+J67+N67 -> 4597.65 | S67: =+K67+O67 -> 1 | U67: =+E67-Q67 -> 0 | V67: =+G67-R67 -> 0 | W67: =1-S67 -> 0
B68: 01.03.03.03 | C68: CURADO DE CONCRETO EN RAMPA | D68: m2 | E68: 86.65 | F68: 2.92 | G68: =ROUND(E68*F68,2) -> 253.02 | J68: 0 | K68: 0 | M68: =+E68 -> 86.65 | N68: =ROUND(M68*$F68,2) -> 253.02 | O68: =ROUND(N68/$G68,4) -> 1 | Q68: =+I68+M68 -> 86.65 | R68: =+J68+N68 -> 253.02 | S68: =+K68+O68 -> 1 | U68: =+E68-Q68 -> 0 | V68: =+G68-R68 -> 0 | W68: =1-S68 -> 0
B69: 01.03.03.04 | C69: JUNTA ASFALTICA | D69: m | E69: 110 | F69: 4.48 | G69: =ROUND(E69*F69,2) -> 492.8 | J69: 0 | K69: 0 | M69: =+E69 -> 110 | N69: =ROUND(M69*$F69,2) -> 492.8 | O69: =ROUND(N69/$G69,4) -> 1 | Q69: =+I69+M69 -> 110 | R69: =+J69+N69 -> 492.8 | S69: =+K69+O69 -> 1 | U69: =+E69-Q69 -> 0 | V69: =+G69-R69 -> 0 | W69: =1-S69 -> 0
B70: 01.03.04 | C70: OBRAS DE CONCRETO EN MARTILLO
B71: 01.03.04.01 | C71: CONCRETO F'c=175 KG/CM2, ACABADO FROTACHADO | D71: m2 | E71: 64 | F71: 49.11 | G71: =ROUND(E71*F71,2) -> 3143.04 | J71: 0 | K71: 0 | M71: =+E71 -> 64 | N71: =ROUND(M71*$F71,2) -> 3143.04 | O71: =ROUND(N71/$G71,4) -> 1 | Q71: =+I71+M71 -> 64 | R71: =+J71+N71 -> 3143.04 | S71: =+K71+O71 -> 1 | U71: =+E71-Q71 -> 0 | V71: =+G71-R71 -> 0 | W71: =1-S71 -> 0
B72: 01.03.04.02 | C72: ENCOFRADO Y DESENCOFRADO DE MARTILLOS | D72: m2 | E72: 2.8 | F72: 87.93 | G72: =ROUND(E72*F72,2) -> 246.2 | J72: 0 | K72: 0 | M72: =+E72 -> 2.8 | N72: =ROUND(M72*$F72,2) -> 246.2 | O72: =ROUND(N72/$G72,4) -> 1 | Q72: =+I72+M72 -> 2.8 | R72: =+J72+N72 -> 246.2 | S72: =+K72+O72 -> 1 | U72: =+E72-Q72 -> 0 | V72: =+G72-R72 -> 0 | W72: =1-S72 -> 0
B73: 01.03.04.03 | C73: UÑA DE CONCRETO SUMERGIDOF'c=175 kg/cm2A=0.13m | D73: m | E73: 28 | F73: 51.24 | G73: =ROUND(E73*F73,2) -> 1434.72 | J73: 0 | K73: 0 | M73: =+E73 -> 28 | N73: =ROUND(M73*$F73,2) -> 1434.72 | O73: =ROUND(N73/$G73,4) -> 1 | Q73: =+I73+M73 -> 28 | R73: =+J73+N73 -> 1434.72 | S73: =+K73+O73 -> 1 | U73: =+E73-Q73 -> 0 | V73: =+G73-R73 -> 0 | W73: =1-S73 -> 0
B74: 01.03.04.04 | C74: CURADO DE CONCRETO | D74: m2 | E74: 64 | F74: 2.92 | G74: =ROUND(E74*F74,2) -> 186.88 | J74: 0 | K74: 0 | M74: =+E74 -> 64 | N74: =ROUND(M74*$F74,2) -> 186.88 | O74: =ROUND(N74/$G74,4) -> 1 | Q74: =+I74+M74 -> 64 | R74: =+J74+N74 -> 186.88 | S74: =+K74+O74 -> 1 | U74: =+E74-Q74 -> 0 | V74: =+G74-R74 -> 0 | W74: =1-S74 -> 0
B75: 01.03.05 | C75: NIVELACION DE CONEXIONES DOMICILIARIAS
B76: 01.03.05.01 | C76: NIVELACION DE CONEXIONES DOMICILIARIAS DE AGUA | D76: und | E76: 32 | F76: 202.81 | G76: =ROUND(E76*F76,2) -> 6489.92 | I76: 32 | J76: 6489.92 | K76: 1 | N76: =ROUND(M76*$F76,2) -> 0 | O76: =ROUND(N76/$G76,4) -> 0 | Q76: =+I76+M76 -> 32 | R76: =+J76+N76 -> 6489.92 | S76: =+K76+O76 -> 1 | U76: =+E76-Q76 -> 0 | V76: =+G76-R76 -> 0 | W76: =1-S76 -> 0
B77: 01.03.05.02 | C77: NIVELACION DE CONEXIONES DOMICILIARIAS DE DESAGUE | D77: und | E77: 32 | F77: 312.41 | G77: =ROUND(E77*F77,2) -> 9997.12 | I77: 32 | J77: 9997.12 | K77: 1 | N77: =ROUND(M77*$F77,2) -> 0 | O77: =ROUND(N77/$G77,4) -> 0 | Q77: =+I77+M77 -> 32 | R77: =+J77+N77 -> 9997.12 | S77: =+K77+O77 -> 1 | U77: =+E77-Q77 -> 0 | V77: =+G77-R77 -> 0 | W77: =1-S77 -> 0
B78: 01.04 | C78: CUNETA PLUVIAL
B79: 01.04.01 | C79: MOVIMIENTO DE TIERRAS HASTA NIVEL DE SUB-RAZANTE
B80: 01.04.01.01 | C80: EXCAVACION EN TERRENO NORMAL | D80: m3 | E80: 43.2 | F80: 56.41 | G80: =ROUND(E80*F80,2) -> 2436.91 | J80: 0 | K80: 0 | M80: =+E80 -> 43.2 | N80: =ROUND(M80*$F80,2) -> 2436.91 | O80: =ROUND(N80/$G80,4) -> 1 | Q80: =+I80+M80 -> 43.2 | R80: =+J80+N80 -> 2436.91 | S80: =+K80+O80 -> 1 | U80: =+E80-Q80 -> 0 | V80: =+G80-R80 -> 0 | W80: =1-S80 -> 0
B81: 01.04.01.02 | C81: RELLENO COMPACTADO CON MATERIAL PROPIO | D81: m3 | E81: 5.5 | F81: 42.31 | G81: =ROUND(E81*F81,2) -> 232.71 | J81: 0 | K81: 0 | M81: =+E81 -> 5.5 | N81: =ROUND(M81*$F81,2) -> 232.71 | O81: =ROUND(N81/$G81,4) -> 1 | Q81: =+I81+M81 -> 5.5 | R81: =+J81+N81 -> 232.71 | S81: =+K81+O81 -> 1 | U81: =+E81-Q81 -> 0 | V81: =+G81-R81 -> 0 | W81: =1-S81 -> 0
B82: 01.04.01.03 | C82: ACARREO DE MATERIAL EXCEDENTE HASTA 30 M | D82: m3 | E82: 47.13 | F82: 28.21 | G82: =ROUND(E82*F82,2) -> 1329.54 | J82: 0 | K82: 0 | M82: =+E82 -> 47.13 | N82: =ROUND(M82*$F82,2) -> 1329.54 | O82: =ROUND(N82/$G82,4) -> 1 | Q82: =+I82+M82 -> 47.13 | R82: =+J82+N82 -> 1329.54 | S82: =+K82+O82 -> 1 | U82: =+E82-Q82 -> 0 | V82: =+G82-R82 -> 0 | W82: =1-S82 -> 0
B83: 01.04.01.04 | C83: ELIMINACION DE MATERIAL EXCEDENTE C/VOLQUETE DE 15M3 (D=10KM) | D83: m3 | E83: 47.13 | F83: 18.98 | G83: =ROUND(E83*F83,2) -> 894.53 | J83: 0 | K83: 0 | M83: =+E83 -> 47.13 | N83: =ROUND(M83*$F83,2) -> 894.53 | O83: =ROUND(N83/$G83,4) -> 1 | Q83: =+I83+M83 -> 47.13 | R83: =+J83+N83 -> 894.53 | S83: =+K83+O83 -> 1 | U83: =+E83-Q83 -> 0 | V83: =+G83-R83 -> 0 | W83: =1-S83 -> 0
B84: 01.04.01.05 | C84: CONFORMACIÓN Y COMPACTACIÓN SUBRASANTE C/PLANCHA | D84: m2 | E84: 115.95 | F84: 4.25 | G84: =ROUND(E84*F84,2) -> 492.79 | J84: 0 | K84: 0 | M84: =+E84 -> 115.95 | N84: =ROUND(M84*$F84,2) -> 492.79 | O84: =ROUND(N84/$G84,4) -> 1 | Q84: =+I84+M84 -> 115.95 | R84: =+J84+N84 -> 492.79 | S84: =+K84+O84 -> 1 | U84: =+E84-Q84 -> 0 | V84: =+G84-R84 -> 0 | W84: =1-S84 -> 0
B85: 01.04.02 | C85: OBRAS DE CONCRETO SIMPLE EN CUNETAS
B86: 01.04.02.01 | C86: ENCOFRADO Y DESENCOFRADO EN CUNETA TRIANGULAR | D86: m2 | E86: 5.76 | F86: 34.68 | G86: =ROUND(E86*F86,2) -> 199.76 | J86: 0 | K86: 0 | M86: =+E86 -> 5.76 | N86: =ROUND(M86*$F86,2) -> 199.76 | O86: =ROUND(N86/$G86,4) -> 1 | Q86: =+I86+M86 -> 5.76 | R86: =+J86+N86 -> 199.76 | S86: =+K86+O86 -> 1 | U86: =+E86-Q86 -> 0 | V86: =+G86-R86 -> 0 | W86: =1-S86 -> 0
B87: 01.04.02.02 | C87: CONCRETO F'C =175 KG/CM2 EN CUNETA TRIANGULAR | D87: m | E87: 386 | F87: 40.96 | G87: =ROUND(E87*F87,2) -> 15810.56 | J87: 0 | K87: 0 | M87: =+E87 -> 386 | N87: =ROUND(M87*$F87,2) -> 15810.56 | O87: =ROUND(N87/$G87,4) -> 1 | Q87: =+I87+M87 -> 386 | R87: =+J87+N87 -> 15810.56 | S87: =+K87+O87 -> 1 | U87: =+E87-Q87 -> 0 | V87: =+G87-R87 -> 0 | W87: =1-S87 -> 0
B88: 01.04.02.03 | C88: CURADO DE CONCRETO TRIANGULAR | D88: m2 | E88: 115.8 | F88: 5.86 | G88: =ROUND(E88*F88,2) -> 678.59 | J88: 0 | K88: 0 | M88: =+E88 -> 115.8 | N88: =ROUND(M88*$F88,2) -> 678.59 | O88: =ROUND(N88/$G88,4) -> 1 | Q88: =+I88+M88 -> 115.8 | R88: =+J88+N88 -> 678.59 | S88: =+K88+O88 -> 1 | U88: =+E88-Q88 -> 0 | V88: =+G88-R88 -> 0 | W88: =1-S88 -> 0
B89: 01.04.02.04 | C89: JUNTA TRANSVERSAL DE DILATACION e=20mm | D89: m | E89: 38.5 | F89: 5.44 | G89: =ROUND(E89*F89,2) -> 209.44 | J89: 0 | K89: 0 | M89: =+E89 -> 38.5 | N89: =ROUND(M89*$F89,2) -> 209.44 | O89: =ROUND(N89/$G89,4) -> 1 | Q89: =+I89+M89 -> 38.5 | R89: =+J89+N89 -> 209.44 | S89: =+K89+O89 -> 1 | U89: =+E89-Q89 -> 0 | V89: =+G89-R89 -> 0 | W89: =1-S89 -> 0
B90: 01.05 | C90: SARDINELES DE CONCRETO
B91: 01.05.01 | C91: MOVIMIENTO DE TIERRAS HASTA NIVEL DE SUB RAZANTE
B92: 01.05.01.01 | C92: EXCAVACION EN TERRENO NORMAL | D92: m3 | E92: 9 | F92: 56.41 | G92: =ROUND(E92*F92,2) -> 507.69 | J92: 0 | K92: 0 | M92: =+E92 -> 9 | N92: =ROUND(M92*$F92,2) -> 507.69 | O92: =ROUND(N92/$G92,4) -> 1 | Q92: =+I92+M92 -> 9 | R92: =+J92+N92 -> 507.69 | S92: =+K92+O92 -> 1 | U92: =+E92-Q92 -> 0 | V92: =+G92-R92 -> 0 | W92: =1-S92 -> 0
B93: 01.05.01.02 | C93: RELLENO COMPACTACION CON MATERIAL PROPIO SELECCIONADO | D93: m3 | E93: 10.75 | F93: 19.04 | G93: =ROUND(E93*F93,2) -> 204.68 | J93: 0 | K93: 0 | M93: =+E93 -> 10.75 | N93: =ROUND(M93*$F93,2) -> 204.68 | O93: =ROUND(N93/$G93,4) -> 1 | Q93: =+I93+M93 -> 10.75 | R93: =+J93+N93 -> 204.68 | S93: =+K93+O93 -> 1 | U93: =+E93-Q93 -> 0 | V93: =+G93-R93 -> 0 | W93: =1-S93 -> 0
B94: 01.05.01.03 | C94: ACARREO DE MATERIAL EXCEDENTE HASTA 30 M | D94: m3 | E94: 8.75 | F94: 28.21 | G94: =ROUND(E94*F94,2) -> 246.84 | J94: 0 | K94: 0 | M94: =+E94 -> 8.75 | N94: =ROUND(M94*$F94,2) -> 246.84 | O94: =ROUND(N94/$G94,4) -> 1 | Q94: =+I94+M94 -> 8.75 | R94: =+J94+N94 -> 246.84 | S94: =+K94+O94 -> 1 | U94: =+E94-Q94 -> 0 | V94: =+G94-R94 -> 0 | W94: =1-S94 -> 0
B95: 01.05.01.04 | C95: ELIMINACION DE MATERIAL EXCEDENTE C/VOLQUETE DE 15M3 (D=10KM) | D95: m3 | E95: 8.75 | F95: 18.98 | G95: =ROUND(E95*F95,2) -> 166.08 | J95: 0 | K95: 0 | M95: =+E95 -> 8.75 | N95: =ROUND(M95*$F95,2) -> 166.08 | O95: =ROUND(N95/$G95,4) -> 1 | Q95: =+I95+M95 -> 8.75 | R95: =+J95+N95 -> 166.08 | S95: =+K95+O95 -> 1 | U95: =+E95-Q95 -> 0 | V95: =+G95-R95 -> 0 | W95: =1-S95 -> 0
B96: 01.05.02 | C96: OBRAS DE CONCRETO EN SARDINEL ARMADO
B97: 01.05.02.01 | C97: ACERO CORRUGADO F'Y=4200 KG/CM2 GRADO 60 | D97: kg | E97: 653.8 | F97: 7.85 | G97: =ROUND(E97*F97,2) -> 5132.33 | J97: 0 | K97: 0 | M97: =+E97 -> 653.8 | N97: =ROUND(M97*$F97,2) -> 5132.33 | O97: =ROUND(N97/$G97,4) -> 1 | Q97: =+I97+M97 -> 653.8 | R97: =+J97+N97 -> 5132.33 | S97: =+K97+O97 -> 1 | U97: =+E97-Q97 -> 0 | V97: =+G97-R97 -> 0 | W97: =1-S97 -> 0
B98: 01.05.02.02 | C98: ENCOFRADO Y DESENCOFRADO EN SARDINELES | D98: m2 | E98: 251.02 | F98: 73.97 | G98: =ROUND(E98*F98,2) -> 18567.95 | J98: 0 | K98: 0 | M98: =+E98 -> 251.02 | N98: =ROUND(M98*$F98,2) -> 18567.95 | O98: =ROUND(N98/$G98,4) -> 1 | Q98: =+I98+M98 -> 251.02 | R98: =+J98+N98 -> 18567.95 | S98: =+K98+O98 -> 1 | U98: =+E98-Q98 -> 0 | V98: =+G98-R98 -> 0 | W98: =1-S98 -> 0
B99: 01.05.02.03 | C99: CONCRETO F'C=175 KG/CM2 PARA SARDINEL (b=0.15m , h=0.40m) ACABADO SOLAQUEADO | D99: m3 | E99: 32.94 | F99: 477.23 | G99: =ROUND(E99*F99,2) -> 15719.96 | J99: 0 | K99: 0 | M99: =+E99 -> 32.94 | N99: =ROUND(M99*$F99,2) -> 15719.96 | O99: =ROUND(N99/$G99,4) -> 1 | Q99: =+I99+M99 -> 32.94 | R99: =+J99+N99 -> 15719.96 | S99: =+K99+O99 -> 1 | U99: =+E99-Q99 -> 0 | V99: =+G99-R99 -> 0 | W99: =1-S99 -> 0
B100: 01.05.02.04 | C100: CURADO DE CONCRETO | D100: m2 | E100: 219.61 | F100: 2.92 | G100: =ROUND(E100*F100,2) -> 641.26 | J100: 0 | K100: 0 | M100: =+E100 -> 219.61 | N100: =ROUND(M100*$F100,2) -> 641.26 | O100: =ROUND(N100/$G100,4) -> 1 | Q100: =+I100+M100 -> 219.61 | R100: =+J100+N100 -> 641.26 | S100: =+K100+O100 -> 1 | U100: =+E100-Q100 -> 0 | V100: =+G100-R100 -> 0 | W100: =1-S100 -> 0
B101: 01.05.02.05 | C101: JUNTA ASFALTICA | D101: m | E101: 6 | F101: 4.48 | G101: =ROUND(E101*F101,2) -> 26.88 | J101: 0 | K101: 0 | M101: =+E101 -> 6 | N101: =ROUND(M101*$F101,2) -> 26.88 | O101: =ROUND(N101/$G101,4) -> 1 | Q101: =+I101+M101 -> 6 | R101: =+J101+N101 -> 26.88 | S101: =+K101+O101 -> 1 | U101: =+E101-Q101 -> 0 | V101: =+G101-R101 -> 0 | W101: =1-S101 -> 0
...

Sheet PROG VS. EJEC
B1: AVANCE PROGRAMADO VS. EJECUTADO (JULIO 2026)
B2: Obra: | C2: =+FT!$E$5 -> "MEJORAMIENTO Y AMPLIACIÓN DE LOS SERVICIOS DE TRANSITABILIDAD VEHICULAR Y PEATONAL DEL JR LOS PINOS Y JR LOS CEDROS EN CAYHUAYNA Y CAYHUAYNA DEL DISTRITO DE PILLCO MARCA - PROVINCIA DE HUÁNUCO - DEPARTAMENTO DE HUÁNUCO" con CUI N°2536252
B3: Entidad: | C3: =+FT!$E$4 -> MUNICIPALIDAD DISTRITAL DE PILLCO MARCA
B4: Ejecutor: | C4: =+FT!$E$15 -> CONSORCIO EJECUTOR LOS PINOS
B5: Supervisor: | C5: =+FT!$E$34 -> PROYECTA PCL S.A.C | D5: VALOR REFERENCIAL (CON IGV) | G5: =+FT!$E$24 -> 638827.47
B6: Residente: | C6: =+FT!$E$32 -> ING. RAMIREZ BLANCO GABRIEL AUGUSTO HERMOGENES | D6: MONTO DEL CONTRATO (INCL. IGV): | G6: =+FT!$E$25 -> 638827.47
B7: Ing. Supervisor: | C7: =+FT!$E$46 -> ING. CESAR RICARDO ZELADA RODRIGUEZ (CIP N° 98469) | D7: PLAZO DE EJECUCIÓN: | G7: =+FT!$E$31 -> SESENTA (60) DÍAS CALENDARIOS
B9: ITEM | C9: DESCRIPCION | D9: PRESUPUESTO DE OBRA | I9: 46204 | L9: 46204
I10: 46204 | J10: 46234 | L10: 46204 | M10: 46234
D11: UND | E11: METRADO | F11: P.UND | G11: TOTAL | I11: PORCEN. (%) | J11: COSTO (S/) | L11: PORCEN. (%) | M11: COSTO (S/)
B12: 01 | C12: CREACION DE PISTAS Y VEREDAS JR LOS CEDROS
B13: 01.01 | C13: OBRAS PROVISIONALES Y TRABAJOS PRELIMINARES
B14: 01.01.01 | C14: OBRAS PROVISIONALES
B15: 01.01.01.01 | C15: ALQUILER DE ALAMACEN, OFICINA Y CASETA DE GUARDIANIA | D15: mes | E15: 2 | F15: 2400 | G15: =ROUND(E15*F15,2) -> 4800 | I15: =ROUND(J15/$G15,4) -> 0.3333 | J15: 1600 | L15: 1 | M15: 1152
B16: 01.01.01.02 | C16: CARTEL DE IDENTIFICACION DE LA OBRA DE 3.60 x 4.80 m (SOPORTE DE MADERA) | D16: und | E16: 1 | F16: 1205.49 | G16: =ROUND(E16*F16,2) -> 1205.49 | I16: =ROUND(J16/$G16,4) -> 0 | L16: 1 | M16: 0
B17: 01.01.01.03 | C17: ALQUILER DE BAÑOS PORTATILES Y LAVADERO | D17: mes | E17: 2 | F17: 850 | G17: =ROUND(E17*F17,2) -> 1700 | I17: =ROUND(J17/$G17,4) -> 0.5167 | J17: 878.33333 | L17: 1 | M17: 408
B18: 01.01.02 | C18: TRABAJOS PRELIMINARES | G18: =ROUND(E18*F18,2) -> 0
B19: 01.01.02.01 | C19: LIMPIEZA DE TERRENO MANUAL | D19: m2 | E19: 1932.21 | F19: 1.06 | G19: =ROUND(E19*F19,2) -> 2048.14 | I19: =ROUND(J19/$G19,4) -> 0 | L19: 1932.21 | M19: 0
B20: 01.01.02.02 | C20: TRAZO Y REPLANTEO EN TERRENO NORMAL | D20: m2 | E20: 1932.21 | F20: 4.32 | G20: =ROUND(E20*F20,2) -> 8347.15 | I20: =ROUND(J20/$G20,4) -> 0.4539 | J20: 3789.15 | L20: 1932.21 | M20: 0
B21: 01.01.02.03 | C21: MOVILIZACION Y DESMOVILIZACION DE MAQUINARIA Y EQUIPO | D21: GLB | E21: 1 | F21: 2500 | G21: =ROUND(E21*F21,2) -> 2500 | I21: =ROUND(J21/$G21,4) -> 0 | L21: 1 | M21: 0
B22: 01.01.03 | C22: DEMOLICIONES | G22: =ROUND(E22*F22,2) -> 0
B23: 01.01.03.01 | C23: DEMOLICION DE VEREDAS EXISTENTES DE 0.10M | D23: m2 | E23: 135.5 | F23: 21.33 | G23: =ROUND(E23*F23,2) -> 2890.22 | I23: =ROUND(J23/$G23,4) -> 0 | L23: 135.5 | M23: 0
B24: 01.01.03.02 | C24: ELIMINACION DE MATERIAL EXCEDENTE C/VOLQUETE DE 15M3 (D=10 KM) | D24: m3 | E24: 20.33 | F24: 18.98 | G24: =ROUND(E24*F24,2) -> 385.86 | I24: =ROUND(J24/$G24,4) -> 0 | L24: 20.33 | M24: 0
B25: 01.01.04 | C25: PLAN DE DESVIO VEHICULAR
B26: 01.01.04.01 | C26: TRANQUERAS DE MADERA 2.40 x 1.20 | D26: und | E26: 2 | F26: 221.35 | G26: =ROUND(E26*F26,2) -> 442.7 | I26: =ROUND(J26/$G26,4) -> 0 | L26: 2 | M26: 0
B27: 01.01.04.02 | C27: SEÑALIZACION DE DESVIO DE TRANSITO EN PERIODO DE CONSTRUCCION | D27: GLB | E27: 1 | F27: 221.16 | G27: =ROUND(E27*F27,2) -> 221.16 | I27: =ROUND(J27/$G27,4) -> 0 | L27: 1 | M27: 0
B28: 01.02 | C28: PAVIMENTO RIGIDO | G28: =ROUND(E28*F28,2) -> 0
B29: 01.02.01 | C29: MOVIMIENTO DE TIERRAS HASTA EL NIVEL DE SUB - RASANTE
B30: 01.02.01.01 | C30: CORTE EN TERRENO NORMAL CON MAQUINARIA | D30: m3 | E30: 590.54 | F30: 10.47 | G30: =ROUND(E30*F30,2) -> 6182.95 | I30: =ROUND(J30/$G30,4) -> 0 | L30: 590.54 | M30: 0
B31: 01.02.01.02 | C31: RELLENO COMPACTACION CON MATERIAL PROPIO SELECCIONADO | D31: m3 | E31: 51.64 | F31: 19.04 | G31: =ROUND(E31*F31,2) -> 983.23 | I31: =ROUND(J31/$G31,4) -> 0 | L31: 51.64 | M31: 0
B32: 01.02.01.03 | C32: ELIMINACION DE MATERIAL EXCEDENTE C/VOLQUETE DE 15M3 (D=10KM) | D32: m3 | E32: 738.18 | F32: 18.98 | G32: =ROUND(E32*F32,2) -> 14010.66 | I32: =ROUND(J32/$G32,4) -> 1 | J32: 14010.66 | L32: 738.18 | M32: 0
B33: 01.02.02 | C33: BASE | G33: =ROUND(E33*F33,2) -> 0
B34: 01.02.02.01 | C34: CONFORMACION DE BASE MATERIAL MEZCLADO E=0.20m | D34: m2 | E34: 910.14 | F34: 31.15 | G34: =ROUND(E34*F34,2) -> 28350.86 | I34: =ROUND(J34/$G34,4) -> 0 | L34: 910.14 | M34: 0
B35: 01.02.03 | C35: SUB RASANTE | G35: =ROUND(E35*F35,2) -> 0
B36: 01.02.03.01 | C36: PERFILADO, RIEGO Y COMPACTACIÓN DE SUBRASANTE | D36: m2 | E36: 910.14 | F36: 5.54 | G36: =ROUND(E36*F36,2) -> 5042.18 | I36: =ROUND(J36/$G36,4) -> 0 | L36: 910.14 | M36: 0
B37: 01.02.04 | C37: OBRAS DE CONCRETO | G37: =ROUND(E37*F37,2) -> 0
B38: 01.02.04.01 | C38: ENCOFRADO Y DESENCOFRADO EN PAVIMENTOS | D38: m2 | E38: 127.29 | F38: 63.41 | G38: =ROUND(E38*F38,2) -> 8071.46 | I38: =ROUND(J38/$G38,4) -> 0 | L38: 127.29 | M38: 0
B39: 01.02.04.02 | C39: CONCRETO F'C =210 KG/CM2 EN VIA E=15CM | D39: m2 | E39: 910.14 | F39: 119.99 | G39: =ROUND(E39*F39,2) -> 109207.7 | I39: =ROUND(J39/$G39,4) -> 0.9213 | J39: 100614.38 | L39: 910.14 | M39: 0
B40: 01.02.04.03 | C40: CURADO DE CONCRETO | D40: m2 | E40: 910.14 | F40: 2.92 | G40: =ROUND(E40*F40,2) -> 2657.61 | I40: =ROUND(J40/$G40,4) -> 1 | J40: 2657.61 | L40: 910.14 | M40: 0
B41: 01.02.04.04 | C41: ACERO FY = 4200Kg/cm2 EN JUNTAS DE DILATACION LONGITUDINAL Ø 3/8" | D41: kg | E41: 80.64 | F41: 12.14 | G41: =ROUND(E41*F41,2) -> 978.97 | I41: =ROUND(J41/$G41,4) -> 0 | L41: 80.64 | M41: 0
B42: 01.02.04.05 | C42: ACERO FY = 2400Kg/cm2 GRADO 60 EN JUNTAS DE DILATACION TRANSVERSAL Ø 3/4" | D42: kg | E42: 176.4 | F42: 42.88 | G42: =ROUND(E42*F42,2) -> 7564.03 | I42: =ROUND(J42/$G42,4) -> 0 | L42: 176.4 | M42: 0
B43: 01.02.04.06 | C43: JUNTA DE AISLAMIENTO e=1" X 0.20 m | D43: m | E43: 360 | F43: 5.59 | G43: =ROUND(E43*F43,2) -> 2012.4 | I43: =ROUND(J43/$G43,4) -> 1 | J43: 2012.4 | L43: 360 | M43: 0
B44: 01.02.04.07 | C44: JUNTA DE DILATACION e=1" X 0.10 m | D44: m | E44: 255 | F44: 5.59 | G44: =ROUND(E44*F44,2) -> 1425.45 | I44: =ROUND(J44/$G44,4) -> 1 | J44: 1425.45 | L44: 255 | M44: 0
B45: 01.02.04.08 | C45: JUNTAS DE CONTRACCION CON ELASTOMERICO DE POLIURETANO E=1/2" X 0.10m | D45: m | E45: 150 | F45: 19.22 | G45: =ROUND(E45*F45,2) -> 2883 | I45: =ROUND(J45/$G45,4) -> 1 | J45: 2883 | L45: 150 | M45: 0
B46: 01.02.05 | C46: NIVELACION DE BUZONES | G46: =ROUND(E46*F46,2) -> 0
B47: 01.02.05.01 | C47: NIVELACION DE BUZONES EN GENERAL | D47: und | E47: 3 | F47: 471.14 | G47: =ROUND(E47*F47,2) -> 1413.42 | I47: =ROUND(J47/$G47,4) -> 0 | L47: 3 | M47: 0
B48: 01.02.06 | C48: SEÑALIZACION | G48: =ROUND(E48*F48,2) -> 0
B49: 01.02.06.01 | C49: PINTURA EN PAVIMENTO (SIMBOLO Y LETRA) | D49: m2 | E49: 50.6 | F49: 38.21 | G49: =ROUND(E49*F49,2) -> 1933.43 | I49: =ROUND(J49/$G49,4) -> 1 | J49: 1933.43 | M49: 0
B50: 01.02.06.02 | C50: PINTURA DE PAVIMENTO (LINEAS DISCONTINUAS CENTRALES) | D50: m | E50: 170 | F50: 10.43 | G50: =ROUND(E50*F50,2) -> 1773.1 | I50: =ROUND(J50/$G50,4) -> 1 | J50: 1773.1 | M50: 0
B51: 01.02.06.03 | C51: SEÑALIZACION VERTICAL | D51: und | E51: 4 | F51: 361.47 | G51: =ROUND(E51*F51,2) -> 1445.88 | I51: =ROUND(J51/$G51,4) -> 1 | J51: 1445.88 | M51: 0
B52: 01.03 | C52: VEREDAS, RAMPAS Y MARTILLOS | G52: =ROUND(E52*F52,2) -> 0
B53: 01.03.01 | C53: MOVIMIENTO DE TIERRAS HASTA EL NIVEL DE SUB - RASANTE
B54: 01.03.01.01 | C54: EXCAVACION EN TERRENO NORMAL C/MAQUINARIA LIVIANA | D54: m3 | E54: 56.3 | F54: 22.11 | G54: =ROUND(E54*F54,2) -> 1244.79 | I54: =ROUND(J54/$G54,4) -> 1 | J54: 1244.79 | L54: 56.3 | M54: 0
B55: 01.03.01.02 | C55: RELLENO Y COMPACTACION CON MATERIAL PROPIO SELECCIONADO | D55: m3 | E55: 12 | F55: 42.31 | G55: =ROUND(E55*F55,2) -> 507.72 | I55: =ROUND(J55/$G55,4) -> 0 | L55: 12 | M55: 0
B56: 01.03.01.03 | C56: ELIMINACION DE MATERIAL EXCEDENTE C/VOLQUETE DE 15M3 (D=10KM) | D56: m3 | E56: 55.38 | F56: 18.98 | G56: =ROUND(E56*F56,2) -> 1051.11 | I56: =ROUND(J56/$G56,4) -> 0 | L56: 55.38 | M56: 0
B57: 01.03.01.04 | C57: PERFILADO Y COMPACTADO CON PLANCHA | D57: m2 | E57: 547.38 | F57: 4.25 | G57: =ROUND(E57*F57,2) -> 2326.37 | I57: =ROUND(J57/$G57,4) -> 0 | L57: 547.38 | M57: 0
B58: 01.03.01.05 | C58: CONFORMACIÓN Y COMPACTACIÓN DE BASE EN VEREDAS Y RAMPAS (e=10cm) | D58: m2 | E58: 547.38 | F58: 16.02 | G58: =ROUND(E58*F58,2) -> 8769.03 | I58: =ROUND(J58/$G58,4) -> 0 | L58: 547.38 | M58: 0
B59: 01.03.02 | C59: OBRAS DE CONCRETO EN VEREDAS | G59: =ROUND(E59*F59,2) -> 0
B60: 01.03.02.01 | C60: ENCOFRADO Y DESENCOFRADO EN VEREDAS | D60: m2 | E60: 55.28 | F60: 72.37 | G60: =ROUND(E60*F60,2) -> 4000.61 | I60: =ROUND(J60/$G60,4) -> 0 | M60: 4000.61
B61: 01.03.02.02 | C61: CONCRETO F'c=175 kg/cm2 (E=4") EN VEREDA CON ACABADO FROTACHADO Y BRUÑADO S/DISEÑO | D61: m2 | E61: 547.38 | F61: 49.11 | G61: =ROUND(E61*F61,2) -> 26881.83 | I61: =ROUND(J61/$G61,4) -> 0 | M61: 26881.83
B62: 01.03.02.03 | C62: CONCRETO F'c=175 kg/cm2 PARA UÑA EN VEREDA (A=0.025 m2) | D62: m | E62: 404 | F62: 16.32 | G62: =ROUND(E62*F62,2) -> 6593.28 | I62: =ROUND(J62/$G62,4) -> 0 | M62: 6593.28
B63: 01.03.02.04 | C63: CURADO DE CONCRETO | E63: 547.38 | F63: 2.92 | G63: =ROUND(E63*F63,2) -> 1598.35 | I63: =ROUND(J63/$G63,4) -> 0 | M63: 1598.35
B64: 01.03.02.05 | C64: JUNTA ASFALTICA | D64: m | E64: 158.4 | F64: 4.48 | G64: =ROUND(E64*F64,2) -> 709.63 | I64: =ROUND(J64/$G64,4) -> 0 | M64: 709.63
B65: 01.03.03 | C65: OBRAS DE CONCRETO EN RAMPA | G65: =ROUND(E65*F65,2) -> 0
B66: 01.03.03.01 | C66: ENCOFRADO Y DESENCOFRADO EN RAMPAS | D66: m2 | E66: 16.25 | F66: 46.94 | G66: =ROUND(E66*F66,2) -> 762.78 | I66: =ROUND(J66/$G66,4) -> 0 | M66: 762.78
B67: 01.03.03.02 | C67: CONCRETO F'c=175 KG/CM2, ACABADO 1:2 BRUÑADO Y FROTACHADO | D67: m2 | E67: 86.65 | F67: 53.06 | G67: =ROUND(E67*F67,2) -> 4597.65 | I67: =ROUND(J67/$G67,4) -> 0 | M67: 4597.65
B68: 01.03.03.03 | C68: CURADO DE CONCRETO EN RAMPA | D68: m2 | E68: 86.65 | F68: 2.92 | G68: =ROUND(E68*F68,2) -> 253.02 | I68: =ROUND(J68/$G68,4) -> 0 | M68: 253.02
B69: 01.03.03.04 | C69: JUNTA ASFALTICA | D69: m | E69: 110 | F69: 4.48 | G69: =ROUND(E69*F69,2) -> 492.8 | I69: =ROUND(J69/$G69,4) -> 0 | M69: 492.8
B70: 01.03.04 | C70: OBRAS DE CONCRETO EN MARTILLO
B71: 01.03.04.01 | C71: CONCRETO F'c=175 KG/CM2, ACABADO FROTACHADO | D71: m2 | E71: 64 | F71: 49.11 | G71: =ROUND(E71*F71,2) -> 3143.04 | I71: =ROUND(J71/$G71,4) -> 0 | M71: 3143.04
B72: 01.03.04.02 | C72: ENCOFRADO Y DESENCOFRADO DE MARTILLOS | D72: m2 | E72: 2.8 | F72: 87.93 | G72: =ROUND(E72*F72,2) -> 246.2 | I72: =ROUND(J72/$G72,4) -> 0 | M72: 246.2
B73: 01.03.04.03 | C73: UÑA DE CONCRETO SUMERGIDOF'c=175 kg/cm2A=0.13m | D73: m | E73: 28 | F73: 51.24 | G73: =ROUND(E73*F73,2) -> 1434.72 | I73: =ROUND(J73/$G73,4) -> 0 | M73: 1434.72
B74: 01.03.04.04 | C74: CURADO DE CONCRETO | D74: m2 | E74: 64 | F74: 2.92 | G74: =ROUND(E74*F74,2) -> 186.88 | I74: =ROUND(J74/$G74,4) -> 0 | M74: 186.88
B75: 01.03.05 | C75: NIVELACION DE CONEXIONES DOMICILIARIAS
B76: 01.03.05.01 | C76: NIVELACION DE CONEXIONES DOMICILIARIAS DE AGUA | D76: und | E76: 32 | F76: 202.81 | G76: =ROUND(E76*F76,2) -> 6489.92 | I76: =ROUND(J76/$G76,4) -> 0 | L76: 32 | M76: 0
B77: 01.03.05.02 | C77: NIVELACION DE CONEXIONES DOMICILIARIAS DE DESAGUE | D77: und | E77: 32 | F77: 312.41 | G77: =ROUND(E77*F77,2) -> 9997.12 | I77: =ROUND(J77/$G77,4) -> 0 | L77: 32 | M77: 0
B78: 01.04 | C78: CUNETA PLUVIAL
B79: 01.04.01 | C79: MOVIMIENTO DE TIERRAS HASTA NIVEL DE SUB-RAZANTE
B80: 01.04.01.01 | C80: EXCAVACION EN TERRENO NORMAL | D80: m3 | E80: 43.2 | F80: 56.41 | G80: =ROUND(E80*F80,2) -> 2436.91 | I80: =ROUND(J80/$G80,4) -> 0.6667 | J80: 1624.61 | M80: 2436.91
B81: 01.04.01.02 | C81: RELLENO COMPACTADO CON MATERIAL PROPIO | D81: m3 | E81: 5.5 | F81: 42.31 | G81: =ROUND(E81*F81,2) -> 232.71 | I81: =ROUND(J81/$G81,4) -> 0 | M81: 232.71
B82: 01.04.01.03 | C82: ACARREO DE MATERIAL EXCEDENTE HASTA 30 M | D82: m3 | E82: 47.13 | F82: 28.21 | G82: =ROUND(E82*F82,2) -> 1329.54 | I82: =ROUND(J82/$G82,4) -> 0.125 | J82: 166.19 | M82: 1329.54
B83: 01.04.01.04 | C83: ELIMINACION DE MATERIAL EXCEDENTE C/VOLQUETE DE 15M3 (D=10KM) | D83: m3 | E83: 47.13 | F83: 18.98 | G83: =ROUND(E83*F83,2) -> 894.53 | I83: =ROUND(J83/$G83,4) -> 0 | M83: 894.53
B84: 01.04.01.05 | C84: CONFORMACIÓN Y COMPACTACIÓN SUBRASANTE C/PLANCHA | D84: m2 | E84: 115.95 | F84: 4.25 | G84: =ROUND(E84*F84,2) -> 492.79 | I84: =ROUND(J84/$G84,4) -> 0 | M84: 492.79
B85: 01.04.02 | C85: OBRAS DE CONCRETO SIMPLE EN CUNETAS
B86: 01.04.02.01 | C86: ENCOFRADO Y DESENCOFRADO EN CUNETA TRIANGULAR | D86: m2 | E86: 5.76 | F86: 34.68 | G86: =ROUND(E86*F86,2) -> 199.76 | I86: =ROUND(J86/$G86,4) -> 0 | M86: 199.76
B87: 01.04.02.02 | C87: CONCRETO F'C =175 KG/CM2 EN CUNETA TRIANGULAR | D87: m | E87: 386 | F87: 40.96 | G87: =ROUND(E87*F87,2) -> 15810.56 | I87: =ROUND(J87/$G87,4) -> 0 | M87: 15810.56
B88: 01.04.02.03 | C88: CURADO DE CONCRETO TRIANGULAR | D88: m2 | E88: 115.8 | F88: 5.86 | G88: =ROUND(E88*F88,2) -> 678.59 | I88: =ROUND(J88/$G88,4) -> 0 | M88: 678.59
B89: 01.04.02.04 | C89: JUNTA TRANSVERSAL DE DILATACION e=20mm | D89: m | E89: 38.5 | F89: 5.44 | G89: =ROUND(E89*F89,2) -> 209.44 | I89: =ROUND(J89/$G89,4) -> 0 | M89: 209.44
B90: 01.05 | C90: SARDINELES DE CONCRETO
B91: 01.05.01 | C91: MOVIMIENTO DE TIERRAS HASTA NIVEL DE SUB RAZANTE
B92: 01.05.01.01 | C92: EXCAVACION EN TERRENO NORMAL | D92: m3 | E92: 9 | F92: 56.41 | G92: =ROUND(E92*F92,2) -> 507.69 | I92: =ROUND(J92/$G92,4) -> 1 | J92: 507.69 | M92: 507.69
B93: 01.05.01.02 | C93: RELLENO COMPACTACION CON MATERIAL PROPIO SELECCIONADO | D93: m3 | E93: 10.75 | F93: 19.04 | G93: =ROUND(E93*F93,2) -> 204.68 | I93: =ROUND(J93/$G93,4) -> 1 | J93: 204.68 | M93: 204.68
B94: 01.05.01.03 | C94: ACARREO DE MATERIAL EXCEDENTE HASTA 30 M | D94: m3 | E94: 8.75 | F94: 28.21 | G94: =ROUND(E94*F94,2) -> 246.84 | I94: =ROUND(J94/$G94,4) -> 1 | J94: 246.84 | M94: 246.84
B95: 01.05.01.04 | C95: ELIMINACION DE MATERIAL EXCEDENTE C/VOLQUETE DE 15M3 (D=10KM) | D95: m3 | E95: 8.75 | F95: 18.98 | G95: =ROUND(E95*F95,2) -> 166.08 | I95: =ROUND(J95/$G95,4) -> 1 | J95: 166.08 | M95: 166.08
B96: 01.05.02 | C96: OBRAS DE CONCRETO EN SARDINEL ARMADO
B97: 01.05.02.01 | C97: ACERO CORRUGADO F'Y=4200 KG/CM2 GRADO 60 | D97: kg | E97: 653.8 | F97: 7.85 | G97: =ROUND(E97*F97,2) -> 5132.33 | I97: =ROUND(J97/$G97,4) -> 0 | M97: 5132.33
B98: 01.05.02.02 | C98: ENCOFRADO Y DESENCOFRADO EN SARDINELES | D98: m2 | E98: 251.02 | F98: 73.97 | G98: =ROUND(E98*F98,2) -> 18567.95 | I98: =ROUND(J98/$G98,4) -> 0.1892 | J98: 3512.19 | M98: 18567.95
B99: 01.05.02.03 | C99: CONCRETO F'C=175 KG/CM2 PARA SARDINEL (b=0.15m , h=0.40m) ACABADO SOLAQUEADO | D99: m3 | E99: 32.94 | F99: 477.23 | G99: =ROUND(E99*F99,2) -> 15719.96 | I99: =ROUND(J99/$G99,4) -> 0 | M99: 15719.96
B100: 01.05.02.04 | C100: CURADO DE CONCRETO | D100: m2 | E100: 219.61 | F100: 2.92 | G100: =ROUND(E100*F100,2) -> 641.26 | I100: =ROUND(J100/$G100,4) -> 0 | M100: 641.26
B101: 01.05.02.05 | C101: JUNTA ASFALTICA | D101: m | E101: 6 | F101: 4.48 | G101: =ROUND(E101*F101,2) -> 26.88 | I101: =ROUND(J101/$G101,4) -> 0 | M101: 26.88
...

Sheet CONTROL GEN. AVAN. OBRA.
B1: CONTROL GENERAL DE AVANCE DE OBRA
B2: Obra: | C2: =+FT!$E$5 -> "MEJORAMIENTO Y AMPLIACIÓN DE LOS SERVICIOS DE TRANSITABILIDAD VEHICULAR Y PEATONAL DEL JR LOS PINOS Y JR LOS CEDROS EN CAYHUAYNA Y CAYHUAYNA DEL DISTRITO DE PILLCO MARCA - PROVINCIA DE HUÁNUCO - DEPARTAMENTO DE HUÁNUCO" con CUI N°2536252
B3: Entidad: | C3: =+FT!$E$4 -> MUNICIPALIDAD DISTRITAL DE PILLCO MARCA
B4: Ejecutor: | C4: =+FT!$E$15 -> CONSORCIO EJECUTOR LOS PINOS
B5: Supervisor: | C5: =+FT!$E$34 -> PROYECTA PCL S.A.C | G5: VALOR REFERENCIAL (CON IGV) | I5: =+FT!$E$24 -> 638827.47
B6: Residente: | C6: =+FT!$E$32 -> ING. RAMIREZ BLANCO GABRIEL AUGUSTO HERMOGENES | G6: MONTO DEL CONTRATO (INCL. IGV): | I6: =+FT!$E$25 -> 638827.47
B7: Ing. Supervisor: | C7: =+FT!$E$46 -> ING. CESAR RICARDO ZELADA RODRIGUEZ (CIP N° 98469) | G7: PLAZO DE EJECUCIÓN: | I7: =+FT!$E$31 -> SESENTA (60) DÍAS CALENDARIOS
B9: VALORIZACIÓN | D9: PROGRAMADO | H9: EJECUTADO | L9: EVALUACIÓN DEL ATRASO (80% DEL PROGRAMADO ACUMULADO) | P9: SITUACIÓN DE LA OBRA
B10: Nº | C10: MES | D10: MENSUAL | E10: ACUMULADO | F10: % MENSUAL | G10: % ACUMULADO | H10: MENSUAL | I10: ACUMULADO | J10: % MENSUAL | K10: % ACUMULADO | L10: % PROGRAMADO ACUMULADO | M10: 80% DEL PROGRAMADO ACUMULADO | N10: % EJECUTADO ACUMULADO | O10: CONCLUSIÓN: ATRASO (-) ADELANTO (+) | T10: 131453.71
B11: 1 | C11: =+'CALEN. PROG.'!I9 -> 46174 | D11: =+'CALEN. PROG.'!J161 -> 157550.32 | E11: =D11 -> 157550.32 | F11: =ROUND(D11/$D$14,4) -> 0.2466 | G11: =+F11 -> 0.2466 | H11: =+'CALEN. VALO.'!J161 -> 400648.29 | I11: =+H11 -> 400648.29 | J11: =ROUND(H11/$D$14,4) -> 0.6272 | K11: =+J11 -> 0.6272 | L11: =+G11 -> 0.2466 | M11: =ROUND(L11*0.8,4) -> 0.1973 | N11: =+K11 -> 0.6272 | O11: =+N11-L11 -> 0.3806 | P11: =+IF(K11<G11,"ATRASADA",IF(K11=100%,"CULMINADA","ADELANTADA")) -> ADELANTADA | T11: 122142.92
B12: 2 | C12: =+'CALEN. PROG.'!L9 -> 46204 | D12: =+'CALEN. PROG.'!M161 -> 203396.72 | E12: =+D12+E11 -> 360947.04 | F12: =ROUND(D12/$D$14,4) -> 0.3184 | G12: =+F12+G11 -> 0.565 | H12: =+'CALEN. VALO.'!M161 -> 224198.55 | I12: =+H12+I11 -> 624846.84 | J12: =ROUND(H12/$D$14,4) -> 0.351 | K12: =+J12+K11 -> 0.9782 | L12: =+G12 -> 0.565 | M12: =ROUND(L12*0.8,4) -> 0.452 | N12: =+K12 -> 0.9782 | O12: =+N12-L12 -> 0.4132 | P12: =+IF(K12<G12,"ATRASADA",IF(K12=100%,"CULMINADA","ADELANTADA")) -> ADELANTADA | T12: =SUM(T10:T11) -> 253596.63
B13: 3 | C13: =+'CALEN. PROG.'!O9 -> 46235 | D13: =+'CALEN. PROG.'!P161 -> 277880.43 | E13: =+D13+E12 -> 638827.47 | F13: =ROUND(D13/$D$14,4) -> 0.435 | G13: =+F13+G12 -> 1
B14: TOTAL C/IGV | D14: =SUM(D11:D13) -> 638827.47 | F14: =SUM(F11:F13) -> 1 | H14: =SUM(H11:H12) -> 624846.84 | J14: =SUM(J11:J12) -> 0.9782 | L14: =+L12 -> 0.565 | M14: =+M12 -> 0.452 | N14: =+N12 -> 0.9782 | O14: =+O12 -> 0.4132 | P14: OBRA ADELANTADA

Sheet CURVA S
B1: CURVA S
B2: Obra: | C2: =+FT!$E$5 -> "MEJORAMIENTO Y AMPLIACIÓN DE LOS SERVICIOS DE TRANSITABILIDAD VEHICULAR Y PEATONAL DEL JR LOS PINOS Y JR LOS CEDROS EN CAYHUAYNA Y CAYHUAYNA DEL DISTRITO DE PILLCO MARCA - PROVINCIA DE HUÁNUCO - DEPARTAMENTO DE HUÁNUCO" con CUI N°2536252
B3: Entidad: | C3: =+FT!$E$4 -> MUNICIPALIDAD DISTRITAL DE PILLCO MARCA
B4: Ejecutor: | C4: =+FT!$E$15 -> CONSORCIO EJECUTOR LOS PINOS
B5: Supervisor: | C5: =+FT!$E$34 -> PROYECTA PCL S.A.C | F5: VALOR REFERENCIAL (CON IGV) | H5: =+FT!$E$24 -> 638827.47
B6: Residente: | C6: =+FT!$E$32 -> ING. RAMIREZ BLANCO GABRIEL AUGUSTO HERMOGENES | F6: MONTO DEL CONTRATO (INCL. IGV): | H6: =+FT!$E$25 -> 638827.47
B7: Ing. Supervisor: | C7: =+FT!$E$46 -> ING. CESAR RICARDO ZELADA RODRIGUEZ (CIP N° 98469) | F7: PLAZO DE EJECUCIÓN: | H7: =+FT!$E$31 -> SESENTA (60) DÍAS CALENDARIOS
I31: 0
B32: VALORIZACIÓN | D32: PROGRAMADO | G32: CURVA DEL 80% | H32: EJECUTADO | K32: ESTADO DE LA OBRA
B33: Nº | C33: MES | D33: MONTO | E33: % MENSUAL | F33: %ACUMULADO | H33: MONTO | I33: MENSUAL | J33: ACUMULADO
B34: 0 | E34: 0 | F34: 0 | I34: 0 | J34: 0
B35: 1 | C35: =+'CONTROL GEN. AVAN. OBRA.'!C11 -> 46174 | D35: =+'CONTROL GEN. AVAN. OBRA.'!D11 -> 157550.32 | E35: =ROUND(D35/$D$38,4) -> 0.2466 | F35: =+E35 -> 0.2466 | G35: =0.8*F35 -> 0.19728 | H35: =+'CONTROL GEN. AVAN. OBRA.'!H11 -> 400648.29 | I35: =ROUND(H35/$D$38,4) -> 0.6272 | J35: =+I35 -> 0.6272 | K35: =+'CONTROL GEN. AVAN. OBRA.'!P11 -> ADELANTADA
B36: 2 | C36: =+'CONTROL GEN. AVAN. OBRA.'!C12 -> 46204 | D36: =+'CONTROL GEN. AVAN. OBRA.'!D12 -> 203396.72 | E36: =ROUND(D36/$D$38,4) -> 0.3184 | F36: =+E36+F35 -> 0.565 | G36: =0.8*F36 -> 0.452 | H36: =+'CONTROL GEN. AVAN. OBRA.'!H12 -> 224198.55 | I36: =ROUND(H36/$D$38,4) -> 0.351 | J36: =+I36+J35 -> 0.9782 | K36: =+'CONTROL GEN. AVAN. OBRA.'!P12 -> ADELANTADA
B37: 3 | C37: =+'CONTROL GEN. AVAN. OBRA.'!C13 -> 46235 | D37: =+'CONTROL GEN. AVAN. OBRA.'!D13 -> 277880.43 | E37: =ROUND(D37/$D$38,4) -> 0.435 | F37: =+E37+F36 -> 1 | G37: =0.8*F37 -> 0.8
B38: TOTAL | D38: =SUM(D35:D37) -> 638827.47 | E38: =SUM(E35:E37) -> 1 | H38: =SUM(H35:H36) -> 624846.84 | I38: =SUM(I35:I36) -> 0.9782 | K38: =+'CONTROL GEN. AVAN. OBRA.'!P14 -> OBRA ADELANTADA

Sheet CONTROL AVAN. FISICO
B1: CONTROL DE AVANCE FÍSICO DE OBRA
B2: Obra: | C2: =+FT!$E$5 -> "MEJORAMIENTO Y AMPLIACIÓN DE LOS SERVICIOS DE TRANSITABILIDAD VEHICULAR Y PEATONAL DEL JR LOS PINOS Y JR LOS CEDROS EN CAYHUAYNA Y CAYHUAYNA DEL DISTRITO DE PILLCO MARCA - PROVINCIA DE HUÁNUCO - DEPARTAMENTO DE HUÁNUCO" con CUI N°2536252
B3: Entidad: | C3: =+FT!$E$4 -> MUNICIPALIDAD DISTRITAL DE PILLCO MARCA
B4: Ejecutor: | C4: =+FT!$E$15 -> CONSORCIO EJECUTOR LOS PINOS
B5: Supervisor: | C5: =+FT!$E$34 -> PROYECTA PCL S.A.C
B6: Residente: | C6: =+FT!$E$32 -> ING. RAMIREZ BLANCO GABRIEL AUGUSTO HERMOGENES | F6: MONTO DEL CONTRATO ORIGINAL: | H6: =+FT!$E$25 -> 638827.47 | I6: INCL. IGV | J6: que representa el | K6: 1
B7: Ing. Supervisor: | C7: =+FT!$E$46 -> ING. CESAR RICARDO ZELADA RODRIGUEZ (CIP N° 98469) | F7: MONTO DEL CONTRATO VIGENTE: | H7: =+H6 -> 638827.47 | I7: INCL. IGV | J7: que representa el | K7: =+K6 -> 1
B9: AVANCE FÍSICO
B10: N° | C10: MES | D10: MONTO | E10: % MENSUAL
B11: VAL. N°01 | C11: =+'CONTROL GEN. AVAN. OBRA.'!C11 -> 46174 | D11: =+'CONTROL GEN. AVAN. OBRA.'!H11 -> 400648.29 | E11: =+'CONTROL GEN. AVAN. OBRA.'!J11 -> 0.6272
B12: VAL. N°02 | C12: =+'CONTROL GEN. AVAN. OBRA.'!C12 -> 46204 | D12: =+'CONTROL GEN. AVAN. OBRA.'!H12 -> 224198.55 | E12: =+'CONTROL GEN. AVAN. OBRA.'!J12 -> 0.351
B13: VAL. N°03 | C13: =+'CONTROL GEN. AVAN. OBRA.'!C13 -> 46235
B14: ACUMULADO | D14: =SUM(D11:D12) -> 624846.84 | E14: =SUM(E11:E12) -> 0.9782
B15: SALDO | D15: =+H6-D14 -> 13980.63 | E15: =1-E14 -> 0.0218
B18: ='CURVA S'!B32 -> VALORIZACIÓN | C18: ='CURVA S'!C32 -> 0 | D18: ='CURVA S'!D32 -> PROGRAMADO | E18: ='CURVA S'!E32 -> 0 | F18: ='CURVA S'!F32 -> 0 | G18: ='CURVA S'!G32 -> CURVA DEL 80% | H18: ='CURVA S'!H32 -> EJECUTADO | I18: ='CURVA S'!I32 -> 0 | ... K18: ='CURVA S'!K32 -> ESTADO DE LA OBRA
B19: ='CURVA S'!B33 -> Nº | C19: ='CURVA S'!C33 -> MES | D19: ='CURVA S'!D33 -> MONTO | E19: ='CURVA S'!E33 -> % MENSUAL | F19: ='CURVA S'!F33 -> %ACUMULADO | G19: ='CURVA S'!G33 -> 0 | H19: ='CURVA S'!H33 -> MONTO | I19: ='CURVA S'!I33 -> MENSUAL | ... K19: ='CURVA S'!K33 -> 0
B20: ='CURVA S'!B35 -> 1 | C20: ='CURVA S'!C35 -> 46174 | D20: ='CURVA S'!D35 -> 157550.32 | E20: ='CURVA S'!E35 -> 0.2466 | F20: ='CURVA S'!F35 -> 0.2466 | G20: ='CURVA S'!G35 -> 0.19728 | H20: ='CURVA S'!H35 -> 400648.29 | I20: ='CURVA S'!I35 -> 0.6272 | ... K20: ='CURVA S'!K35 -> ADELANTADA
B21: ='CURVA S'!B36 -> 2 | C21: ='CURVA S'!C36 -> 46204 | D21: ='CURVA S'!D36 -> 203396.72 | E21: ='CURVA S'!E36 -> 0.3184 | F21: ='CURVA S'!F36 -> 0.565 | G21: ='CURVA S'!G36 -> 0.452 | H21: ='CURVA S'!H36 -> 224198.55 | I21: ='CURVA S'!I36 -> 0.351 | ... K21: ='CURVA S'!K36 -> ADELANTADA
B22: ='CURVA S'!B37 -> 3 | C22: ='CURVA S'!C37 -> 46235 | D22: ='CURVA S'!D37 -> 277880.43 | E22: ='CURVA S'!E37 -> 0.435 | F22: ='CURVA S'!F37 -> 1 | G22: ='CURVA S'!G37 -> 0.8
B23: ='CURVA S'!B38 -> TOTAL | D23: ='CURVA S'!D38 -> 638827.47 | E23: ='CURVA S'!E38 -> 1 | H23: ='CURVA S'!H38 -> 624846.84 | I23: ='CURVA S'!I38 -> 0.9782 | K23: ='CURVA S'!K38 -> OBRA ADELANTADA

Sheet CONTROL FINANCIERO
B1: CONTROL DE AVANCE FINANCIERO DE OBRA
B2: Obra: | C2: =+FT!$E$5 -> "MEJORAMIENTO Y AMPLIACIÓN DE LOS SERVICIOS DE TRANSITABILIDAD VEHICULAR Y PEATONAL DEL JR LOS PINOS Y JR LOS CEDROS EN CAYHUAYNA Y CAYHUAYNA DEL DISTRITO DE PILLCO MARCA - PROVINCIA DE HUÁNUCO - DEPARTAMENTO DE HUÁNUCO" con CUI N°2536252
B3: Entidad: | C3: =+FT!$E$4 -> MUNICIPALIDAD DISTRITAL DE PILLCO MARCA
B4: Ejecutor: | C4: =+FT!$E$15 -> CONSORCIO EJECUTOR LOS PINOS
B5: Supervisor: | C5: =+FT!$E$34 -> PROYECTA PCL S.A.C
B6: Residente: | C6: =+FT!$E$32 -> ING. RAMIREZ BLANCO GABRIEL AUGUSTO HERMOGENES | E6: MONTO DEL CONTRATO ORIGINAL: | F6: =+FT!$E$25 -> 638827.47 | G6: INCL. IGV
B7: Ing. Supervisor: | C7: =+FT!$E$46 -> ING. CESAR RICARDO ZELADA RODRIGUEZ (CIP N° 98469) | E7: MONTO DEL CONTRATO VIGENTE: | F7: =+F6 -> 638827.47 | G7: INCL. IGV
B9: N° | C9: Periodo | D9: Monto Facturables | E9: Montos Devengados | G9: Montos Pendientes por devengar
E10: Montos | F10: %
B11: A. Adelantos otorgados
B12: Adelanto directo | C12: - | D12: 0 | E12: =+D12 -> 0 | F12: =+E12/$F$6 -> 0 | G12: 0
B13: Adelanto de materiales | C13: - | D13: 0 | E13: =+D13 -> 0 | F13: =+E13/$F$6 -> 0 | G13: 0
B14: B. Valorizaciones de obra
B15: Valorización N°01 | C15: 46174 | D15: =+'CONTROL GEN. AVAN. OBRA.'!H11 -> 400648.29 | E15: =+D15 -> 400648.29 | F15: =+E15/$F$6 -> 0.62716196 | G15: =+D15-E15 -> 0
B16: Valorización N°02 | C16: 46204 | D16: =+'CONTROL GEN. AVAN. OBRA.'!H12 -> 224198.55 | E16: 0 | F16: =+E16/$F$6 -> 0 | G16: =+D16-E16 -> 224198.55
B17: Valorización N°03 | C17: 46235
B19: ACUMULADO | D19: =SUM(D12:D18) -> 624846.84 | E19: =SUM(E12:E18) -> 400648.29 | F19: =SUM(F12:F18) -> 0.62716196 | G19: =SUM(G12:G18) -> 224198.55
B20: SALDO | D20: =$F$7-D19 -> 13980.63 | E20: =$F$7-E19 -> 238179.18 | F20: =1-F19 -> 0.37283804 | G20: =+D20 -> 13980.63

Sheet RESUMEN VAL.
B1: RESUMEN DE VALORIZACIÓN POR COMPONENTES
B2: =+FT!E20 -> CONTRATO DE EJECUCIÓN DE OBRA N°004-2026-MDPM/GM
B3: Obra: | C3: =+FT!$E$5 -> "MEJORAMIENTO Y AMPLIACIÓN DE LOS SERVICIOS DE TRANSITABILIDAD VEHICULAR Y PEATONAL DEL JR LOS PINOS Y JR LOS CEDROS EN CAYHUAYNA Y CAYHUAYNA DEL DISTRITO DE PILLCO MARCA - PROVINCIA DE HUÁNUCO - DEPARTAMENTO DE HUÁNUCO" con CUI N°2536252
B4: Entidad: | C4: =+FT!$E$4 -> MUNICIPALIDAD DISTRITAL DE PILLCO MARCA
B5: Ejecutor: | C5: =+FT!$E$15 -> CONSORCIO EJECUTOR LOS PINOS
B6: Supervisor: | C6: =+FT!$E$34 -> PROYECTA PCL S.A.C
B7: Residente: | C7: =+FT!$E$32 -> ING. RAMIREZ BLANCO GABRIEL AUGUSTO HERMOGENES
B8: Ing. Supervisor: | C8: =+FT!$E$46 -> ING. CESAR RICARDO ZELADA RODRIGUEZ (CIP N° 98469)
B10: ÍTEM | C10: DESCRIPCIÓN | E10: MONTO CONTRATADO | G10: ACUMULADO ANTERIOR | J10: ACTUAL | M10: ACUMULADO ACTUAL | P10: SALDO
G11: % DE AVANCE | H11: MONTO | J11: % DE AVANCE | K11: MONTO | M11: % DE AVANCE | N11: MONTO | P11: % DE SALDO | Q11: MONTO
B12: =+'VAL. MENSUAL'!B13 -> 01.01 | C12: =+'VAL. MENSUAL'!C13 -> OBRAS PROVISIONALES Y TRABAJOS PRELIMINARES | E12: =SUM('VAL. MENSUAL'!G13:G27) -> 24540.72 | G12: =ROUND(H12/$E12,4) -> 0.8676 | H12: =SUM('VAL. MENSUAL'!J13:J27) -> 21290.72 | J12: =ROUND(K12/$E12,4) -> 0.0636 | K12: =SUM('VAL. MENSUAL'!N13:N27) -> 1560 | M12: =+G12+J12 -> 0.9312 | N12: =H12+K12 -> 22850.72 | P12: =1-M12 -> 0.0688 | Q12: =E12-N12 -> 1690
B13: =+'VAL. MENSUAL'!B28 -> 01.02 | C13: =+'VAL. MENSUAL'!C28 -> PAVIMENTO RIGIDO | E13: =SUM('VAL. MENSUAL'!G28:G51) -> 195936.33 | G13: =ROUND(H13/$E13,4) -> 0.9737 | H13: =SUM('VAL. MENSUAL'!J28:J51) -> 190783.92 | J13: =ROUND(K13/$E13,4) -> 0 | K13: =SUM('VAL. MENSUAL'!N28:N51) -> 0 | M13: =+G13+J13 -> 0.9737 | N13: =H13+K13 -> 190783.92 | P13: =1-M13 -> 0.0263 | Q13: =E13-N13 -> 5152.41
B14: =+'VAL. MENSUAL'!B52 -> 01.03 | C14: =+'VAL. MENSUAL'!C52 -> VEREDAS, RAMPAS Y MARTILLOS | E14: =SUM('VAL. MENSUAL'!G52:G77) -> 81286.85 | G14: =ROUND(H14/$E14,4) -> 0.3738 | H14: =SUM('VAL. MENSUAL'!J52:J77) -> 30386.06 | J14: =ROUND(K14/$E14,4) -> 0.6262 | K14: =SUM('VAL. MENSUAL'!N52:N77) -> 50900.79 | M14: =+G14+J14 -> 1 | N14: =H14+K14 -> 81286.85 | P14: =1-M14 -> 0 | Q14: =E14-N14 -> 0
B15: =+'VAL. MENSUAL'!B78 -> 01.04 | C15: =+'VAL. MENSUAL'!C78 -> CUNETA PLUVIAL | E15: =SUM('VAL. MENSUAL'!G78:G89) -> 22284.83 | G15: =ROUND(H15/$E15,4) -> 0 | H15: =SUM('VAL. MENSUAL'!J78:J89) -> 0 | J15: =ROUND(K15/$E15,4) -> 1 | K15: =SUM('VAL. MENSUAL'!N78:N89) -> 22284.83 | M15: =+G15+J15 -> 1 | N15: =H15+K15 -> 22284.83 | P15: =1-M15 -> 0 | Q15: =E15-N15 -> 0
B16: =+'VAL. MENSUAL'!B90 -> 01.05 | C16: =+'VAL. MENSUAL'!C90 -> SARDINELES DE CONCRETO | E16: =SUM('VAL. MENSUAL'!G90:G101) -> 41213.67 | G16: =ROUND(H16/$E16,4) -> 0 | H16: =SUM('VAL. MENSUAL'!J90:J101) -> 0 | J16: =ROUND(K16/$E16,4) -> 1 | K16: =SUM('VAL. MENSUAL'!N90:N101) -> 41213.67 | M16: =+G16+J16 -> 1 | N16: =H16+K16 -> 41213.67 | P16: =1-M16 -> 0 | Q16: =E16-N16 -> 0
B17: =+'VAL. MENSUAL'!B102 -> 01.06 | C17: =+'VAL. MENSUAL'!C102 -> MURO DE CONTENCION | E17: =SUM('VAL. MENSUAL'!G102:G122) -> 18738.92 | G17: =ROUND(H17/$E17,4) -> 0 | H17: =SUM('VAL. MENSUAL'!J102:J122) -> 0 | J17: =ROUND(K17/$E17,4) -> 1 | K17: =SUM('VAL. MENSUAL'!N102:N122) -> 18738.92 | M17: =+G17+J17 -> 1 | N17: =H17+K17 -> 18738.92 | P17: =1-M17 -> 0 | Q17: =E17-N17 -> 0
B18: =+'VAL. MENSUAL'!B123 -> 01.07 | C18: =+'VAL. MENSUAL'!C123 -> GRADERIAS | E18: =SUM('VAL. MENSUAL'!G123:G133) -> 6001.05 | G18: =ROUND(H18/$E18,4) -> 0.3717 | H18: =SUM('VAL. MENSUAL'!J123:J133) -> 2230.76 | J18: =ROUND(K18/$E18,4) -> 0.6283 | K18: =SUM('VAL. MENSUAL'!N123:N133) -> 3770.29 | M18: =+G18+J18 -> 1 | N18: =H18+K18 -> 6001.05 | P18: =1-M18 -> 0 | Q18: =E18-N18 -> 0
B19: =+'VAL. MENSUAL'!B134 -> 01.08 | C19: =+'VAL. MENSUAL'!C134 -> JARDINERIA | E19: =SUM('VAL. MENSUAL'!G134:G136) -> 18254.61 | G19: =ROUND(H19/$E19,4) -> 0 | H19: =SUM('VAL. MENSUAL'!J134:J136) -> 0 | J19: =ROUND(K19/$E19,4) -> 1 | K19: =SUM('VAL. MENSUAL'!N134:N136) -> 18254.61 | M19: =+G19+J19 -> 1 | N19: =H19+K19 -> 18254.61 | P19: =1-M19 -> 0 | Q19: =E19-N19 -> 0
B20: =+'VAL. MENSUAL'!B137 -> 01.09 | C20: =+'VAL. MENSUAL'!C137 -> PLANTAS DECORATIVAS | E20: =SUM('VAL. MENSUAL'!G137:G138) -> 1224 | H20: =SUM('VAL. MENSUAL'!J137:J138) -> 0 | K20: =SUM('VAL. MENSUAL'!N137:N138) -> 1224 | M20: =+G20+J20 -> 0 | N20: =H20+K20 -> 1224 | P20: =1-M20 -> 1 | Q20: =E20-N20 -> 0
B21: =+'VAL. MENSUAL'!B139 -> 01.10 | C21: =+'VAL. MENSUAL'!C139 -> OTROS | E21: =SUM('VAL. MENSUAL'!G139:G140) -> 10200 | H21: =SUM('VAL. MENSUAL'!J139:J140) -> 10200 | K21: =SUM('VAL. MENSUAL'!N139:N140) -> 0 | M21: =+G21+J21 -> 0 | N21: =H21+K21 -> 10200 | P21: =1-M21 -> 1 | Q21: =E21-N21 -> 0
B22: =+'VAL. MENSUAL'!B141 -> 01.11 | C22: =+'VAL. MENSUAL'!C141 -> SEGURIDAD Y SALUD | E22: =SUM('VAL. MENSUAL'!F141:F146) -> 18340.56 | H22: =SUM('VAL. MENSUAL'!I141:I146) -> 4.3 | K22: =SUM('VAL. MENSUAL'!N141:N146) -> 840 | M22: =+G22+J22 -> 0 | N22: =H22+K22 -> 844.3 | P22: =1-M22 -> 1 | Q22: =E22-N22 -> 17496.26
B23: =+'VAL. MENSUAL'!B147 -> 01.12 | C23: =+'VAL. MENSUAL'!C147 -> FLETE | E23: =SUM('VAL. MENSUAL'!G147:G148) -> 6023 | H23: =SUM('VAL. MENSUAL'!J147:J148) -> 6023 | K23: =SUM('VAL. MENSUAL'!N147:N148) -> 0 | M23: =+G23+J23 -> 0 | N23: =H23+K23 -> 6023 | P23: =1-M23 -> 1 | Q23: =E23-N23 -> 0
B24: =+'VAL. MENSUAL'!B149 -> 01.13 | C24: =+'VAL. MENSUAL'!C149 -> IMPACTO AMBIENTAL | E24: =SUM('VAL. MENSUAL'!G149:G155) -> 18672.73 | H24: =SUM('VAL. MENSUAL'!J149:J155) -> 12903.65 | K24: =SUM('VAL. MENSUAL'!N149:N155) -> 3605 | M24: =+G24+J24 -> 0 | N24: =H24+K24 -> 16508.65 | P24: =1-M24 -> 1 | Q24: =E24-N24 -> 2164.08
C25: COSTO DIRECTO | E25: =ROUND(SUM(E12:E24),2) -> 462717.27 | G25: =+H31 -> 0.6272 | H25: =+'VAL. MENSUAL'!J157 -> 290198.67 | J25: =+K31 -> 0.351 | K25: =ROUND(SUM(K12:K24),2) -> 162392.11 | M25: =+N31 -> 0.9782 | N25: =ROUND(H25+K25,2) -> 452590.78 | P25: =+Q31 -> 0.0218 | Q25: =ROUND(E25-N25,2) -> 10126.49
C26: GASTOS GENERALES | D26: 0.1 | E26: =ROUND($D26*E$25,2) -> 46271.73 | H26: =+'VAL. MENSUAL'!J158 -> 29019.87 | K26: =ROUND($D26*K$25,2) -> 16239.21 | N26: =ROUND(H26+K26,2) -> 45259.08 | Q26: =ROUND(E26-N26,2) -> 1012.65
C27: UTILIDAD | D27: 0.07 | E27: =ROUND($D27*E$25,2) -> 32390.21 | H27: =+'VAL. MENSUAL'!J159 -> 20313.91 | K27: =ROUND($D27*K$25,2) -> 11367.45 | N27: =ROUND(H27+K27,2) -> 31681.36 | Q27: =ROUND(E27-N27,2) -> 708.85
C28: SUB TOTAL | E28: =ROUND(E25+E26+E27,2) -> 541379.21 | H28: =+'VAL. MENSUAL'!J160 -> 339532.45 | K28: =ROUND(K25+K26+K27,2) -> 189998.77 | N28: =ROUND(H28+K28,2) -> 529531.22 | Q28: =ROUND(E28-N28,2) -> 11847.99
C29: IGV | D29: 0.18 | E29: =ROUND($D$29*E28,2) -> 97448.26 | H29: =+'VAL. MENSUAL'!J161 -> 61115.84 | K29: =ROUND($D$29*K28,2) -> 34199.78 | N29: =ROUND(H29+K29,2) -> 95315.62 | Q29: =ROUND(E29-N29,2) -> 2132.64
C30: MONTO TOTAL VALORIZADO | E30: =ROUND(E28+E29,2) -> 638827.47 | H30: =+'VAL. MENSUAL'!J162 -> 400648.29 | K30: =ROUND(K28+K29,2) -> 224198.55 | N30: =ROUND(H30+K30,2) -> 624846.84 | Q30: =ROUND(E30-N30,2) -> 13980.63
C31: PORCENTAJE DE AVANCE | E31: =ROUND(E25/$E$25,4) -> 1 | H31: =+'VAL. MENSUAL'!J163 -> 0.6272 | K31: =ROUND(K25/$E$25,4) -> 0.351 | N31: =ROUND(H31+K31,4) -> 0.9782 | Q31: =ROUND(E31-N31,4) -> 0.0218

Sheet R.F.C
B1: RETENCIÓN DE GARANTÍA DE FIEL CUMPLIMIENTO
B2: Obra: | C2: =+FT!$E$5 -> "MEJORAMIENTO Y AMPLIACIÓN DE LOS SERVICIOS DE TRANSITABILIDAD VEHICULAR Y PEATONAL DEL JR LOS PINOS Y JR LOS CEDROS EN CAYHUAYNA Y CAYHUAYNA DEL DISTRITO DE PILLCO MARCA - PROVINCIA DE HUÁNUCO - DEPARTAMENTO DE HUÁNUCO" con CUI N°2536252
B3: Entidad: | C3: =+FT!$E$4 -> MUNICIPALIDAD DISTRITAL DE PILLCO MARCA
B4: Ejecutor: | C4: =+FT!$E$15 -> CONSORCIO EJECUTOR LOS PINOS
B5: Supervisor: | C5: =+FT!$E$34 -> PROYECTA PCL S.A.C
B6: Residente: | C6: =+FT!$E$32 -> ING. RAMIREZ BLANCO GABRIEL AUGUSTO HERMOGENES
B7: Ing. Supervisor: | C7: =+FT!$E$46 -> ING. CESAR RICARDO ZELADA RODRIGUEZ (CIP N° 98469)
B8: Monto del contrato: | C8: =+FT!$E$25 -> 638827.47
B10: Según el REGLAMENTO DE LA LEY GENERAL DE CONTRATACIONES PÚBLICAS: El CONSORCIO EJECUTOR LOS PINOS con el objetivo de cumplir con el Artículo 114 del Reglamento de la Ley N°32069, Ley General de Contrataciones Públicas, en los contratos de ejecución de obras que celebren las Entidades con las micro y pequeñas empresas (MYPES), estas últimas pueden otorgar como Garantía de Fiel Cumplimiento el diez por ciento (10%) del monto del contrato original, cuyo monto asciende a S/ 63,882.75 (Sesenta y Tres Mil Ochocientos Ochenta y Dos con 75/100 soles) incluido IGV, porcentaje que es retenido por la Entidad durante la primera mitad del número de pagos a realizarse, en forma prorrateada, con cargo a ser devuelto en la liquidación de la Obra.
B16: En ese sentido, se PROGRAMÓ realizar la RETENCIÓN DE GARANTÍA DE FIEL CUMPLIMIENTO en el primer pago, es decir, en la primera valorización, por un monto de retención total de S/ 63,882.75 (Sesenta y Tres Mil Ochocientos Ochenta y Dos con 75/100 soles) incluido IGV. Para dicho efecto, se verifica que las empresas consorciadas se encuentran registrados en el REMYPE.
B20: MONTO DEL CONTRATO: | D20: =+FT!$E$25 -> 638827.47
B21: TOTAL DE RETENCIÓN (10.00%): | D21: =ROUND(D20*10%,2) -> 63882.75
B23: N° | C23: MES | D23: MONTO VALORIZADO | E23: RETENCIÓN MENSUAL PROGRAMADA | F23: RETENCIÓN EFECTIVA
B24: =+'CONTROL GEN. AVAN. OBRA.'!B11 -> 1 | C24: =+'CONTROL GEN. AVAN. OBRA.'!C11 -> 46174 | D24: =+'CONTROL GEN. AVAN. OBRA.'!H11 -> 400648.29 | E24: =+D21 -> 63882.75 | F24: =IF(D24<E24,D24,E24) -> 63882.75
B25: =+'CONTROL GEN. AVAN. OBRA.'!B12 -> 2 | C25: =+'CONTROL GEN. AVAN. OBRA.'!C12 -> 46204 | D25: =+'CONTROL GEN. AVAN. OBRA.'!H12 -> 224198.55 | E25: 0 | F25: =IF(D25<E25,D25,E25) -> 0
B26: =+'CONTROL GEN. AVAN. OBRA.'!B13 -> 3 | C26: =+'CONTROL GEN. AVAN. OBRA.'!C13 -> 46235 | D26: =+'CONTROL GEN. AVAN. OBRA.'!H13 -> 0 | E26: 0 | F26: =IF(D26<E26,D26,E26) -> 0
B28: RETENCIÓN ANTERIOR ACUMULADA | F28: =+F24 -> 63882.75
B29: RETENCIÓN ACTUAL | F29: =+F25 -> 0
B30: RETENCIÓN ACTUAL ACUMULADA | F30: =+F28+F29 -> 63882.75
B31: SALDO POR RETENER | F31: =+D21-F30 -> 0
E33: TOTAL A RETENERSE POR GARANTÍA DE FIEL CUMPLIMIENTO: | F33: =+F29 -> 0

Sheet R PAGO MENSUAL
B1: ="RESUMEN DE PAGO DE LA "&'VAL. MENSUAL'!B1 -> RESUMEN DE PAGO DE LA VALORIZACIÓN N°02 DEL MES DE JULIO DE 2026
B2: Obra: | C2: =+FT!$E$5 -> "MEJORAMIENTO Y AMPLIACIÓN DE LOS SERVICIOS DE TRANSITABILIDAD VEHICULAR Y PEATONAL DEL JR LOS PINOS Y JR LOS CEDROS EN CAYHUAYNA Y CAYHUAYNA DEL DISTRITO DE PILLCO MARCA - PROVINCIA DE HUÁNUCO - DEPARTAMENTO DE HUÁNUCO" con CUI N°2536252
B3: Entidad: | C3: =+FT!$E$4 -> MUNICIPALIDAD DISTRITAL DE PILLCO MARCA
B4: Ejecutor: | C4: =+FT!$E$15 -> CONSORCIO EJECUTOR LOS PINOS
B5: Supervisor: | C5: =+FT!$E$34 -> PROYECTA PCL S.A.C
B6: Residente: | C6: =+FT!$E$32 -> ING. RAMIREZ BLANCO GABRIEL AUGUSTO HERMOGENES
B7: Ing. Supervisor: | C7: =+FT!$E$46 -> ING. CESAR RICARDO ZELADA RODRIGUEZ (CIP N° 98469)
B9: ITEM | C9: DESCRIPCIÓN | E9: MONTO
B11: =+'RESUMEN VAL.'!B12 -> 01.01 | C11: =+'RESUMEN VAL.'!C12 -> OBRAS PROVISIONALES Y TRABAJOS PRELIMINARES | D11: =+'RESUMEN VAL.'!J12 -> 0.0636 | E11: =+'RESUMEN VAL.'!K12 -> 1560
B12: =+'RESUMEN VAL.'!B13 -> 01.02 | C12: =+'RESUMEN VAL.'!C13 -> PAVIMENTO RIGIDO | D12: =+'RESUMEN VAL.'!J13 -> 0 | E12: =+'RESUMEN VAL.'!K13 -> 0
B13: =+'RESUMEN VAL.'!B14 -> 01.03 | C13: =+'RESUMEN VAL.'!C14 -> VEREDAS, RAMPAS Y MARTILLOS | D13: =+'RESUMEN VAL.'!J14 -> 0.6262 | E13: =+'RESUMEN VAL.'!K14 -> 50900.79
B14: =+'RESUMEN VAL.'!B15 -> 01.04 | C14: =+'RESUMEN VAL.'!C15 -> CUNETA PLUVIAL | D14: =+'RESUMEN VAL.'!J15 -> 1 | E14: =+'RESUMEN VAL.'!K15 -> 22284.83
B15: =+'RESUMEN VAL.'!B16 -> 01.05 | C15: =+'RESUMEN VAL.'!C16 -> SARDINELES DE CONCRETO | D15: =+'RESUMEN VAL.'!J16 -> 1 | E15: =+'RESUMEN VAL.'!K16 -> 41213.67
B16: =+'RESUMEN VAL.'!B17 -> 01.06 | C16: =+'RESUMEN VAL.'!C17 -> MURO DE CONTENCION | D16: =+'RESUMEN VAL.'!J17 -> 1 | E16: =+'RESUMEN VAL.'!K17 -> 18738.92
B17: =+'RESUMEN VAL.'!B18 -> 01.07 | C17: =+'RESUMEN VAL.'!C18 -> GRADERIAS | D17: =+'RESUMEN VAL.'!J18 -> 0.6283 | E17: =+'RESUMEN VAL.'!K18 -> 3770.29
B18: =+'RESUMEN VAL.'!B19 -> 01.08 | C18: =+'RESUMEN VAL.'!C19 -> JARDINERIA | D18: =+'RESUMEN VAL.'!J19 -> 1 | E18: =+'RESUMEN VAL.'!K19 -> 18254.61
B19: =+'RESUMEN VAL.'!B20 -> 01.09 | C19: =+'RESUMEN VAL.'!C20 -> PLANTAS DECORATIVAS | D19: =+'RESUMEN VAL.'!J20 -> 0 | E19: =+'RESUMEN VAL.'!K20 -> 1224
B20: =+'RESUMEN VAL.'!B21 -> 01.10 | C20: =+'RESUMEN VAL.'!C21 -> OTROS | D20: =+'RESUMEN VAL.'!J21 -> 0 | E20: =+'RESUMEN VAL.'!K21 -> 0
B21: =+'RESUMEN VAL.'!B22 -> 01.11 | C21: =+'RESUMEN VAL.'!C22 -> SEGURIDAD Y SALUD | D21: =+'RESUMEN VAL.'!J22 -> 0 | E21: =+'RESUMEN VAL.'!K22 -> 840
B22: =+'RESUMEN VAL.'!B23 -> 01.12 | C22: =+'RESUMEN VAL.'!C23 -> FLETE | D22: =+'RESUMEN VAL.'!J23 -> 0 | E22: =+'RESUMEN VAL.'!K23 -> 0
B23: =+'RESUMEN VAL.'!B24 -> 01.13 | C23: =+'RESUMEN VAL.'!C24 -> IMPACTO AMBIENTAL | D23: =+'RESUMEN VAL.'!J24 -> 0 | E23: =+'RESUMEN VAL.'!K24 -> 3605
C24: COSTO DIRECTO | E24: =ROUND(SUM(E11:E23),2) -> 162392.11
C25: GASTOS GENERALES | D25: =+'RESUMEN VAL.'!D26 -> 0.1 | E25: =ROUND($D25*E$24,2) -> 16239.21
C26: UTILIDAD | D26: =+'RESUMEN VAL.'!D27 -> 0.07 | E26: =ROUND($D26*E$24,2) -> 11367.45
C27: SUB TOTAL | E27: =ROUND(E24+E25+E26,2) -> 189998.77
C28: IGV | D28: 0.18 | E28: =ROUND($D$28*E27,2) -> 34199.78
B29: A | C29: VALORIZACIÓN DEL MES SIN REAJUSTE | D29: =+'RESUMEN VAL.'!K31 -> 0.351 | E29: =E27+E28 -> 224198.55
B30: B | C30: REAJUSTE DE LA VALORIZACIÓN | E30: 0
C31: REAJUSTE DEL MES | E31: 0
C32: REINTEGRO DEL MES ANTERIOR | E32: 0
B33: C | C33: MONTO BRUTO VALORIZADO REAJUSTADO | D33: (A+B) | E33: =E29+E30 -> 224198.55
B34: D | C34: DEDUCCIÓN DEL REAJUSTE QUE NO CORRESPONDE | E34: =SUM(E35:E36) -> 0
C35: POR ADELANTO DIRECTO | D35: (-) | E35: 0
C36: POR ADELANTO DE MATERIALES | D36: (-) | E36: 0
B37: E | C37: AMORTIZACIÓN POR ADELANTOS | E37: =SUM(E38:E39) -> 0
C38: POR ADELANTO DIRECTO | D38: (-) | E38: 0
C39: POR ADELANTO DE MATERIALES | D39: (-) | E39: 0
B40: F | C40: MONTO NETO VALORIZADO FACTURABLE | D40: (C-D-E) | E40: =E33-E34-E37 -> 224198.55
B41: G | C41: RETENCIONES | E41: =SUM(E42:E43) -> 8968
C42: POR GARANTÍA DE FIEL CUMPLIMIENTO | D42: (-) | E42: =+'R.F.C'!F29 -> 0
C43: DETRACCIONES (4%) | E43: =ROUND(E40*4%,0) -> 8968
B44: H | C44: PENALIDADES | E44: =SUM(E45:E46) -> 0
C45: POR ATRASO DE OBRA | D45: (-) | E45: 0
C46: OTROS | D46: (-) | E46: 0
B47: J | C47: MONTO A FACTURAR POR EL CONTRATISTA | D47: (F) | E47: =E40 -> 224198.55
B48: K | C48: MONTO LÍQUIDO A PAGAR AL CONTRATISTA | D48: (F-G-H) | E48: =+E40-E41-E44 -> 215230.55
B50: El monto a facturar por el contratista ejecutor CONSORCIO EJECUTOR LOS PINOS en la presente VALORIZACIÓN N°02 DEL MES DE JULIO DE 2026, asciende a la suma de S/ 224,198.55 (Doscientos Veinticuatro Mil Ciento Noventa y Ocho con 55/100 soles) incluido IGV.

Sheet PAGOS ACUMULADOS
B1: ="RESUMEN DE LA "&'VAL. MENSUAL'!B1 -> RESUMEN DE LA VALORIZACIÓN N°02 DEL MES DE JULIO DE 2026
B2: Obra: | C2: =+FT!$E$5 -> "MEJORAMIENTO Y AMPLIACIÓN DE LOS SERVICIOS DE TRANSITABILIDAD VEHICULAR Y PEATONAL DEL JR LOS PINOS Y JR LOS CEDROS EN CAYHUAYNA Y CAYHUAYNA DEL DISTRITO DE PILLCO MARCA - PROVINCIA DE HUÁNUCO - DEPARTAMENTO DE HUÁNUCO" con CUI N°2536252
B3: Entidad: | C3: =+FT!$E$4 -> MUNICIPALIDAD DISTRITAL DE PILLCO MARCA
B4: Ejecutor: | C4: =+FT!$E$15 -> CONSORCIO EJECUTOR LOS PINOS
B5: Supervisor: | C5: =+FT!$E$34 -> PROYECTA PCL S.A.C
B6: Residente: | C6: =+FT!$E$32 -> ING. RAMIREZ BLANCO GABRIEL AUGUSTO HERMOGENES
B7: Ing. Supervisor: | C7: =+FT!$E$46 -> ING. CESAR RICARDO ZELADA RODRIGUEZ (CIP N° 98469)
B9: ÍTEM | C9: DESCRIPCIÓN DE SUB PRESUPUESTOS | E9: MONTO CONTRATADO | F9: ACUMULADO ANTERIOR | G9: ACTUAL | H9: ACUMULADO ACTUAL | I9: SALDO POR PAGAR
B11: =+'RESUMEN VAL.'!B12 -> 01.01 | C11: =+'RESUMEN VAL.'!C12 -> OBRAS PROVISIONALES Y TRABAJOS PRELIMINARES | E11: =+'RESUMEN VAL.'!E12 -> 24540.72 | F11: 21290.72 | G11: =+'RESUMEN VAL.'!K12 -> 1560 | H11: =+F11+G11 -> 22850.72 | I11: =+E11-H11 -> 1690
B12: =+'RESUMEN VAL.'!B13 -> 01.02 | C12: =+'RESUMEN VAL.'!C13 -> PAVIMENTO RIGIDO | E12: =+'RESUMEN VAL.'!E13 -> 195936.33 | F12: 190783.92 | G12: =+'RESUMEN VAL.'!K13 -> 0 | H12: =+F12+G12 -> 190783.92 | I12: =+E12-H12 -> 5152.41
B13: =+'RESUMEN VAL.'!B14 -> 01.03 | C13: =+'RESUMEN VAL.'!C14 -> VEREDAS, RAMPAS Y MARTILLOS | E13: =+'RESUMEN VAL.'!E14 -> 81286.85 | F13: 30386.06 | G13: =+'RESUMEN VAL.'!K14 -> 50900.79 | H13: =+F13+G13 -> 81286.85 | I13: =+E13-H13 -> 0
B14: =+'RESUMEN VAL.'!B15 -> 01.04 | C14: =+'RESUMEN VAL.'!C15 -> CUNETA PLUVIAL | E14: =+'RESUMEN VAL.'!E15 -> 22284.83 | F14: 0 | G14: =+'RESUMEN VAL.'!K15 -> 22284.83 | H14: =+F14+G14 -> 22284.83 | I14: =+E14-H14 -> 0
B15: =+'RESUMEN VAL.'!B16 -> 01.05 | C15: =+'RESUMEN VAL.'!C16 -> SARDINELES DE CONCRETO | E15: =+'RESUMEN VAL.'!E16 -> 41213.67 | F15: 0 | G15: =+'RESUMEN VAL.'!K16 -> 41213.67 | H15: =+F15+G15 -> 41213.67 | I15: =+E15-H15 -> 0
B16: =+'RESUMEN VAL.'!B17 -> 01.06 | C16: =+'RESUMEN VAL.'!C17 -> MURO DE CONTENCION | E16: =+'RESUMEN VAL.'!E17 -> 18738.92 | F16: 0 | G16: =+'RESUMEN VAL.'!K17 -> 18738.92 | H16: =+F16+G16 -> 18738.92 | I16: =+E16-H16 -> 0
B17: =+'RESUMEN VAL.'!B18 -> 01.07 | C17: =+'RESUMEN VAL.'!C18 -> GRADERIAS | E17: =+'RESUMEN VAL.'!E18 -> 6001.05 | F17: 2230.76 | G17: =+'RESUMEN VAL.'!K18 -> 3770.29 | H17: =+F17+G17 -> 6001.05 | I17: =+E17-H17 -> 0
B18: =+'RESUMEN VAL.'!B19 -> 01.08 | C18: =+'RESUMEN VAL.'!C19 -> JARDINERIA | E18: =+'RESUMEN VAL.'!E19 -> 18254.61 | F18: 0 | G18: =+'RESUMEN VAL.'!K19 -> 18254.61 | H18: =+F18+G18 -> 18254.61 | I18: =+E18-H18 -> 0
B19: =+'RESUMEN VAL.'!B20 -> 01.09 | C19: =+'RESUMEN VAL.'!C20 -> PLANTAS DECORATIVAS | E19: =+'RESUMEN VAL.'!E20 -> 1224 | F19: 0 | G19: =+'RESUMEN VAL.'!K20 -> 1224
B20: =+'RESUMEN VAL.'!B21 -> 01.10 | C20: =+'RESUMEN VAL.'!C21 -> OTROS | E20: =+'RESUMEN VAL.'!E21 -> 10200 | F20: 10200 | G20: =+'RESUMEN VAL.'!K21 -> 0
B21: =+'RESUMEN VAL.'!B22 -> 01.11 | C21: =+'RESUMEN VAL.'!C22 -> SEGURIDAD Y SALUD | E21: =+'RESUMEN VAL.'!E22 -> 18340.56 | F21: 16380.56 | G21: =+'RESUMEN VAL.'!K22 -> 840
B22: =+'RESUMEN VAL.'!B23 -> 01.12 | C22: =+'RESUMEN VAL.'!C23 -> FLETE | E22: =+'RESUMEN VAL.'!E23 -> 6023 | F22: 6023 | G22: =+'RESUMEN VAL.'!K23 -> 0
B23: =+'RESUMEN VAL.'!B24 -> 01.13 | C23: =+'RESUMEN VAL.'!C24 -> IMPACTO AMBIENTAL | E23: =+'RESUMEN VAL.'!E24 -> 18672.73 | F23: 12903.65 | G23: =+'RESUMEN VAL.'!K24 -> 3605
C24: COSTO DIRECTO | E24: =ROUND(SUM(E11:E23),2) -> 462717.27 | F24: 290198.67 | G24: =ROUND(SUM(G11:G23),2) -> 162392.11 | H24: =+F24+G24 -> 452590.78 | I24: =+E24-H24 -> 10126.49
C25: GASTOS GENERALES | D25: =+'RESUMEN VAL.'!D26 -> 0.1 | E25: =ROUND($D25*E$24,2) -> 46271.73 | F25: 29019.87 | G25: =ROUND($D25*G$24,2) -> 16239.21 | H25: =+F25+G25 -> 45259.08 | I25: =+E25-H25 -> 1012.65
C26: UTILIDAD | D26: =+'RESUMEN VAL.'!D27 -> 0.07 | E26: =ROUND($D26*E$24,2) -> 32390.21 | F26: 20313.91 | G26: =ROUND($D26*G$24,2) -> 11367.45 | H26: =+F26+G26 -> 31681.36 | I26: =+E26-H26 -> 708.85
C27: SUB TOTAL | E27: =ROUND(E24+E25+E26,2) -> 541379.21 | F27: 339532.45 | G27: =ROUND(G24+G25+G26,2) -> 189998.77 | H27: =+F27+G27 -> 529531.22 | I27: =+E27-H27 -> 11847.99
C28: IGV | D28: 0.18 | E28: =ROUND($D$28*E27,2) -> 97448.26 | F28: 61115.84 | G28: =ROUND($D$28*G27,2) -> 34199.78 | H28: =+F28+G28 -> 95315.62 | I28: =+E28-H28 -> 2132.64
B29: A | C29: VALORIZACIÓN MENSUAL | D29: =+'RESUMEN VAL.'!K31 -> 0.351 | E29: =ROUND(E27+E28,2) -> 638827.47 | F29: 400648.29 | G29: =ROUND(G27+G28,2) -> 224198.55 | H29: =+F29+G29 -> 624846.84 | I29: =+E29-H29 -> 13980.63
B30: B | C30: REAJUSTE DE LA VALORIZACIÓN | E30: =+E31+E32 -> 0 | F30: 0 | G30: =+G31-G32 -> 0 | H30: =+F30+G30 -> 0 | I30: =+E30-H30 -> 0
C31: REAJUSTE DEL MES | E31: 0 | F31: 0 | G31: 0 | H31: =+F31+G31 -> 0 | I31: =+E31-H31 -> 0
C32: REINTEGRO DEL MES ANTERIOR | E32: 0 | F32: 0 | G32: 0 | H32: =+F32+G32 -> 0 | I32: =+E32-H32 -> 0
B33: C | C33: MONTO BRUTO VALORIZADO REAJUSTADO | D33: (A+B) | E33: =+E29+E30 -> 638827.47 | F33: 400648.29 | G33: =+G29+G30 -> 224198.55 | H33: =+F33+G33 -> 624846.84 | I33: =+E33-H33 -> 13980.63
B34: D | C34: DEDUCCIÓN DEL REAJUSTE QUE NO CORRESPONDE | E34: =+E35+E36 -> 0 | F34: 0 | G34: =+G35+G36 -> 0 | H34: =+F34+G34 -> 0 | I34: =+E34-H34 -> 0
C35: POR ADELANTO DIRECTO | D35: (-) | E35: 0 | F35: 0 | G35: 0 | H35: =+F35+G35 -> 0 | I35: =+E35-H35 -> 0
C36: POR ADELANTO DE MATERIALES | D36: (-) | E36: 0 | F36: 0 | G36: 0 | H36: =+F36+G36 -> 0 | I36: =+E36-H36 -> 0
B37: E | C37: AMORTIZACIÓN POR ADELANTOS | E37: =+E38+E39 -> 0 | F37: 0 | G37: =+G38+G39 -> 0 | H37: =+F37+G37 -> 0 | I37: =+E37-H37 -> 0
C38: POR ADELANTO DIRECTO | D38: (-) | E38: 0 | F38: 0 | G38: 0 | H38: =+F38+G38 -> 0 | I38: =+E38-H38 -> 0
C39: POR ADELANTO DE MATERIALES | D39: (-) | E39: 0 | F39: 0 | G39: 0 | H39: =+F39+G39 -> 0 | I39: =+E39-H39 -> 0
B40: F | C40: MONTO NETO VALORIZADO FACTURABLE | D40: (C-D-E) | E40: =+E33+E34+E37 -> 638827.47 | F40: 400648.29 | G40: =+G33+G34+G37 -> 224198.55 | H40: =+F40+G40 -> 624846.84 | I40: =+E40-H40 -> 13980.63
B41: G | C41: RETENCIONES | E41: =+E42+E43 -> 89435.75 | F41: 79908.75 | G41: =+G42+G43 -> 8968 | H41: =+F41+G41 -> 88876.75 | I41: =+E41-H41 -> 559
C42: POR GARANTÍA DE FIEL CUMPLIMIENTO | D42: (-) | E42: =+'R.F.C'!D21 -> 63882.75 | F42: 63882.75 | G42: =+'R.F.C'!F33 -> 0 | H42: =+F42+G42 -> 63882.75 | I42: =+E42-H42 -> 0
C43: DETRACCIONES (4%) | E43: =ROUND(E40*4%,0) -> 25553 | F43: 16026 | G43: =ROUND(G40*4%,0) -> 8968 | H43: =+F43+G43 -> 24994 | I43: =+E43-H43 -> 559
B44: H | C44: PENALIDADES | E44: =+E45+E46 -> 0 | F44: 0 | G44: =+G45+G46 -> 0 | H44: =+F44+G44 -> 0 | I44: =+E44-H44 -> 0
C45: POR ATRASO DE OBRA | D45: (-) | E45: 0 | F45: 0 | G45: 0 | H45: =+F45+G45 -> 0 | I45: =+E45-H45 -> 0
C46: OTROS | D46: (-) | E46: 0 | F46: 0 | G46: 0 | H46: =+F46+G46 -> 0 | I46: =+E46-H46 -> 0
B47: J | C47: MONTO A FACTURAR POR EL CONTRATISTA | D47: (F) | E47: =+E40 -> 638827.47 | F47: 400648.29 | G47: =+G40 -> 224198.55 | H47: =+F47+G47 -> 624846.84 | I47: =+E47-H47 -> 13980.63
B48: K | C48: MONTO LÍQUIDO A PAGAR AL CONTRATISTA | D48: (F-G-H) | E48: =+E40-E41-E44 -> 549391.72 | F48: 320739.54 | G48: =+G40-G41-G44 -> 215230.55 | H48: =+F48+G48 -> 535970.09 | I48: =+E48-H48 -> 13421.63
B50: =+'R PAGO MENSUAL'!B50 -> El monto a facturar por el contratista ejecutor CONSORCIO EJECUTOR LOS PINOS en la presente VALORIZACIÓN N°02 DEL MES DE JULIO DE 2026, asciende a la suma de S/ 224,198.55 (Doscientos Veinticuatro Mil Ciento Noventa y Ocho con 55/100 soles) incluido IGV.

Sheet CONTROL DE PAGOS
B1: RESUMEN DE VALORIZACIONES TRAMITADAS Y PAGADAS
B2: =+FT!$C$5 -> Obra | C2: =+FT!$E$5 -> "MEJORAMIENTO Y AMPLIACIÓN DE LOS SERVICIOS DE TRANSITABILIDAD VEHICULAR Y PEATONAL DEL JR LOS PINOS Y JR LOS CEDROS EN CAYHUAYNA Y CAYHUAYNA DEL DISTRITO DE PILLCO MARCA - PROVINCIA DE HUÁNUCO - DEPARTAMENTO DE HUÁNUCO" con CUI N°2536252
B3: Entidad: | C3: =+FT!$E$4 -> MUNICIPALIDAD DISTRITAL DE PILLCO MARCA
B4: Ejecutor: | C4: =+FT!$E$15 -> CONSORCIO EJECUTOR LOS PINOS
B5: Supervisor: | C5: =+FT!$E$34 -> PROYECTA PCL S.A.C | F5: VALOR REFERENCIAL (CON IGV) | H5: =+FT!$E$24 -> 638827.47
B6: Residente: | C6: =+FT!$E$32 -> ING. RAMIREZ BLANCO GABRIEL AUGUSTO HERMOGENES | F6: MONTO DEL CONTRATO (INCL. IGV): | H6: =+FT!$E$25 -> 638827.47
B7: Ing. Supervisor: | C7: =+FT!$E$46 -> ING. CESAR RICARDO ZELADA RODRIGUEZ (CIP N° 98469) | F7: PLAZO DE EJECUCIÓN: | H7: =+FT!$E$31 -> SESENTA (60) DÍAS CALENDARIOS
B9: CONTRATO PRINCIPAL
B10: VALORIZACIONES CONTRACTUALES | F10: VALORIZACIÓN BRUTA | G10: AMORTIZACIONES | I10: VALORIZACIÓN NETA FACTURABLE | J10: RETENCIONES (G.F.C) | K10: PENALIDADES | L10: DETRACCIONES | M10: MONTO LÍQUIDO PAGADO | P10: COMPROBANTES DE PAGO
B11: Nro | C11: MES | D11: MONTO | E11: REAJUSTE | G11: DIRECTO | H11: MATERIALES | P11: FACTURA Nro. | Q11: COMPROBANTE Nro. | R11: FECHA DE PAGO
D12: (V) | E12: (R) | F12: Vb=V+R | G12: (D) | H12: (M) | I12: Vn=Vb-(D+M) | J12: (G) | K12: (P) | L12: (D)
B13: 1 | C13: =+'CONTROL GEN. AVAN. OBRA.'!C11 -> 46174 | D13: =+'CONTROL GEN. AVAN. OBRA.'!H11 -> 400648.29 | E13: 0 | F13: =+D13+E13 -> 400648.29 | G13: 0 | H13: 0 | I13: =+F13-(G13+H13) -> 400648.29 | J13: =+'R.F.C'!F24 -> 63882.75 | K13: 0 | L13: =ROUND(I13*4%,0) -> 16026 | M13: =ROUND(O13/1.18,2) -> 271813.17 | N13: =+O13-M13 -> 48926.37 | O13: =+I13-(J13+K13+L13) -> 320739.54
B14: 2 | C14: =+'CONTROL GEN. AVAN. OBRA.'!C12 -> 46204 | D14: =+'CONTROL GEN. AVAN. OBRA.'!H12 -> 224198.55 | E14: 0 | F14: =+D14+E14 -> 224198.55 | G14: 0 | H14: 0 | I14: =+F14-(G14+H14) -> 224198.55 | J14: 0 | K14: 0 | L14: =ROUND(I14*4%,0) -> 8968 | M14: =ROUND(O14/1.18,2) -> 182398.77 | N14: =+O14-M14 -> 32831.78 | O14: =+I14-(J14+K14+L14) -> 215230.55
B15: 3 | C15: =+'CONTROL GEN. AVAN. OBRA.'!C13 -> 46235 | D15: =+'[12]CGO-OP'!H27 -> 0 | E15: 0 | F15: =+D15+E15 -> 0 | G15: 0 | H15: 0 | I15: =+F15-(G15+H15) -> 0 | J15: 0 | K15: 0 | L15: =ROUND(I15*4%,0) -> 0 | M15: =ROUND(O15/1.18,2) -> 0 | N15: =+O15-M15 -> 0 | O15: =+I15-(J15+K15+L15) -> 0
B16: TOTAL | D16: =SUM(D13:D15) -> 624846.84 | E16: =SUM(E13:E15) -> 0 | F16: =SUM(F13:F15) -> 624846.84 | G16: =SUM(G13:G15) -> 0 | H16: =SUM(H13:H15) -> 0 | I16: =SUM(I13:I15) -> 624846.84 | J16: =SUM(J13:J15) -> 63882.75 | K16: =SUM(K13:K15) -> 0 | ... O16: =SUM(O13:O15) -> 535970.09
B18: ADICIONALES, COSTO ADICIONALES, MAYORES GASTOS GENERALES, INTERESES Y OTROS
B19: VALORIZACIONES DE ADICIONAL | F19: VALORIZACIÓN BRUTA | G19: AMORTIZACIONES | I19: VALORIZACIÓN NETA FACTURABLE | J19: RETENCIONES | M19: MONTO NETO PAGADO | P19: COMPROBANTES DE PAGO
B20: Nro | C20: MES | D20: MONTO | E20: REAJUSTE | G20: DIRECTO | H20: MATERIALES | J20: G.F.C. | K20: PENALIDADES | M20: EFECTIVO | N20: I.G.V. | O20: TOTAL | P20: FACTURA Nro. | Q20: COMPROBANTE Nro. | R20: FECHA DE PAGO
D21: (V) | E21: (R) | F21: Vb=V+R | G21: (D) | H21: (M) | I21: Vn=Vb-(D+M) | J21: (G) | K21: (P) | M21: Vn-(G+P) | N21: 0.18
B22: 1 | C22: =+C13 -> 46174 | D22: 0 | E22: 0 | F22: =+D22+E22 -> 0 | G22: 0 | H22: 0 | I22: =+F22-(G22+H22) -> 0 | K22: 0 | M22: =(I22-(J22+K22))/1.18 -> 0 | N22: =M22*18% -> 0 | O22: =+M22+N22 -> 0
B23: 2 | C23: =+C14 -> 46204 | D23: 0 | E23: 0 | F23: =+D23+E23 -> 0 | G23: 0 | H23: 0 | I23: =+F23-(G23+H23) -> 0 | J23: 0 | K23: 0 | N23: =M23*18% -> 0 | O23: =+M23+N23 -> 0
B24: 3 | C24: =+C15 -> 46235 | D24: 0 | E24: 0 | F24: =+D24+E24 -> 0 | G24: 0 | H24: 0 | I24: =+F24-(G24+H24) -> 0 | J24: 0 | K24: 0 | N24: =M24*18% -> 0 | O24: =+M24+N24 -> 0
B25: TOTAL | D25: =SUM(D22:D24) -> 0 | E25: =SUM(E22:E24) -> 0 | F25: =SUM(F22:F24) -> 0 | G25: =SUM(G22:G24) -> 0 | H25: =SUM(H22:H24) -> 0 | I25: =SUM(I22:I24) -> 0 | J25: =SUM(J22:J24) -> 0 | K25: =SUM(K22:K24) -> 0 | M25: =SUM(M22:M24) -> 0 | N25: =SUM(N22:N24) -> 0 | O25: =SUM(O22:O24) -> 0
J27: ADELANTOS (C/IGV) | M27: MONTO NETO PAGADO | P27: COMPROBANTES DE PAGO
J28: Nro. | K28: DIRECTO | L28: MATERIALES | M28: EFECTIVO | N28: I.G.V. | O28: TOTAL | P28: FACTURA Nro. | Q28: COMPROBANTE Nro. | R28: FECHA DE PAGO
J30: 1 | K30: 0 | M30: =+K30/1.18 -> 0 | N30: =+M30*18% -> 0 | O30: =+M30+N30 -> 0
J31: 2 | L31: 0 | M31: =+L31/1.18 -> 0 | N31: =+M31*18% -> 0 | O31: =+M31+N31 -> 0
J32: TOTAL | K32: =SUM(K30:K31) -> 0 | L32: =SUM(L30:L31) -> 0 | M32: =SUM(M30:M31) -> 0 | N32: =SUM(N30:N31) -> 0 | O32: =SUM(O30:O31) -> 0
B34: TOTAL | D34: =+D16+D25 -> 624846.84 | E34: =+E16+E25 -> 0 | F34: =+F16+F25 -> 624846.84 | G34: =+G16+G25 -> 0 | H34: =+H16+H25 -> 0 | I34: =+I16+I25 -> 624846.84 | J34: =+J16+J25 -> 63882.75 | K34: =+K16+K25 -> 0 | ... O34: =+O16+O25 -> 535970.09

Sheet RH-EM
B1: CRONOGRAMA DE PARTICIPACIÓN DE PERSONAL CLAVE - JULIO 2026
B2: =+FT!$C$5 -> Obra | C2: =+FT!$E$5 -> "MEJORAMIENTO Y AMPLIACIÓN DE LOS SERVICIOS DE TRANSITABILIDAD VEHICULAR Y PEATONAL DEL JR LOS PINOS Y JR LOS CEDROS EN CAYHUAYNA Y CAYHUAYNA DEL DISTRITO DE PILLCO MARCA - PROVINCIA DE HUÁNUCO - DEPARTAMENTO DE HUÁNUCO" con CUI N°2536252
B3: Entidad: | C3: =+FT!$E$4 -> MUNICIPALIDAD DISTRITAL DE PILLCO MARCA
B4: Ejecutor: | C4: =+FT!$E$15 -> CONSORCIO EJECUTOR LOS PINOS
B5: Supervisor: | C5: =+FT!$E$34 -> PROYECTA PCL S.A.C | D5: VALOR REFERENCIAL (CON IGV) | E5: =+FT!$E$24 -> 638827.47
B6: Residente: | C6: =+FT!$E$32 -> ING. RAMIREZ BLANCO GABRIEL AUGUSTO HERMOGENES | D6: MONTO DEL CONTRATO (INCL. IGV): | E6: =+FT!$E$25 -> 638827.47
B7: Ing. Supervisor: | C7: =+FT!$E$46 -> ING. CESAR RICARDO ZELADA RODRIGUEZ (CIP N° 98469) | D7: PLAZO DE EJECUCIÓN: | E7: =+FT!$E$31 -> SESENTA (60) DÍAS CALENDARIOS
B9: PERSONAL CLAVE
B10: ÍTEM | C10: PROFESIONALES | D10: CARGO | E10: CANTIDAD | F10: DÍAS ASISTIDOS EN EL MES
B12: 1 | C12: =+FT!E32 -> ING. RAMIREZ BLANCO GABRIEL AUGUSTO HERMOGENES | D12: RESIDENTE DE OBRA | E12: 1 | F12: 1
B13: 2 | C13: ING. PAJUELO VASQUEZ, BAYLON ARTURO | D13: ESPECIALISTA DE SEGURIDAD Y SALUD EN EL TRABAJO | E13: 1 | F13: 1
B15: PERSONAL CLAVE | AL15: TOTAL DÍAS
B16: ÍTEM | C16: PROFESIONALES | D16: CARGO | E16: DNI | F16: CIP | G16: X | H16: J | I16: V | J16: S | K16: D | L16: L | M16: M | N16: X | O16: J | P16: V | Q16: S | R16: D | S16: L | T16: M | U16: X | V16: J | W16: V | X16: S | Y16: D | Z16: L | AA16: M | AB16: X | AC16: J | AD16: V | AE16: S | AF16: D | AG16: L | AH16: M | AI16: X | AJ16: J | AK16: V
G17: 1 | H17: 2 | I17: 3 | J17: 4 | K17: 5 | L17: 6 | M17: 7 | N17: 8 | O17: 9 | P17: 10 | Q17: 11 | R17: 12 | S17: 13 | T17: 14 | U17: 15 | V17: 16 | W17: 17 | X17: 18 | Y17: 19 | Z17: 20 | AA17: 21 | AB17: 22 | AC17: 23 | AD17: 24 | AE17: 25 | AF17: 26 | AG17: 27 | AH17: 28 | AI17: 29 | AJ17: 30 | AK17: 31
B18: 1 | C18: =+C12 -> ING. RAMIREZ BLANCO GABRIEL AUGUSTO HERMOGENES | D18: =+D12 -> RESIDENTE DE OBRA | E18: 71535828 | F18: 230440 | AL18: 31
B19: 2 | C19: =+C13 -> ING. PAJUELO VASQUEZ, BAYLON ARTURO | D19: =+D13 -> ESPECIALISTA DE SEGURIDAD Y SALUD EN EL TRABAJO | E19: 22520709 | F19: 86312 | AL19: 31

Sheet resumen 3
A1: RESUMEN DE LA VALORIZACION N° 03
A2: Del 01 de Octubre Al 31 de Octubre del 2014
A4: PROYECTO : | B4: =#REF! -> #REF!
A6: LUGAR : | B6: CODO DEL POZUZO - PUERTO INCA - HUANUCO.
A7: FECHA : | B7: =#REF! -> #REF!
A9: ITEM | B9: DESCRIPCION | F9: PRESUPUESTO BASE | G9: EJECUTADO
G10: MONTO | H10: %
A11: 01 | B11: EJECUCIÓN DE LA PRIMERA ETAPA DE LA OBRA “MEJORAMIENTO DE CAMINOS VECINALES, TRAMO CODO DE POZUZO – INDEPENDENCIA - NUEVO HORIZONTE, TRAMO DESVIÓ KM 1 + 500 DEL C.V. CODO DE POZUZO – NUEVO HORIZONTE A ALTO MASHOCA, TRAMO DESVIO KM 6 + 200 DEL C.V. CODO DE POZUZO – NUEVO HORIZONTE A BAJO MASHOCA, EN EL DISTRITO DE CODO DE POZUZO, PROVINCIA DE PUERTO INCA - HUANUCO” PRIMERA ETAPA | F11: =#REF! -> #REF! | G11: =#REF! -> #REF! | H11: =#REF! -> #REF!
C12: COSTO DIRECTO : | F12: =SUM(F11:F11) -> #REF! | G12: =SUM(G11:G11) -> #REF! | H12: =G12/F12 -> #REF!
C13: GASTOS GENERALES (7.5%) : | F13: =F12*0.075 -> #REF! | G13: =G12*0.075 -> #REF!
C14: UTILIDAD (5%) : | F14: =F12*0.05 -> #REF! | G14: =G12*0.05 -> #REF!
C15: SUB TOTAL : | F15: =SUM(F12:F14) -> #REF! | G15: =SUM(G12:G14)-0.01 -> #REF!
C16: IGV(18%) | F16: =F15*0.18+0.01 -> #REF! | G16: =G15*0.18-0.01 -> #REF!
F17: =SUM(F15:F16)-0.01 -> #REF! | G17: =SUM(G15:G16)+0.01 -> #REF!
C18: FACTOR DE RELACION (1.00000) | F18: =F17*1 -> #REF! | G18: =G17*1 -> #REF!
C19: COSTO DE EJECUCION PRIMERA ETAPA | F19: =F18 -> #REF!
C20: ELABORACION DE EXPEDIENTE TECNICO: | F20: =#REF! -> #REF! | G20: 0 | H20: 0
C22: MONTO CONTRACTUAL: | F22: =SUM(F19:F20) -> #REF!
C23: MONTO VALORIZADO : | G23: =SUM(G18:G21) -> #REF! | H23: =G23/F22 -> #REF!
C25: Descuentos:
D26: Retención por Fiel Cumplimiento (0%) | I26: 0
C29: Total a Pagar al Contratista (CONSTRUCTORA Y SERVICIOS MULTIPLES M&E AIBA-PERU): | I29: =F23-I26 -> 0
B31: Son: | C31: Setecientos Cuarenta y seis Mil dos cientos cincuenta y nueve con y 81/100 Nuevos Soles
B34: RESUMEN DE LA VALORIZACION N° 03
C35: =A2 -> Del 01 de Octubre Al 31 de Octubre del 2014
B37: COSTO DIRECTO : | G37: =G12 -> #REF!
B38: GASTOS GENERALES : | G38: =G13 -> #REF!
B39: UTILIDAD : | G39: =G14 -> #REF!
B40: SUB TOTAL : | G40: =G15 -> #REF!
B41: IGV(18%) | G41: =G16 -> #REF!
B43: VALORIZACIÓN Nº 1 : | G43: =G23 -> #REF!
B45: Descuentos:
C46: Retenciónes : | G46: 0
C47: Amortizaciones: | G47: 0
B49: Total a Pagar al Contratista (CONSORCIO HORIZONTE): | G49: =SUM(G43:G47) -> #REF!
B51: SON: | C51: =C31 -> Setecientos Cuarenta y seis Mil dos cientos cincuenta y nueve con y 81/100 Nuevos Soles
B55: RESUMEN DE LA VALORIZACION N° 01 super
C56: =A23 -> 0
B58: COSTO DIRECTO : | G58: =#REF! -> #REF!
B59: IGV(18%) | G59: =#REF! -> #REF!
B61: VALORIZACIÓN Nº 1 : | G61: =SUM(G58:G60) -> #REF!
B63: Descuentos:
C64: Retenciónes : | E64: 10% por Fiel Cumplimiento | G64: =#REF!*0.1 -> #REF!
C65: Amortizaciones: | G65: 0
B67: Total a Pagar al Contratista (CENTRO ORIENTE): | G67: =G61-G64 -> #REF!
B69: SON: | C69: Treinta y Nueve Mil Quinientos Veinte y Nueve con 90/100 Nuevos Soles

Sheet resumen 2
A1: RESUMEN DE LA VALORIZACION N° 03
A2: Del 01 de Setiembre Al 30 de Setiembre del 2014
A4: PROYECTO : | B4: =#REF! -> #REF!
A6: LUGAR : | B6: CODO DEL POZUZO - PUERTO INCA - HUANUCO.
A7: FECHA : | B7: =#REF! -> #REF!
A9: ITEM | B9: DESCRIPCION | F9: PRESUPUESTO BASE | G9: EJECUTADO
G10: MONTO | H10: %
A11: 01 | B11: EJECUCIÓN DE LA PRIMERA ETAPA DE LA OBRA “MEJORAMIENTO DE CAMINOS VECINALES, TRAMO CODO DE POZUZO – INDEPENDENCIA - NUEVO HORIZONTE, TRAMO DESVIÓ KM 1 + 500 DEL C.V. CODO DE POZUZO – NUEVO HORIZONTE A ALTO MASHOCA, TRAMO DESVIO KM 6 + 200 DEL C.V. CODO DE POZUZO – NUEVO HORIZONTE A BAJO MASHOCA, EN EL DISTRITO DE CODO DE POZUZO, PROVINCIA DE PUERTO INCA - HUANUCO” PRIMERA ETAPA | F11: =#REF! -> #REF! | G11: =#REF! -> #REF! | H11: =#REF! -> #REF!
C12: COSTO DIRECTO : | F12: =#REF! -> #REF! | G12: =SUM(G11:G11) -> #REF! | H12: =G12/F12 -> #REF!
C13: GASTOS GENERALES (5%) : | F13: =F12*0.075 -> #REF! | G13: =G12*0.075 -> #REF!
C14: UTILIDAD (5%) : | F14: =F12*0.05 -> #REF! | G14: =G12*0.05 -> #REF!
C15: SUB TOTAL : | F15: =SUM(F12:F14) -> #REF! | G15: =SUM(G12:G14) -> #REF!
C16: IGV(18%) | F16: =F15*0.18+0.01 -> #REF! | G16: =G15*0.18 -> #REF!
F17: =SUM(F15:F16)-0.01 -> #REF! | G17: =SUM(G15:G16)+0.01 -> #REF!
C18: FACTOR DE RELACION (1.00000) | F18: =F17*1 -> #REF! | G18: =G17*1 -> #REF!
C19: COSTO DE EJECUCION PRIMERA ETAPA | F19: =F18 -> #REF!
C20: ELABORACION DE EXPEDIENTE TECNICO: | F20: =#REF! -> #REF! | G20: =G18 -> #REF! | H20: 0
C22: MONTO CONTRACTUAL: | F22: =SUM(F19:F20) -> #REF!
C23: MONTO VALORIZADO : | G23: =G20 -> #REF! | H23: =G23/F22 -> #REF!
C25: Descuentos:
D26: Retención por Fiel Cumplimiento (0%) | I26: 0
C29: Total a Pagar al Contratista (CONSTRUCTORA Y SERVICIOS MULTIPLES M&E AIBA-PERU): | I29: =F23-I26 -> 0
B31: Son: | C31: Cuatrocientos Un Mil Tres cientos cuatro con y 81/100 Nuevos Soles
B34: RESUMEN DE LA VALORIZACION N° 02
C35: =A2 -> Del 01 de Setiembre Al 30 de Setiembre del 2014
B37: COSTO DIRECTO : | G37: =G12 -> #REF!
B38: GASTOS GENERALES : | G38: =G13 -> #REF!
B39: UTILIDAD : | G39: =G14 -> #REF!
B40: SUB TOTAL : | G40: =G15 -> #REF!
B41: IGV(18%) | G41: =G16 -> #REF!
B43: VALORIZACIÓN Nº 1 : | G43: =G23 -> #REF!
B45: Descuentos:
C46: Retenciónes : | G46: 0
C47: Amortizaciones: | G47: 0
B49: Total a Pagar al Contratista (CONSORCIO HORIZONTE): | G49: =SUM(G43:G47) -> #REF!
B51: SON: | C51: =C31 -> Cuatrocientos Un Mil Tres cientos cuatro con y 81/100 Nuevos Soles

Sheet Hoja2

Sheet PROGRAMADO
A1: AVANCE DE OBRA PROGRAMADO VS EJECUTADO - FISICO Y FINANCIERO
A2: Mes/Año | C2: DESCRIPCIÓN | D2: Avance Físico % | J2: Avance Financiero %
B3: Cronogramas | D3: Programado | G3: Ejecutado | J3: Programado | M3: Ejecutado
D4: Soles | E4: Unitario | F4: Acum. | G4: Soles | H4: Unitario | I4: Acum. | J4: Soles | K4: Unitario | L4: Acum. | M4: Soles | N4: Unitario | O4: Acum.
A5: 1 | B5: MAYO | C5: Val. N°01 - Cont. Princ. | D5: 21540.34 | E5: =+D5/$D$11 -> 0.010024922 | F5: =+E5 -> 0.010024922 | G5: 212361.45 | H5: =+G5/$D$11 -> 0.098833493 | I5: =H5 -> 0.098833493 | J5: 21540.34 | K5: =+J5/$D$11 -> 0.010024922 | L5: =+K5 -> 0.010024922 | M5: 212361.45 | N5: =+M5/J$11 -> 0.098833493 | O5: =N5 -> 0.098833493 | R5: 21540.34 | S5: 294239.47 | T5: 435698.42 | U5: 434098.66 | V5: 529096.96 | W5: 434005.16
A6: 2 | B6: JUNIO | C6: Val. N°02 - Cont. Princ. | D6: 294239.47 | E6: =+D6/$D$11 -> 0.13693971 | F6: =+E6+F5 -> 0.14696463 | J6: 294239.47 | K6: =+J6/$D$11 -> 0.13693971 | L6: =+K6+L5 -> 0.14696463 | R6: 21540.34
A7: 3 | B7: JULIO | C7: Val. N°03 - Cont. Princ. | D7: 435698.42 | E7: =+D7/$D$11 -> 0.20277502 | F7: =+E7+F6 -> 0.34973964 | J7: 435698.42 | K7: =+J7/$D$11 -> 0.20277502 | L7: =+K7+L6 -> 0.34973964 | R7: 294239.47
A8: 4 | B8: AGOSTO | C8: Val. N°04 - Cont. Princ. | D8: 434098.66 | E8: =+D8/$D$11 -> 0.20203048 | F8: =+E8+F7 -> 0.55177013 | J8: 434098.66 | K8: =+J8/$D$11 -> 0.20203048 | L8: =+K8+L7 -> 0.55177013 | R8: 435698.42
A9: 5 | B9: SETIEMBRE | C9: Val. N°05 - Cont. Princ. | D9: 529096.96 | E9: =+D9/$D$11 -> 0.24624291 | F9: =+E9+F8 -> 0.79801303 | J9: 529096.96 | K9: =+J9/$D$11 -> 0.24624291 | L9: =+K9+L8 -> 0.79801303 | R9: 434098.66
A10: 6 | B10: OCTUBRE | C10: Val. N°06 - Cont. Princ. | D10: 434005.15 | E10: =+D10/$D$11 -> 0.20198697 | F10: =+E10+F9 -> 1 | J10: 434005.15 | K10: =+J10/$D$11 -> 0.20198697 | L10: =+K10+L9 -> 1 | R10: 529096.96
D11: =SUM(D5:D10) -> 2148679 | G11: =SUM(G5:G10) -> 212361.45 | J11: =SUM(J5:J10) -> 2148679 | M11: =SUM(M5:M10) -> 212361.45 | R11: 434005.16
F15: 129606.67
F16: 492009.27
F17: 531275.33
F18: 656816.27
F19: 502902.7
F20: 407630.11
